Workbook

Sheet Dashboard
A1: PRACTICAL INCOME INVESTING- Trading Journal
A2: TOTAL P&L | F2: TOTAL COLLATERAL | K2: OVERALL ROC | P2: TOTAL WINS | U2: TOTAL TRADES
A3: =IFERROR(SUM('CC&CSP'!P5:'CC&CSP'!P304),0)+IFERROR(SUM('Call & Puts'!P5:'Call & Puts'!P304),0)+IFERROR(SUM('Credit Spreads'!S5:'Credit Spreads'!S304),0)+IFERROR(SUM('Buy-Writes'!S5:'Buy-Writes'!S304),0)+IFERROR(SUMIF(Stocks!R5:'Stocks'!R304,"Closed",Stocks!P5:'Stocks'!P304),0) -> 0 | F3: =IFERROR(SUM('CC&CSP'!O5:'CC&CSP'!O304),0)+IFERROR(SUM('Call & Puts'!O5:'Call & Puts'!O304),0)+IFERROR(SUM('Credit Spreads'!R5:'Credit Spreads'!R304),0)+IFERROR(SUM('Buy-Writes'!P5:'Buy-Writes'!P304),0) -> 0 | K3: =IFERROR(A5/F5,0) -> 0 | P3: =IFERROR(COUNTIF('CC&CSP'!P5:'CC&CSP'!P304,">0"),0)+IFERROR(COUNTIF('Call & Puts'!P5:'Call & Puts'!P304,">0"),0)+IFERROR(COUNTIF('Credit Spreads'!S5:'Credit Spreads'!S304,">0"),0)+IFERROR(COUNTIF('Buy-Writes'!S5:'Buy-Writes'!S304,">0"),0) -> 0 | U3: =IFERROR(COUNTA('CC&CSP'!A5:'CC&CSP'!A304),0)+IFERROR(COUNTA('Call & Puts'!A5:'Call & Puts'!A304),0)+IFERROR(COUNTA('Credit Spreads'!A5:'Credit Spreads'!A304),0)+IFERROR(COUNTA('Buy-Writes'!B5:'Buy-Writes'!B304),0) -> 0
A4: STRATEGY PERFORMANCE
A5: =IFERROR(SUM('CC&CSP'!P5:'CC&CSP'!P304),0)+IFERROR(SUM('Call & Puts'!P5:'Call & Puts'!P304),0)+IFERROR(SUM('Credit Spreads'!S5:'Credit Spreads'!S304),0)+IFERROR(SUM('Buy-Writes'!S5:'Buy-Writes'!S304),0)+IFERROR(SUMIF(Stocks!R5:'Stocks'!R304,"Closed",Stocks!P5:'Stocks'!P304),0) -> 0 | F5: =IFERROR(SUM('CC&CSP'!O5:'CC&CSP'!O304),0)+IFERROR(SUM('Call & Puts'!O5:'Call & Puts'!O304),0)+IFERROR(SUM('Credit Spreads'!R5:'Credit Spreads'!R304),0)+IFERROR(SUM('Buy-Writes'!P5:'Buy-Writes'!P304),0) -> 0
A6: STRATEGY | D6: TOTAL P&L | G6: WINS | I6: LOSSES | K6: WIN RATE | M6: AVG WIN | O6: AVG LOSS | Q6: COLLATERAL | T6: ROC % | V6: BEST TRADE | Y6: WORST TRADE
A7: CC & CSP | D7: =IFERROR(SUM('CC&CSP'!P5:'CC&CSP'!P304),0) -> 0 | G7: =IFERROR(COUNTIF('CC&CSP'!P5:'CC&CSP'!P304,">0"),0) -> 0 | I7: =IFERROR(COUNTIF('CC&CSP'!P5:'CC&CSP'!P304,"<0"),0) -> 0 | K7: =IFERROR(G7/(G7+I7),0) -> 0 | M7: =IFERROR(AVERAGEIF('CC&CSP'!P5:'CC&CSP'!P304,">0"),0) -> 0 | O7: =IFERROR(AVERAGEIF('CC&CSP'!P5:'CC&CSP'!P304,"<0"),0) -> 0 | Q7: =IFERROR(SUM('CC&CSP'!O5:'CC&CSP'!O304),0) -> 0 | T7: =IFERROR(D7/Q7,0) -> 0 | V7: =IFERROR(MAX('CC&CSP'!P5:'CC&CSP'!P304),0) -> 0 | Y7: =IFERROR(MIN('CC&CSP'!P5:'CC&CSP'!P304),0) -> 0
A8: LEAPS & Swings | D8: =IFERROR(SUM('Call & Puts'!P5:'Call & Puts'!P304),0) -> 0 | G8: =IFERROR(COUNTIF('Call & Puts'!P5:'Call & Puts'!P304,">0"),0) -> 0 | I8: =IFERROR(COUNTIF('Call & Puts'!P5:'Call & Puts'!P304,"<0"),0) -> 0 | K8: =IFERROR(G8/(G8+I8),0) -> 0 | M8: =IFERROR(AVERAGEIF('Call & Puts'!P5:'Call & Puts'!P304,">0"),0) -> 0 | O8: =IFERROR(AVERAGEIF('Call & Puts'!P5:'Call & Puts'!P304,"<0"),0) -> 0 | Q8: =IFERROR(SUM('Call & Puts'!O5:'Call & Puts'!O304),0) -> 0 | T8: =IFERROR(D8/Q8,0) -> 0 | V8: =IFERROR(MAX('Call & Puts'!P5:'Call & Puts'!P304),0) -> 0 | Y8: =IFERROR(MIN('Call & Puts'!P5:'Call & Puts'!P304),0) -> 0
A9: Credit Spreads | D9: =IFERROR(SUM('Credit Spreads'!S5:'Credit Spreads'!S304),0) -> 0 | G9: =IFERROR(COUNTIF('Credit Spreads'!S5:'Credit Spreads'!S304,">0"),0) -> 0 | I9: =IFERROR(COUNTIF('Credit Spreads'!S5:'Credit Spreads'!S304,"<0"),0) -> 0 | K9: =IFERROR(G9/(G9+I9),0) -> 0 | M9: =IFERROR(AVERAGEIF('Credit Spreads'!S5:'Credit Spreads'!S304,">0"),0) -> 0 | O9: =IFERROR(AVERAGEIF('Credit Spreads'!S5:'Credit Spreads'!S304,"<0"),0) -> 0 | Q9: =IFERROR(SUM('Credit Spreads'!R5:'Credit Spreads'!R304),0) -> 0 | T9: =IFERROR(D9/Q9,0) -> 0 | V9: =IFERROR(MAX('Credit Spreads'!S5:'Credit Spreads'!S304),0) -> 0 | Y9: =IFERROR(MIN('Credit Spreads'!S5:'Credit Spreads'!S304),0) -> 0
A10: Buy-Writes | D10: =IFERROR(SUM('Buy-Writes'!S5:'Buy-Writes'!S304),0) -> 0 | G10: =IFERROR(COUNTIF('Buy-Writes'!S5:'Buy-Writes'!S304,">0"),0) -> 0 | I10: =IFERROR(COUNTIF('Buy-Writes'!S5:'Buy-Writes'!S304,"<0"),0) -> 0 | K10: =IFERROR(G10/(G10+I10),0) -> 0 | M10: =IFERROR(AVERAGEIF('Buy-Writes'!S5:'Buy-Writes'!S304,">0"),0) -> 0 | O10: =IFERROR(AVERAGEIF('Buy-Writes'!S5:'Buy-Writes'!S304,"<0"),0) -> 0 | Q10: =IFERROR(SUM('Buy-Writes'!P5:'Buy-Writes'!P304),0) -> 0 | T10: =IFERROR(D10/Q10,0) -> 0 | V10: =IFERROR(MAX('Buy-Writes'!S5:'Buy-Writes'!S304),0) -> 0 | Y10: =IFERROR(MIN('Buy-Writes'!S5:'Buy-Writes'!S304),0) -> 0
A11: Stocks | D11: =IFERROR(SUM(Stocks!P5:'Stocks'!P304),0) -> 0 | G11: =IFERROR(COUNTIF(Stocks!P5:'Stocks'!P304,">0"),0) -> 0 | I11: =IFERROR(COUNTIF(Stocks!P5:'Stocks'!P304,"<0"),0) -> 0 | K11: =IFERROR(G11/(G11+I11),0) -> 0 | M11: =IFERROR(AVERAGEIF(Stocks!P5:'Stocks'!P304,">0"),0) -> 0 | O11: =IFERROR(AVERAGEIF(Stocks!P5:'Stocks'!P304,"<0"),0) -> 0 | Q11: 0 | T11: =IFERROR(D11/Q11,0) -> 0 | V11: =IFERROR(MAX(Stocks!P5:'Stocks'!P304),0) -> 0 | Y11: =IFERROR(MIN(Stocks!P5:'Stocks'!P304),0) -> 0
A13: MONTHLY BREAKDOWN
A14: MONTH | C14: CC & CSP | G14: LEAPS & SWINGS | K14: CREDIT SPREADS | O14: BUY-WRITES | S14: STOCKS | W14: TOTAL
A15: Jan 2026 | C15: =IFERROR(SUMPRODUCT((MONTH('CC&CSP'!E5:'CC&CSP'!E304)=1)*(YEAR('CC&CSP'!E5:'CC&CSP'!E304)=2026)*('CC&CSP'!P5:'CC&CSP'!P304)),0) -> 0 | G15: =IFERROR(SUMPRODUCT((MONTH('Call & Puts'!E5:'Call & Puts'!E304)=1)*(YEAR('Call & Puts'!E5:'Call & Puts'!E304)=2026)*('Call & Puts'!P5:'Call & Puts'!P304)),0) -> 0 | K15: =IFERROR(SUMPRODUCT((MONTH('Credit Spreads'!E5:'Credit Spreads'!E304)=1)*(YEAR('Credit Spreads'!E5:'Credit Spreads'!E304)=2026)*('Credit Spreads'!S5:'Credit Spreads'!S304)),0) -> 0 | O15: =IFERROR(SUMPRODUCT((MONTH('Buy-Writes'!D5:'Buy-Writes'!D304)=1)*(YEAR('Buy-Writes'!D5:'Buy-Writes'!D304)=2026)*('Buy-Writes'!S5:'Buy-Writes'!S304)),0) -> 0 | S15: =IFERROR(SUMPRODUCT((MONTH(Stocks!M5:'Stocks'!M304)=1)*(YEAR(Stocks!M5:'Stocks'!M304)=2026)*(Stocks!P5:'Stocks'!P304)),0) -> 0 | W15: =IFERROR(C15+G15+K15+O15+S15,0) -> 0
A16: Feb 2026 | C16: =IFERROR(SUMPRODUCT((MONTH('CC&CSP'!E5:'CC&CSP'!E304)=2)*(YEAR('CC&CSP'!E5:'CC&CSP'!E304)=2026)*('CC&CSP'!P5:'CC&CSP'!P304)),0) -> 0 | G16: =IFERROR(SUMPRODUCT((MONTH('Call & Puts'!E5:'Call & Puts'!E304)=2)*(YEAR('Call & Puts'!E5:'Call & Puts'!E304)=2026)*('Call & Puts'!P5:'Call & Puts'!P304)),0) -> 0 | K16: =IFERROR(SUMPRODUCT((MONTH('Credit Spreads'!E5:'Credit Spreads'!E304)=2)*(YEAR('Credit Spreads'!E5:'Credit Spreads'!E304)=2026)*('Credit Spreads'!S5:'Credit Spreads'!S304)),0) -> 0 | O16: =IFERROR(SUMPRODUCT((MONTH('Buy-Writes'!D5:'Buy-Writes'!D304)=2)*(YEAR('Buy-Writes'!D5:'Buy-Writes'!D304)=2026)*('Buy-Writes'!S5:'Buy-Writes'!S304)),0) -> 0 | S16: =IFERROR(SUMPRODUCT((MONTH(Stocks!M5:'Stocks'!M304)=2)*(YEAR(Stocks!M5:'Stocks'!M304)=2026)*(Stocks!P5:'Stocks'!P304)),0) -> 0 | W16: =IFERROR(C16+G16+K16+O16+S16,0) -> 0
A17: Mar 2026 | C17: =IFERROR(SUMPRODUCT((MONTH('CC&CSP'!E5:'CC&CSP'!E304)=3)*(YEAR('CC&CSP'!E5:'CC&CSP'!E304)=2026)*('CC&CSP'!P5:'CC&CSP'!P304)),0) -> 0 | G17: =IFERROR(SUMPRODUCT((MONTH('Call & Puts'!E5:'Call & Puts'!E304)=3)*(YEAR('Call & Puts'!E5:'Call & Puts'!E304)=2026)*('Call & Puts'!P5:'Call & Puts'!P304)),0) -> 0 | K17: =IFERROR(SUMPRODUCT((MONTH('Credit Spreads'!E5:'Credit Spreads'!E304)=3)*(YEAR('Credit Spreads'!E5:'Credit Spreads'!E304)=2026)*('Credit Spreads'!S5:'Credit Spreads'!S304)),0) -> 0 | O17: =IFERROR(SUMPRODUCT((MONTH('Buy-Writes'!D5:'Buy-Writes'!D304)=3)*(YEAR('Buy-Writes'!D5:'Buy-Writes'!D304)=2026)*('Buy-Writes'!S5:'Buy-Writes'!S304)),0) -> 0 | S17: =IFERROR(SUMPRODUCT((MONTH(Stocks!M5:'Stocks'!M304)=3)*(YEAR(Stocks!M5:'Stocks'!M304)=2026)*(Stocks!P5:'Stocks'!P304)),0) -> 0 | W17: =IFERROR(C17+G17+K17+O17+S17,0) -> 0
A18: Apr 2026 | C18: =IFERROR(SUMPRODUCT((MONTH('CC&CSP'!E5:'CC&CSP'!E304)=4)*(YEAR('CC&CSP'!E5:'CC&CSP'!E304)=2026)*('CC&CSP'!P5:'CC&CSP'!P304)),0) -> 0 | G18: =IFERROR(SUMPRODUCT((MONTH('Call & Puts'!E5:'Call & Puts'!E304)=4)*(YEAR('Call & Puts'!E5:'Call & Puts'!E304)=2026)*('Call & Puts'!P5:'Call & Puts'!P304)),0) -> 0 | K18: =IFERROR(SUMPRODUCT((MONTH('Credit Spreads'!E5:'Credit Spreads'!E304)=4)*(YEAR('Credit Spreads'!E5:'Credit Spreads'!E304)=2026)*('Credit Spreads'!S5:'Credit Spreads'!S304)),0) -> 0 | O18: =IFERROR(SUMPRODUCT((MONTH('Buy-Writes'!D5:'Buy-Writes'!D304)=4)*(YEAR('Buy-Writes'!D5:'Buy-Writes'!D304)=2026)*('Buy-Writes'!S5:'Buy-Writes'!S304)),0) -> 0 | S18: =IFERROR(SUMPRODUCT((MONTH(Stocks!M5:'Stocks'!M304)=4)*(YEAR(Stocks!M5:'Stocks'!M304)=2026)*(Stocks!P5:'Stocks'!P304)),0) -> 0 | W18: =IFERROR(C18+G18+K18+O18+S18,0) -> 0
A19: May 2026 | C19: =IFERROR(SUMPRODUCT((MONTH('CC&CSP'!E5:'CC&CSP'!E304)=5)*(YEAR('CC&CSP'!E5:'CC&CSP'!E304)=2026)*('CC&CSP'!P5:'CC&CSP'!P304)),0) -> 0 | G19: =IFERROR(SUMPRODUCT((MONTH('Call & Puts'!E5:'Call & Puts'!E304)=5)*(YEAR('Call & Puts'!E5:'Call & Puts'!E304)=2026)*('Call & Puts'!P5:'Call & Puts'!P304)),0) -> 0 | K19: =IFERROR(SUMPRODUCT((MONTH('Credit Spreads'!E5:'Credit Spreads'!E304)=5)*(YEAR('Credit Spreads'!E5:'Credit Spreads'!E304)=2026)*('Credit Spreads'!S5:'Credit Spreads'!S304)),0) -> 0 | O19: =IFERROR(SUMPRODUCT((MONTH('Buy-Writes'!D5:'Buy-Writes'!D304)=5)*(YEAR('Buy-Writes'!D5:'Buy-Writes'!D304)=2026)*('Buy-Writes'!S5:'Buy-Writes'!S304)),0) -> 0 | S19: =IFERROR(SUMPRODUCT((MONTH(Stocks!M5:'Stocks'!M304)=5)*(YEAR(Stocks!M5:'Stocks'!M304)=2026)*(Stocks!P5:'Stocks'!P304)),0) -> 0 | W19: =IFERROR(C19+G19+K19+O19+S19,0) -> 0
A20: Jun 2026 | C20: =IFERROR(SUMPRODUCT((MONTH('CC&CSP'!E5:'CC&CSP'!E304)=6)*(YEAR('CC&CSP'!E5:'CC&CSP'!E304)=2026)*('CC&CSP'!P5:'CC&CSP'!P304)),0) -> 0 | G20: =IFERROR(SUMPRODUCT((MONTH('Call & Puts'!E5:'Call & Puts'!E304)=6)*(YEAR('Call & Puts'!E5:'Call & Puts'!E304)=2026)*('Call & Puts'!P5:'Call & Puts'!P304)),0) -> 0 | K20: =IFERROR(SUMPRODUCT((MONTH('Credit Spreads'!E5:'Credit Spreads'!E304)=6)*(YEAR('Credit Spreads'!E5:'Credit Spreads'!E304)=2026)*('Credit Spreads'!S5:'Credit Spreads'!S304)),0) -> 0 | O20: =IFERROR(SUMPRODUCT((MONTH('Buy-Writes'!D5:'Buy-Writes'!D304)=6)*(YEAR('Buy-Writes'!D5:'Buy-Writes'!D304)=2026)*('Buy-Writes'!S5:'Buy-Writes'!S304)),0) -> 0 | S20: =IFERROR(SUMPRODUCT((MONTH(Stocks!M5:'Stocks'!M304)=6)*(YEAR(Stocks!M5:'Stocks'!M304)=2026)*(Stocks!P5:'Stocks'!P304)),0) -> 0 | W20: =IFERROR(C20+G20+K20+O20+S20,0) -> 0
A21: Jul 2026 | C21: =IFERROR(SUMPRODUCT((MONTH('CC&CSP'!E5:'CC&CSP'!E304)=7)*(YEAR('CC&CSP'!E5:'CC&CSP'!E304)=2026)*('CC&CSP'!P5:'CC&CSP'!P304)),0) -> 0 | G21: =IFERROR(SUMPRODUCT((MONTH('Call & Puts'!E5:'Call & Puts'!E304)=7)*(YEAR('Call & Puts'!E5:'Call & Puts'!E304)=2026)*('Call & Puts'!P5:'Call & Puts'!P304)),0) -> 0 | K21: =IFERROR(SUMPRODUCT((MONTH('Credit Spreads'!E5:'Credit Spreads'!E304)=7)*(YEAR('Credit Spreads'!E5:'Credit Spreads'!E304)=2026)*('Credit Spreads'!S5:'Credit Spreads'!S304)),0) -> 0 | O21: =IFERROR(SUMPRODUCT((MONTH('Buy-Writes'!D5:'Buy-Writes'!D304)=7)*(YEAR('Buy-Writes'!D5:'Buy-Writes'!D304)=2026)*('Buy-Writes'!S5:'Buy-Writes'!S304)),0) -> 0 | S21: =IFERROR(SUMPRODUCT((MONTH(Stocks!M5:'Stocks'!M304)=7)*(YEAR(Stocks!M5:'Stocks'!M304)=2026)*(Stocks!P5:'Stocks'!P304)),0) -> 0 | W21: =IFERROR(C21+G21+K21+O21+S21,0) -> 0
A22: Aug 2026 | C22: =IFERROR(SUMPRODUCT((MONTH('CC&CSP'!E5:'CC&CSP'!E304)=8)*(YEAR('CC&CSP'!E5:'CC&CSP'!E304)=2026)*('CC&CSP'!P5:'CC&CSP'!P304)),0) -> 0 | G22: =IFERROR(SUMPRODUCT((MONTH('Call & Puts'!E5:'Call & Puts'!E304)=8)*(YEAR('Call & Puts'!E5:'Call & Puts'!E304)=2026)*('Call & Puts'!P5:'Call & Puts'!P304)),0) -> 0 | K22: =IFERROR(SUMPRODUCT((MONTH('Credit Spreads'!E5:'Credit Spreads'!E304)=8)*(YEAR('Credit Spreads'!E5:'Credit Spreads'!E304)=2026)*('Credit Spreads'!S5:'Credit Spreads'!S304)),0) -> 0 | O22: =IFERROR(SUMPRODUCT((MONTH('Buy-Writes'!D5:'Buy-Writes'!D304)=8)*(YEAR('Buy-Writes'!D5:'Buy-Writes'!D304)=2026)*('Buy-Writes'!S5:'Buy-Writes'!S304)),0) -> 0 | S22: =IFERROR(SUMPRODUCT((MONTH(Stocks!M5:'Stocks'!M304)=8)*(YEAR(Stocks!M5:'Stocks'!M304)=2026)*(Stocks!P5:'Stocks'!P304)),0) -> 0 | W22: =IFERROR(C22+G22+K22+O22+S22,0) -> 0
A23: Sep 2026 | C23: =IFERROR(SUMPRODUCT((MONTH('CC&CSP'!E5:'CC&CSP'!E304)=9)*(YEAR('CC&CSP'!E5:'CC&CSP'!E304)=2026)*('CC&CSP'!P5:'CC&CSP'!P304)),0) -> 0 | G23: =IFERROR(SUMPRODUCT((MONTH('Call & Puts'!E5:'Call & Puts'!E304)=9)*(YEAR('Call & Puts'!E5:'Call & Puts'!E304)=2026)*('Call & Puts'!P5:'Call & Puts'!P304)),0) -> 0 | K23: =IFERROR(SUMPRODUCT((MONTH('Credit Spreads'!E5:'Credit Spreads'!E304)=9)*(YEAR('Credit Spreads'!E5:'Credit Spreads'!E304)=2026)*('Credit Spreads'!S5:'Credit Spreads'!S304)),0) -> 0 | O23: =IFERROR(SUMPRODUCT((MONTH('Buy-Writes'!D5:'Buy-Writes'!D304)=9)*(YEAR('Buy-Writes'!D5:'Buy-Writes'!D304)=2026)*('Buy-Writes'!S5:'Buy-Writes'!S304)),0) -> 0 | S23: =IFERROR(SUMPRODUCT((MONTH(Stocks!M5:'Stocks'!M304)=9)*(YEAR(Stocks!M5:'Stocks'!M304)=2026)*(Stocks!P5:'Stocks'!P304)),0) -> 0 | W23: =IFERROR(C23+G23+K23+O23+S23,0) -> 0
A24: Oct 2026 | C24: =IFERROR(SUMPRODUCT((MONTH('CC&CSP'!E5:'CC&CSP'!E304)=10)*(YEAR('CC&CSP'!E5:'CC&CSP'!E304)=2026)*('CC&CSP'!P5:'CC&CSP'!P304)),0) -> 0 | G24: =IFERROR(SUMPRODUCT((MONTH('Call & Puts'!E5:'Call & Puts'!E304)=10)*(YEAR('Call & Puts'!E5:'Call & Puts'!E304)=2026)*('Call & Puts'!P5:'Call & Puts'!P304)),0) -> 0 | K24: =IFERROR(SUMPRODUCT((MONTH('Credit Spreads'!E5:'Credit Spreads'!E304)=10)*(YEAR('Credit Spreads'!E5:'Credit Spreads'!E304)=2026)*('Credit Spreads'!S5:'Credit Spreads'!S304)),0) -> 0 | O24: =IFERROR(SUMPRODUCT((MONTH('Buy-Writes'!D5:'Buy-Writes'!D304)=10)*(YEAR('Buy-Writes'!D5:'Buy-Writes'!D304)=2026)*('Buy-Writes'!S5:'Buy-Writes'!S304)),0) -> 0 | S24: =IFERROR(SUMPRODUCT((MONTH(Stocks!M5:'Stocks'!M304)=10)*(YEAR(Stocks!M5:'Stocks'!M304)=2026)*(Stocks!P5:'Stocks'!P304)),0) -> 0 | W24: =IFERROR(C24+G24+K24+O24+S24,0) -> 0
A25: Nov 2026 | C25: =IFERROR(SUMPRODUCT((MONTH('CC&CSP'!E5:'CC&CSP'!E304)=11)*(YEAR('CC&CSP'!E5:'CC&CSP'!E304)=2026)*('CC&CSP'!P5:'CC&CSP'!P304)),0) -> 0 | G25: =IFERROR(SUMPRODUCT((MONTH('Call & Puts'!E5:'Call & Puts'!E304)=11)*(YEAR('Call & Puts'!E5:'Call & Puts'!E304)=2026)*('Call & Puts'!P5:'Call & Puts'!P304)),0) -> 0 | K25: =IFERROR(SUMPRODUCT((MONTH('Credit Spreads'!E5:'Credit Spreads'!E304)=11)*(YEAR('Credit Spreads'!E5:'Credit Spreads'!E304)=2026)*('Credit Spreads'!S5:'Credit Spreads'!S304)),0) -> 0 | O25: =IFERROR(SUMPRODUCT((MONTH('Buy-Writes'!D5:'Buy-Writes'!D304)=11)*(YEAR('Buy-Writes'!D5:'Buy-Writes'!D304)=2026)*('Buy-Writes'!S5:'Buy-Writes'!S304)),0) -> 0 | S25: =IFERROR(SUMPRODUCT((MONTH(Stocks!M5:'Stocks'!M304)=11)*(YEAR(Stocks!M5:'Stocks'!M304)=2026)*(Stocks!P5:'Stocks'!P304)),0) -> 0 | W25: =IFERROR(C25+G25+K25+O25+S25,0) -> 0
A26: Dec 2026 | C26: =IFERROR(SUMPRODUCT((MONTH('CC&CSP'!E5:'CC&CSP'!E304)=12)*(YEAR('CC&CSP'!E5:'CC&CSP'!E304)=2026)*('CC&CSP'!P5:'CC&CSP'!P304)),0) -> 0 | G26: =IFERROR(SUMPRODUCT((MONTH('Call & Puts'!E5:'Call & Puts'!E304)=12)*(YEAR('Call & Puts'!E5:'Call & Puts'!E304)=2026)*('Call & Puts'!P5:'Call & Puts'!P304)),0) -> 0 | K26: =IFERROR(SUMPRODUCT((MONTH('Credit Spreads'!E5:'Credit Spreads'!E304)=12)*(YEAR('Credit Spreads'!E5:'Credit Spreads'!E304)=2026)*('Credit Spreads'!S5:'Credit Spreads'!S304)),0) -> 0 | O26: =IFERROR(SUMPRODUCT((MONTH('Buy-Writes'!D5:'Buy-Writes'!D304)=12)*(YEAR('Buy-Writes'!D5:'Buy-Writes'!D304)=2026)*('Buy-Writes'!S5:'Buy-Writes'!S304)),0) -> 0 | S26: =IFERROR(SUMPRODUCT((MONTH(Stocks!M5:'Stocks'!M304)=12)*(YEAR(Stocks!M5:'Stocks'!M304)=2026)*(Stocks!P5:'Stocks'!P304)),0) -> 0 | W26: =IFERROR(C26+G26+K26+O26+S26,0) -> 0

Sheet CC&CSP
A1: Practical Income Investing - Covered Calls & Cash Secured Puts
A2: TOTAL PROFIT | E2: =SUM(P5:P304) -> 0 | J2: COLLATERAL USED | N2: =IFERROR(SUMIF(E5:E304,"<>",O5:O304),0) -> 0 | P2: TOTAL ROC | S2: =IFERROR(E2/N2,0) -> 0 | V2: Locked Cells | W2: Manually Enter
A3: WINS | C3: =COUNTIF(P5:P304,">0") -> 0 | D3: LOSSES | F3: =COUNTIF(P5:P304,"<0") -> 0 | H3: WIN RATE | K3: =IFERROR(C3/(C3+F3),0) -> 0 | M3: AVG WIN | O3: =IFERROR(AVERAGEIF(P5:P304,">0"),0) -> 0 | Q3: AVG LOSS | S3: =IFERROR(AVERAGEIF(P5:P304,"<0"),0) -> 0 | V3: Cell Use Guide
A4: TYPE | B4: STRATEGY | C4: OPEN DATE | D4: EXP DATE | E4: CLOSE DATE | F4: TICKER | G4: BROKERAGE | H4: TODAY'S PRICE | I4: STRIKE $ | J4: BREACH ALERT | K4: QTY | L4: PREMIUM $ | M4: CLOSE $ | N4: CC COLLATERAL | O4: COLLATERAL $ | P4: P / L | Q4: #DAYS | R4: PROFIT PER DAY | S4: RETURN ON CAPITAL | T4: MONTHLY RETURN % | U4: ANNUAL RETURN % | V4: NOTES
J5: =IF(OR(A5="",E5<>""),"",IFERROR(H5-I5,"")) | P5: =IF(A5="","",IF(A5="Sell",IF(M5="","", (L5-M5)*K5*100),IF(A5="Assigned",IF(L5="","",L5*K5*100),IF(A5="Buy",IF(M5="","",(M5-L5)*K5*100),"")))) | Q5: =IF(E5="","",IF(E5-C5<1,1,E5-C5)) | R5: =IFERROR(IF(P5="","",P5/Q5),"") | S5: =IF(E5="","",IFERROR(IF(N5="",P5/O5,P5/N5),"")) | T5: =IFERROR(IF(S5="","",S5/Q5*365/12),"") | U5: =IFERROR(IF(S5="","",S5/Q5*365),"")
J6: =IF(OR(A6="",E6<>""),"",IFERROR(H6-I6,"")) | P6: =IF(A6="","",IF(A6="Sell",IF(M6="","", (L6-M6)*K6*100),IF(A6="Assigned",IF(L6="","",L6*K6*100),IF(A6="Buy",IF(M6="","",(M6-L6)*K6*100),"")))) | Q6: =IF(E6="","",IF(E6-C6<1,1,E6-C6)) | R6: =IFERROR(IF(P6="","",P6/Q6),"") | S6: =IF(E6="","",IFERROR(IF(N6="",P6/O6,P6/N6),"")) | T6: =IFERROR(IF(S6="","",S6/Q6*365/12),"") | U6: =IFERROR(IF(S6="","",S6/Q6*365),"")
J7: =IF(OR(A7="",E7<>""),"",IFERROR(H7-I7,"")) | P7: =IF(A7="","",IF(A7="Sell",IF(M7="","", (L7-M7)*K7*100),IF(A7="Assigned",IF(L7="","",L7*K7*100),IF(A7="Buy",IF(M7="","",(M7-L7)*K7*100),"")))) | Q7: =IF(E7="","",IF(E7-C7<1,1,E7-C7)) | R7: =IFERROR(IF(P7="","",P7/Q7),"") | S7: =IF(E7="","",IFERROR(IF(N7="",P7/O7,P7/N7),"")) | T7: =IFERROR(IF(S7="","",S7/Q7*365/12),"") | U7: =IFERROR(IF(S7="","",S7/Q7*365),"")
H8: =IFERROR(__xludf.DUMMYFUNCTION("IF(F8="""","""",IFERROR(GOOGLEFINANCE(UPPER(F8),""price""),""""))"),"") | J8: =IF(OR(A8="",E8<>""),"",IFERROR(H8-I8,"")) | P8: =IF(A8="","",IF(A8="Sell",IF(M8="","", (L8-M8)*K8*100),IF(A8="Assigned",IF(L8="","",L8*K8*100),IF(A8="Buy",IF(M8="","",(M8-L8)*K8*100),"")))) | Q8: =IF(E8="","",IF(E8-C8<1,1,E8-C8)) | R8: =IFERROR(IF(P8="","",P8/Q8),"") | S8: =IF(E8="","",IFERROR(IF(N8="",P8/O8,P8/N8),"")) | T8: =IFERROR(IF(S8="","",S8/Q8*365/12),"") | U8: =IFERROR(IF(S8="","",S8/Q8*365),"")
H9: =IFERROR(__xludf.DUMMYFUNCTION("IF(F9="""","""",IFERROR(GOOGLEFINANCE(UPPER(F9),""price""),""""))"),"") | J9: =IF(OR(A9="",E9<>""),"",IFERROR(H9-I9,"")) | P9: =IF(A9="","",IF(A9="Sell",IF(M9="","", (L9-M9)*K9*100),IF(A9="Assigned",IF(L9="","",L9*K9*100),IF(A9="Buy",IF(M9="","",(M9-L9)*K9*100),"")))) | Q9: =IF(E9="","",IF(E9-C9<1,1,E9-C9)) | R9: =IFERROR(IF(P9="","",P9/Q9),"") | S9: =IF(E9="","",IFERROR(IF(N9="",P9/O9,P9/N9),"")) | T9: =IFERROR(IF(S9="","",S9/Q9*365/12),"") | U9: =IFERROR(IF(S9="","",S9/Q9*365),"")
H10: =IFERROR(__xludf.DUMMYFUNCTION("IF(F10="""","""",IFERROR(GOOGLEFINANCE(UPPER(F10),""price""),""""))"),"") | J10: =IF(OR(A10="",E10<>""),"",IFERROR(H10-I10,"")) | P10: =IF(A10="","",IF(A10="Sell",IF(M10="","", (L10-M10)*K10*100),IF(A10="Assigned",IF(L10="","",L10*K10*100),IF(A10="Buy",IF(M10="","",(M10-L10)*K10*100),"")))) | Q10: =IF(E10="","",IF(E10-C10<1,1,E10-C10)) | R10: =IFERROR(IF(P10="","",P10/Q10),"") | S10: =IF(E10="","",IFERROR(IF(N10="",P10/O10,P10/N10),"")) | T10: =IFERROR(IF(S10="","",S10/Q10*365/12),"") | U10: =IFERROR(IF(S10="","",S10/Q10*365),"")
H11: =IFERROR(__xludf.DUMMYFUNCTION("IF(F11="""","""",IFERROR(GOOGLEFINANCE(UPPER(F11),""price""),""""))"),"") | J11: =IF(OR(A11="",E11<>""),"",IFERROR(H11-I11,"")) | P11: =IF(A11="","",IF(A11="Sell",IF(M11="","", (L11-M11)*K11*100),IF(A11="Assigned",IF(L11="","",L11*K11*100),IF(A11="Buy",IF(M11="","",(M11-L11)*K11*100),"")))) | Q11: =IF(E11="","",IF(E11-C11<1,1,E11-C11)) | R11: =IFERROR(IF(P11="","",P11/Q11),"") | S11: =IF(E11="","",IFERROR(IF(N11="",P11/O11,P11/N11),"")) | T11: =IFERROR(IF(S11="","",S11/Q11*365/12),"") | U11: =IFERROR(IF(S11="","",S11/Q11*365),"")
H12: =IFERROR(__xludf.DUMMYFUNCTION("IF(F12="""","""",IFERROR(GOOGLEFINANCE(UPPER(F12),""price""),""""))"),"") | J12: =IF(OR(A12="",E12<>""),"",IFERROR(H12-I12,"")) | P12: =IF(A12="","",IF(A12="Sell",IF(M12="","", (L12-M12)*K12*100),IF(A12="Assigned",IF(L12="","",L12*K12*100),IF(A12="Buy",IF(M12="","",(M12-L12)*K12*100),"")))) | Q12: =IF(E12="","",IF(E12-C12<1,1,E12-C12)) | R12: =IFERROR(IF(P12="","",P12/Q12),"") | S12: =IF(E12="","",IFERROR(IF(N12="",P12/O12,P12/N12),"")) | T12: =IFERROR(IF(S12="","",S12/Q12*365/12),"") | U12: =IFERROR(IF(S12="","",S12/Q12*365),"")
H13: =IFERROR(__xludf.DUMMYFUNCTION("IF(F13="""","""",IFERROR(GOOGLEFINANCE(UPPER(F13),""price""),""""))"),"") | J13: =IF(OR(A13="",E13<>""),"",IFERROR(H13-I13,"")) | P13: =IF(A13="","",IF(A13="Sell",IF(M13="","", (L13-M13)*K13*100),IF(A13="Assigned",IF(L13="","",L13*K13*100),IF(A13="Buy",IF(M13="","",(M13-L13)*K13*100),"")))) | Q13: =IF(E13="","",IF(E13-C13<1,1,E13-C13)) | R13: =IFERROR(IF(P13="","",P13/Q13),"") | S13: =IF(E13="","",IFERROR(IF(N13="",P13/O13,P13/N13),"")) | T13: =IFERROR(IF(S13="","",S13/Q13*365/12),"") | U13: =IFERROR(IF(S13="","",S13/Q13*365),"")
H14: =IFERROR(__xludf.DUMMYFUNCTION("IF(F14="""","""",IFERROR(GOOGLEFINANCE(UPPER(F14),""price""),""""))"),"") | J14: =IF(OR(A14="",E14<>""),"",IFERROR(H14-I14,"")) | P14: =IF(A14="","",IF(A14="Sell",IF(M14="","", (L14-M14)*K14*100),IF(A14="Assigned",IF(L14="","",L14*K14*100),IF(A14="Buy",IF(M14="","",(M14-L14)*K14*100),"")))) | Q14: =IF(E14="","",IF(E14-C14<1,1,E14-C14)) | R14: =IFERROR(IF(P14="","",P14/Q14),"") | S14: =IF(E14="","",IFERROR(IF(N14="",P14/O14,P14/N14),"")) | T14: =IFERROR(IF(S14="","",S14/Q14*365/12),"") | U14: =IFERROR(IF(S14="","",S14/Q14*365),"")
H15: =IFERROR(__xludf.DUMMYFUNCTION("IF(F15="""","""",IFERROR(GOOGLEFINANCE(UPPER(F15),""price""),""""))"),"") | J15: =IF(OR(A15="",E15<>""),"",IFERROR(H15-I15,"")) | P15: =IF(A15="","",IF(A15="Sell",IF(M15="","", (L15-M15)*K15*100),IF(A15="Assigned",IF(L15="","",L15*K15*100),IF(A15="Buy",IF(M15="","",(M15-L15)*K15*100),"")))) | Q15: =IF(E15="","",IF(E15-C15<1,1,E15-C15)) | R15: =IFERROR(IF(P15="","",P15/Q15),"") | S15: =IF(E15="","",IFERROR(IF(N15="",P15/O15,P15/N15),"")) | T15: =IFERROR(IF(S15="","",S15/Q15*365/12),"") | U15: =IFERROR(IF(S15="","",S15/Q15*365),"")
H16: =IFERROR(__xludf.DUMMYFUNCTION("IF(F16="""","""",IFERROR(GOOGLEFINANCE(UPPER(F16),""price""),""""))"),"") | J16: =IF(OR(A16="",E16<>""),"",IFERROR(H16-I16,"")) | P16: =IF(A16="","",IF(A16="Sell",IF(M16="","", (L16-M16)*K16*100),IF(A16="Assigned",IF(L16="","",L16*K16*100),IF(A16="Buy",IF(M16="","",(M16-L16)*K16*100),"")))) | Q16: =IF(E16="","",IF(E16-C16<1,1,E16-C16)) | R16: =IFERROR(IF(P16="","",P16/Q16),"") | S16: =IF(E16="","",IFERROR(IF(N16="",P16/O16,P16/N16),"")) | T16: =IFERROR(IF(S16="","",S16/Q16*365/12),"") | U16: =IFERROR(IF(S16="","",S16/Q16*365),"")
H17: =IFERROR(__xludf.DUMMYFUNCTION("IF(F17="""","""",IFERROR(GOOGLEFINANCE(UPPER(F17),""price""),""""))"),"") | J17: =IF(OR(A17="",E17<>""),"",IFERROR(H17-I17,"")) | P17: =IF(A17="","",IF(A17="Sell",IF(M17="","", (L17-M17)*K17*100),IF(A17="Assigned",IF(L17="","",L17*K17*100),IF(A17="Buy",IF(M17="","",(M17-L17)*K17*100),"")))) | Q17: =IF(E17="","",IF(E17-C17<1,1,E17-C17)) | R17: =IFERROR(IF(P17="","",P17/Q17),"") | S17: =IF(E17="","",IFERROR(IF(N17="",P17/O17,P17/N17),"")) | T17: =IFERROR(IF(S17="","",S17/Q17*365/12),"") | U17: =IFERROR(IF(S17="","",S17/Q17*365),"")
H18: =IFERROR(__xludf.DUMMYFUNCTION("IF(F18="""","""",IFERROR(GOOGLEFINANCE(UPPER(F18),""price""),""""))"),"") | J18: =IF(OR(A18="",E18<>""),"",IFERROR(H18-I18,"")) | P18: =IF(A18="","",IF(A18="Sell",IF(M18="","", (L18-M18)*K18*100),IF(A18="Assigned",IF(L18="","",L18*K18*100),IF(A18="Buy",IF(M18="","",(M18-L18)*K18*100),"")))) | Q18: =IF(E18="","",IF(E18-C18<1,1,E18-C18)) | R18: =IFERROR(IF(P18="","",P18/Q18),"") | S18: =IF(E18="","",IFERROR(IF(N18="",P18/O18,P18/N18),"")) | T18: =IFERROR(IF(S18="","",S18/Q18*365/12),"") | U18: =IFERROR(IF(S18="","",S18/Q18*365),"")
H19: =IFERROR(__xludf.DUMMYFUNCTION("IF(F19="""","""",IFERROR(GOOGLEFINANCE(UPPER(F19),""price""),""""))"),"") | J19: =IF(OR(A19="",E19<>""),"",IFERROR(H19-I19,"")) | P19: =IF(A19="","",IF(A19="Sell",IF(M19="","", (L19-M19)*K19*100),IF(A19="Assigned",IF(L19="","",L19*K19*100),IF(A19="Buy",IF(M19="","",(M19-L19)*K19*100),"")))) | Q19: =IF(E19="","",IF(E19-C19<1,1,E19-C19)) | R19: =IFERROR(IF(P19="","",P19/Q19),"") | S19: =IF(E19="","",IFERROR(IF(N19="",P19/O19,P19/N19),"")) | T19: =IFERROR(IF(S19="","",S19/Q19*365/12),"") | U19: =IFERROR(IF(S19="","",S19/Q19*365),"")
H20: =IFERROR(__xludf.DUMMYFUNCTION("IF(F20="""","""",IFERROR(GOOGLEFINANCE(UPPER(F20),""price""),""""))"),"") | J20: =IF(OR(A20="",E20<>""),"",IFERROR(H20-I20,"")) | P20: =IF(A20="","",IF(A20="Sell",IF(M20="","", (L20-M20)*K20*100),IF(A20="Assigned",IF(L20="","",L20*K20*100),IF(A20="Buy",IF(M20="","",(M20-L20)*K20*100),"")))) | Q20: =IF(E20="","",IF(E20-C20<1,1,E20-C20)) | R20: =IFERROR(IF(P20="","",P20/Q20),"") | S20: =IF(E20="","",IFERROR(IF(N20="",P20/O20,P20/N20),"")) | T20: =IFERROR(IF(S20="","",S20/Q20*365/12),"") | U20: =IFERROR(IF(S20="","",S20/Q20*365),"")
H21: =IFERROR(__xludf.DUMMYFUNCTION("IF(F21="""","""",IFERROR(GOOGLEFINANCE(UPPER(F21),""price""),""""))"),"") | J21: =IF(OR(A21="",E21<>""),"",IFERROR(H21-I21,"")) | P21: =IF(A21="","",IF(A21="Sell",IF(M21="","", (L21-M21)*K21*100),IF(A21="Assigned",IF(L21="","",L21*K21*100),IF(A21="Buy",IF(M21="","",(M21-L21)*K21*100),"")))) | Q21: =IF(E21="","",IF(E21-C21<1,1,E21-C21)) | R21: =IFERROR(IF(P21="","",P21/Q21),"") | S21: =IF(E21="","",IFERROR(IF(N21="",P21/O21,P21/N21),"")) | T21: =IFERROR(IF(S21="","",S21/Q21*365/12),"") | U21: =IFERROR(IF(S21="","",S21/Q21*365),"")
H22: =IFERROR(__xludf.DUMMYFUNCTION("IF(F22="""","""",IFERROR(GOOGLEFINANCE(UPPER(F22),""price""),""""))"),"") | J22: =IF(OR(A22="",E22<>""),"",IFERROR(H22-I22,"")) | P22: =IF(A22="","",IF(A22="Sell",IF(M22="","", (L22-M22)*K22*100),IF(A22="Assigned",IF(L22="","",L22*K22*100),IF(A22="Buy",IF(M22="","",(M22-L22)*K22*100),"")))) | Q22: =IF(E22="","",IF(E22-C22<1,1,E22-C22)) | R22: =IFERROR(IF(P22="","",P22/Q22),"") | S22: =IF(E22="","",IFERROR(IF(N22="",P22/O22,P22/N22),"")) | T22: =IFERROR(IF(S22="","",S22/Q22*365/12),"") | U22: =IFERROR(IF(S22="","",S22/Q22*365),"")
H23: =IFERROR(__xludf.DUMMYFUNCTION("IF(F23="""","""",IFERROR(GOOGLEFINANCE(UPPER(F23),""price""),""""))"),"") | J23: =IF(OR(A23="",E23<>""),"",IFERROR(H23-I23,"")) | P23: =IF(A23="","",IF(A23="Sell",IF(M23="","", (L23-M23)*K23*100),IF(A23="Assigned",IF(L23="","",L23*K23*100),IF(A23="Buy",IF(M23="","",(M23-L23)*K23*100),"")))) | Q23: =IF(E23="","",IF(E23-C23<1,1,E23-C23)) | R23: =IFERROR(IF(P23="","",P23/Q23),"") | S23: =IF(E23="","",IFERROR(IF(N23="",P23/O23,P23/N23),"")) | T23: =IFERROR(IF(S23="","",S23/Q23*365/12),"") | U23: =IFERROR(IF(S23="","",S23/Q23*365),"")
H24: =IFERROR(__xludf.DUMMYFUNCTION("IF(F24="""","""",IFERROR(GOOGLEFINANCE(UPPER(F24),""price""),""""))"),"") | J24: =IF(OR(A24="",E24<>""),"",IFERROR(H24-I24,"")) | P24: =IF(A24="","",IF(A24="Sell",IF(M24="","", (L24-M24)*K24*100),IF(A24="Assigned",IF(L24="","",L24*K24*100),IF(A24="Buy",IF(M24="","",(M24-L24)*K24*100),"")))) | Q24: =IF(E24="","",IF(E24-C24<1,1,E24-C24)) | R24: =IFERROR(IF(P24="","",P24/Q24),"") | S24: =IF(E24="","",IFERROR(IF(N24="",P24/O24,P24/N24),"")) | T24: =IFERROR(IF(S24="","",S24/Q24*365/12),"") | U24: =IFERROR(IF(S24="","",S24/Q24*365),"")
H25: =IFERROR(__xludf.DUMMYFUNCTION("IF(F25="""","""",IFERROR(GOOGLEFINANCE(UPPER(F25),""price""),""""))"),"") | J25: =IF(OR(A25="",E25<>""),"",IFERROR(H25-I25,"")) | P25: =IF(A25="","",IF(A25="Sell",IF(M25="","", (L25-M25)*K25*100),IF(A25="Assigned",IF(L25="","",L25*K25*100),IF(A25="Buy",IF(M25="","",(M25-L25)*K25*100),"")))) | Q25: =IF(E25="","",IF(E25-C25<1,1,E25-C25)) | R25: =IFERROR(IF(P25="","",P25/Q25),"") | S25: =IF(E25="","",IFERROR(IF(N25="",P25/O25,P25/N25),"")) | T25: =IFERROR(IF(S25="","",S25/Q25*365/12),"") | U25: =IFERROR(IF(S25="","",S25/Q25*365),"")
H26: =IFERROR(__xludf.DUMMYFUNCTION("IF(F26="""","""",IFERROR(GOOGLEFINANCE(UPPER(F26),""price""),""""))"),"") | J26: =IF(OR(A26="",E26<>""),"",IFERROR(H26-I26,"")) | P26: =IF(A26="","",IF(A26="Sell",IF(M26="","", (L26-M26)*K26*100),IF(A26="Assigned",IF(L26="","",L26*K26*100),IF(A26="Buy",IF(M26="","",(M26-L26)*K26*100),"")))) | Q26: =IF(E26="","",IF(E26-C26<1,1,E26-C26)) | R26: =IFERROR(IF(P26="","",P26/Q26),"") | S26: =IF(E26="","",IFERROR(IF(N26="",P26/O26,P26/N26),"")) | T26: =IFERROR(IF(S26="","",S26/Q26*365/12),"") | U26: =IFERROR(IF(S26="","",S26/Q26*365),"")
H27: =IFERROR(__xludf.DUMMYFUNCTION("IF(F27="""","""",IFERROR(GOOGLEFINANCE(UPPER(F27),""price""),""""))"),"") | J27: =IF(OR(A27="",E27<>""),"",IFERROR(H27-I27,"")) | P27: =IF(A27="","",IF(A27="Sell",IF(M27="","", (L27-M27)*K27*100),IF(A27="Assigned",IF(L27="","",L27*K27*100),IF(A27="Buy",IF(M27="","",(M27-L27)*K27*100),"")))) | Q27: =IF(E27="","",IF(E27-C27<1,1,E27-C27)) | R27: =IFERROR(IF(P27="","",P27/Q27),"") | S27: =IF(E27="","",IFERROR(IF(N27="",P27/O27,P27/N27),"")) | T27: =IFERROR(IF(S27="","",S27/Q27*365/12),"") | U27: =IFERROR(IF(S27="","",S27/Q27*365),"")
H28: =IFERROR(__xludf.DUMMYFUNCTION("IF(F28="""","""",IFERROR(GOOGLEFINANCE(UPPER(F28),""price""),""""))"),"") | J28: =IF(OR(A28="",E28<>""),"",IFERROR(H28-I28,"")) | P28: =IF(A28="","",IF(A28="Sell",IF(M28="","", (L28-M28)*K28*100),IF(A28="Assigned",IF(L28="","",L28*K28*100),IF(A28="Buy",IF(M28="","",(M28-L28)*K28*100),"")))) | Q28: =IF(E28="","",IF(E28-C28<1,1,E28-C28)) | R28: =IFERROR(IF(P28="","",P28/Q28),"") | S28: =IF(E28="","",IFERROR(IF(N28="",P28/O28,P28/N28),"")) | T28: =IFERROR(IF(S28="","",S28/Q28*365/12),"") | U28: =IFERROR(IF(S28="","",S28/Q28*365),"")
H29: =IFERROR(__xludf.DUMMYFUNCTION("IF(F29="""","""",IFERROR(GOOGLEFINANCE(UPPER(F29),""price""),""""))"),"") | J29: =IF(OR(A29="",E29<>""),"",IFERROR(H29-I29,"")) | P29: =IF(A29="","",IF(A29="Sell",IF(M29="","", (L29-M29)*K29*100),IF(A29="Assigned",IF(L29="","",L29*K29*100),IF(A29="Buy",IF(M29="","",(M29-L29)*K29*100),"")))) | Q29: =IF(E29="","",IF(E29-C29<1,1,E29-C29)) | R29: =IFERROR(IF(P29="","",P29/Q29),"") | S29: =IF(E29="","",IFERROR(IF(N29="",P29/O29,P29/N29),"")) | T29: =IFERROR(IF(S29="","",S29/Q29*365/12),"") | U29: =IFERROR(IF(S29="","",S29/Q29*365),"")
H30: =IFERROR(__xludf.DUMMYFUNCTION("IF(F30="""","""",IFERROR(GOOGLEFINANCE(UPPER(F30),""price""),""""))"),"") | J30: =IF(OR(A30="",E30<>""),"",IFERROR(H30-I30,"")) | P30: =IF(A30="","",IF(A30="Sell",IF(M30="","", (L30-M30)*K30*100),IF(A30="Assigned",IF(L30="","",L30*K30*100),IF(A30="Buy",IF(M30="","",(M30-L30)*K30*100),"")))) | Q30: =IF(E30="","",IF(E30-C30<1,1,E30-C30)) | R30: =IFERROR(IF(P30="","",P30/Q30),"") | S30: =IF(E30="","",IFERROR(IF(N30="",P30/O30,P30/N30),"")) | T30: =IFERROR(IF(S30="","",S30/Q30*365/12),"") | U30: =IFERROR(IF(S30="","",S30/Q30*365),"")
H31: =IFERROR(__xludf.DUMMYFUNCTION("IF(F31="""","""",IFERROR(GOOGLEFINANCE(UPPER(F31),""price""),""""))"),"") | J31: =IF(OR(A31="",E31<>""),"",IFERROR(H31-I31,"")) | P31: =IF(A31="","",IF(A31="Sell",IF(M31="","", (L31-M31)*K31*100),IF(A31="Assigned",IF(L31="","",L31*K31*100),IF(A31="Buy",IF(M31="","",(M31-L31)*K31*100),"")))) | Q31: =IF(E31="","",IF(E31-C31<1,1,E31-C31)) | R31: =IFERROR(IF(P31="","",P31/Q31),"") | S31: =IF(E31="","",IFERROR(IF(N31="",P31/O31,P31/N31),"")) | T31: =IFERROR(IF(S31="","",S31/Q31*365/12),"") | U31: =IFERROR(IF(S31="","",S31/Q31*365),"")
H32: =IFERROR(__xludf.DUMMYFUNCTION("IF(F32="""","""",IFERROR(GOOGLEFINANCE(UPPER(F32),""price""),""""))"),"") | J32: =IF(OR(A32="",E32<>""),"",IFERROR(H32-I32,"")) | P32: =IF(A32="","",IF(A32="Sell",IF(M32="","", (L32-M32)*K32*100),IF(A32="Assigned",IF(L32="","",L32*K32*100),IF(A32="Buy",IF(M32="","",(M32-L32)*K32*100),"")))) | Q32: =IF(E32="","",IF(E32-C32<1,1,E32-C32)) | R32: =IFERROR(IF(P32="","",P32/Q32),"") | S32: =IF(E32="","",IFERROR(IF(N32="",P32/O32,P32/N32),"")) | T32: =IFERROR(IF(S32="","",S32/Q32*365/12),"") | U32: =IFERROR(IF(S32="","",S32/Q32*365),"")
H33: =IFERROR(__xludf.DUMMYFUNCTION("IF(F33="""","""",IFERROR(GOOGLEFINANCE(UPPER(F33),""price""),""""))"),"") | J33: =IF(OR(A33="",E33<>""),"",IFERROR(H33-I33,"")) | P33: =IF(A33="","",IF(A33="Sell",IF(M33="","", (L33-M33)*K33*100),IF(A33="Assigned",IF(L33="","",L33*K33*100),IF(A33="Buy",IF(M33="","",(M33-L33)*K33*100),"")))) | Q33: =IF(E33="","",IF(E33-C33<1,1,E33-C33)) | R33: =IFERROR(IF(P33="","",P33/Q33),"") | S33: =IF(E33="","",IFERROR(IF(N33="",P33/O33,P33/N33),"")) | T33: =IFERROR(IF(S33="","",S33/Q33*365/12),"") | U33: =IFERROR(IF(S33="","",S33/Q33*365),"")
H34: =IFERROR(__xludf.DUMMYFUNCTION("IF(F34="""","""",IFERROR(GOOGLEFINANCE(UPPER(F34),""price""),""""))"),"") | J34: =IF(OR(A34="",E34<>""),"",IFERROR(H34-I34,"")) | P34: =IF(A34="","",IF(A34="Sell",IF(M34="","", (L34-M34)*K34*100),IF(A34="Assigned",IF(L34="","",L34*K34*100),IF(A34="Buy",IF(M34="","",(M34-L34)*K34*100),"")))) | Q34: =IF(E34="","",IF(E34-C34<1,1,E34-C34)) | R34: =IFERROR(IF(P34="","",P34/Q34),"") | S34: =IF(E34="","",IFERROR(IF(N34="",P34/O34,P34/N34),"")) | T34: =IFERROR(IF(S34="","",S34/Q34*365/12),"") | U34: =IFERROR(IF(S34="","",S34/Q34*365),"")
H35: =IFERROR(__xludf.DUMMYFUNCTION("IF(F35="""","""",IFERROR(GOOGLEFINANCE(UPPER(F35),""price""),""""))"),"") | J35: =IF(OR(A35="",E35<>""),"",IFERROR(H35-I35,"")) | P35: =IF(A35="","",IF(A35="Sell",IF(M35="","", (L35-M35)*K35*100),IF(A35="Assigned",IF(L35="","",L35*K35*100),IF(A35="Buy",IF(M35="","",(M35-L35)*K35*100),"")))) | Q35: =IF(E35="","",IF(E35-C35<1,1,E35-C35)) | R35: =IFERROR(IF(P35="","",P35/Q35),"") | S35: =IF(E35="","",IFERROR(IF(N35="",P35/O35,P35/N35),"")) | T35: =IFERROR(IF(S35="","",S35/Q35*365/12),"") | U35: =IFERROR(IF(S35="","",S35/Q35*365),"")
H36: =IFERROR(__xludf.DUMMYFUNCTION("IF(F36="""","""",IFERROR(GOOGLEFINANCE(UPPER(F36),""price""),""""))"),"") | J36: =IF(OR(A36="",E36<>""),"",IFERROR(H36-I36,"")) | P36: =IF(A36="","",IF(A36="Sell",IF(M36="","", (L36-M36)*K36*100),IF(A36="Assigned",IF(L36="","",L36*K36*100),IF(A36="Buy",IF(M36="","",(M36-L36)*K36*100),"")))) | Q36: =IF(E36="","",IF(E36-C36<1,1,E36-C36)) | R36: =IFERROR(IF(P36="","",P36/Q36),"") | S36: =IF(E36="","",IFERROR(IF(N36="",P36/O36,P36/N36),"")) | T36: =IFERROR(IF(S36="","",S36/Q36*365/12),"") | U36: =IFERROR(IF(S36="","",S36/Q36*365),"")
H37: =IFERROR(__xludf.DUMMYFUNCTION("IF(F37="""","""",IFERROR(GOOGLEFINANCE(UPPER(F37),""price""),""""))"),"") | J37: =IF(OR(A37="",E37<>""),"",IFERROR(H37-I37,"")) | P37: =IF(A37="","",IF(A37="Sell",IF(M37="","", (L37-M37)*K37*100),IF(A37="Assigned",IF(L37="","",L37*K37*100),IF(A37="Buy",IF(M37="","",(M37-L37)*K37*100),"")))) | Q37: =IF(E37="","",IF(E37-C37<1,1,E37-C37)) | R37: =IFERROR(IF(P37="","",P37/Q37),"") | S37: =IF(E37="","",IFERROR(IF(N37="",P37/O37,P37/N37),"")) | T37: =IFERROR(IF(S37="","",S37/Q37*365/12),"") | U37: =IFERROR(IF(S37="","",S37/Q37*365),"")
H38: =IFERROR(__xludf.DUMMYFUNCTION("IF(F38="""","""",IFERROR(GOOGLEFINANCE(UPPER(F38),""price""),""""))"),"") | J38: =IF(OR(A38="",E38<>""),"",IFERROR(H38-I38,"")) | P38: =IF(A38="","",IF(A38="Sell",IF(M38="","", (L38-M38)*K38*100),IF(A38="Assigned",IF(L38="","",L38*K38*100),IF(A38="Buy",IF(M38="","",(M38-L38)*K38*100),"")))) | Q38: =IF(E38="","",IF(E38-C38<1,1,E38-C38)) | R38: =IFERROR(IF(P38="","",P38/Q38),"") | S38: =IF(E38="","",IFERROR(IF(N38="",P38/O38,P38/N38),"")) | T38: =IFERROR(IF(S38="","",S38/Q38*365/12),"") | U38: =IFERROR(IF(S38="","",S38/Q38*365),"")
H39: =IFERROR(__xludf.DUMMYFUNCTION("IF(F39="""","""",IFERROR(GOOGLEFINANCE(UPPER(F39),""price""),""""))"),"") | J39: =IF(OR(A39="",E39<>""),"",IFERROR(H39-I39,"")) | P39: =IF(A39="","",IF(A39="Sell",IF(M39="","", (L39-M39)*K39*100),IF(A39="Assigned",IF(L39="","",L39*K39*100),IF(A39="Buy",IF(M39="","",(M39-L39)*K39*100),"")))) | Q39: =IF(E39="","",IF(E39-C39<1,1,E39-C39)) | R39: =IFERROR(IF(P39="","",P39/Q39),"") | S39: =IF(E39="","",IFERROR(IF(N39="",P39/O39,P39/N39),"")) | T39: =IFERROR(IF(S39="","",S39/Q39*365/12),"") | U39: =IFERROR(IF(S39="","",S39/Q39*365),"")
H40: =IFERROR(__xludf.DUMMYFUNCTION("IF(F40="""","""",IFERROR(GOOGLEFINANCE(UPPER(F40),""price""),""""))"),"") | J40: =IF(OR(A40="",E40<>""),"",IFERROR(H40-I40,"")) | P40: =IF(A40="","",IF(A40="Sell",IF(M40="","", (L40-M40)*K40*100),IF(A40="Assigned",IF(L40="","",L40*K40*100),IF(A40="Buy",IF(M40="","",(M40-L40)*K40*100),"")))) | Q40: =IF(E40="","",IF(E40-C40<1,1,E40-C40)) | R40: =IFERROR(IF(P40="","",P40/Q40),"") | S40: =IF(E40="","",IFERROR(IF(N40="",P40/O40,P40/N40),"")) | T40: =IFERROR(IF(S40="","",S40/Q40*365/12),"") | U40: =IFERROR(IF(S40="","",S40/Q40*365),"")
H41: =IFERROR(__xludf.DUMMYFUNCTION("IF(F41="""","""",IFERROR(GOOGLEFINANCE(UPPER(F41),""price""),""""))"),"") | J41: =IF(OR(A41="",E41<>""),"",IFERROR(H41-I41,"")) | P41: =IF(A41="","",IF(A41="Sell",IF(M41="","", (L41-M41)*K41*100),IF(A41="Assigned",IF(L41="","",L41*K41*100),IF(A41="Buy",IF(M41="","",(M41-L41)*K41*100),"")))) | Q41: =IF(E41="","",IF(E41-C41<1,1,E41-C41)) | R41: =IFERROR(IF(P41="","",P41/Q41),"") | S41: =IF(E41="","",IFERROR(IF(N41="",P41/O41,P41/N41),"")) | T41: =IFERROR(IF(S41="","",S41/Q41*365/12),"") | U41: =IFERROR(IF(S41="","",S41/Q41*365),"")
H42: =IFERROR(__xludf.DUMMYFUNCTION("IF(F42="""","""",IFERROR(GOOGLEFINANCE(UPPER(F42),""price""),""""))"),"") | J42: =IF(OR(A42="",E42<>""),"",IFERROR(H42-I42,"")) | P42: =IF(A42="","",IF(A42="Sell",IF(M42="","", (L42-M42)*K42*100),IF(A42="Assigned",IF(L42="","",L42*K42*100),IF(A42="Buy",IF(M42="","",(M42-L42)*K42*100),"")))) | Q42: =IF(E42="","",IF(E42-C42<1,1,E42-C42)) | R42: =IFERROR(IF(P42="","",P42/Q42),"") | S42: =IF(E42="","",IFERROR(IF(N42="",P42/O42,P42/N42),"")) | T42: =IFERROR(IF(S42="","",S42/Q42*365/12),"") | U42: =IFERROR(IF(S42="","",S42/Q42*365),"")
H43: =IFERROR(__xludf.DUMMYFUNCTION("IF(F43="""","""",IFERROR(GOOGLEFINANCE(UPPER(F43),""price""),""""))"),"") | J43: =IF(OR(A43="",E43<>""),"",IFERROR(H43-I43,"")) | P43: =IF(A43="","",IF(A43="Sell",IF(M43="","", (L43-M43)*K43*100),IF(A43="Assigned",IF(L43="","",L43*K43*100),IF(A43="Buy",IF(M43="","",(M43-L43)*K43*100),"")))) | Q43: =IF(E43="","",IF(E43-C43<1,1,E43-C43)) | R43: =IFERROR(IF(P43="","",P43/Q43),"") | S43: =IF(E43="","",IFERROR(IF(N43="",P43/O43,P43/N43),"")) | T43: =IFERROR(IF(S43="","",S43/Q43*365/12),"") | U43: =IFERROR(IF(S43="","",S43/Q43*365),"")
H44: =IFERROR(__xludf.DUMMYFUNCTION("IF(F44="""","""",IFERROR(GOOGLEFINANCE(UPPER(F44),""price""),""""))"),"") | J44: =IF(OR(A44="",E44<>""),"",IFERROR(H44-I44,"")) | P44: =IF(A44="","",IF(A44="Sell",IF(M44="","", (L44-M44)*K44*100),IF(A44="Assigned",IF(L44="","",L44*K44*100),IF(A44="Buy",IF(M44="","",(M44-L44)*K44*100),"")))) | Q44: =IF(E44="","",IF(E44-C44<1,1,E44-C44)) | R44: =IFERROR(IF(P44="","",P44/Q44),"") | S44: =IF(E44="","",IFERROR(IF(N44="",P44/O44,P44/N44),"")) | T44: =IFERROR(IF(S44="","",S44/Q44*365/12),"") | U44: =IFERROR(IF(S44="","",S44/Q44*365),"")
H45: =IFERROR(__xludf.DUMMYFUNCTION("IF(F45="""","""",IFERROR(GOOGLEFINANCE(UPPER(F45),""price""),""""))"),"") | J45: =IF(OR(A45="",E45<>""),"",IFERROR(H45-I45,"")) | P45: =IF(A45="","",IF(A45="Sell",IF(M45="","", (L45-M45)*K45*100),IF(A45="Assigned",IF(L45="","",L45*K45*100),IF(A45="Buy",IF(M45="","",(M45-L45)*K45*100),"")))) | Q45: =IF(E45="","",IF(E45-C45<1,1,E45-C45)) | R45: =IFERROR(IF(P45="","",P45/Q45),"") | S45: =IF(E45="","",IFERROR(IF(N45="",P45/O45,P45/N45),"")) | T45: =IFERROR(IF(S45="","",S45/Q45*365/12),"") | U45: =IFERROR(IF(S45="","",S45/Q45*365),"")
H46: =IFERROR(__xludf.DUMMYFUNCTION("IF(F46="""","""",IFERROR(GOOGLEFINANCE(UPPER(F46),""price""),""""))"),"") | J46: =IF(OR(A46="",E46<>""),"",IFERROR(H46-I46,"")) | P46: =IF(A46="","",IF(A46="Sell",IF(M46="","", (L46-M46)*K46*100),IF(A46="Assigned",IF(L46="","",L46*K46*100),IF(A46="Buy",IF(M46="","",(M46-L46)*K46*100),"")))) | Q46: =IF(E46="","",IF(E46-C46<1,1,E46-C46)) | R46: =IFERROR(IF(P46="","",P46/Q46),"") | S46: =IF(E46="","",IFERROR(IF(N46="",P46/O46,P46/N46),"")) | T46: =IFERROR(IF(S46="","",S46/Q46*365/12),"") | U46: =IFERROR(IF(S46="","",S46/Q46*365),"")
H47: =IFERROR(__xludf.DUMMYFUNCTION("IF(F47="""","""",IFERROR(GOOGLEFINANCE(UPPER(F47),""price""),""""))"),"") | J47: =IF(OR(A47="",E47<>""),"",IFERROR(H47-I47,"")) | P47: =IF(A47="","",IF(A47="Sell",IF(M47="","", (L47-M47)*K47*100),IF(A47="Assigned",IF(L47="","",L47*K47*100),IF(A47="Buy",IF(M47="","",(M47-L47)*K47*100),"")))) | Q47: =IF(E47="","",IF(E47-C47<1,1,E47-C47)) | R47: =IFERROR(IF(P47="","",P47/Q47),"") | S47: =IF(E47="","",IFERROR(IF(N47="",P47/O47,P47/N47),"")) | T47: =IFERROR(IF(S47="","",S47/Q47*365/12),"") | U47: =IFERROR(IF(S47="","",S47/Q47*365),"")
H48: =IFERROR(__xludf.DUMMYFUNCTION("IF(F48="""","""",IFERROR(GOOGLEFINANCE(UPPER(F48),""price""),""""))"),"") | J48: =IF(OR(A48="",E48<>""),"",IFERROR(H48-I48,"")) | P48: =IF(A48="","",IF(A48="Sell",IF(M48="","", (L48-M48)*K48*100),IF(A48="Assigned",IF(L48="","",L48*K48*100),IF(A48="Buy",IF(M48="","",(M48-L48)*K48*100),"")))) | Q48: =IF(E48="","",IF(E48-C48<1,1,E48-C48)) | R48: =IFERROR(IF(P48="","",P48/Q48),"") | S48: =IF(E48="","",IFERROR(IF(N48="",P48/O48,P48/N48),"")) | T48: =IFERROR(IF(S48="","",S48/Q48*365/12),"") | U48: =IFERROR(IF(S48="","",S48/Q48*365),"")
H49: =IFERROR(__xludf.DUMMYFUNCTION("IF(F49="""","""",IFERROR(GOOGLEFINANCE(UPPER(F49),""price""),""""))"),"") | J49: =IF(OR(A49="",E49<>""),"",IFERROR(H49-I49,"")) | P49: =IF(A49="","",IF(A49="Sell",IF(M49="","", (L49-M49)*K49*100),IF(A49="Assigned",IF(L49="","",L49*K49*100),IF(A49="Buy",IF(M49="","",(M49-L49)*K49*100),"")))) | Q49: =IF(E49="","",IF(E49-C49<1,1,E49-C49)) | R49: =IFERROR(IF(P49="","",P49/Q49),"") | S49: =IF(E49="","",IFERROR(IF(N49="",P49/O49,P49/N49),"")) | T49: =IFERROR(IF(S49="","",S49/Q49*365/12),"") | U49: =IFERROR(IF(S49="","",S49/Q49*365),"")
H50: =IFERROR(__xludf.DUMMYFUNCTION("IF(F50="""","""",IFERROR(GOOGLEFINANCE(UPPER(F50),""price""),""""))"),"") | J50: =IF(OR(A50="",E50<>""),"",IFERROR(H50-I50,"")) | P50: =IF(A50="","",IF(A50="Sell",IF(M50="","", (L50-M50)*K50*100),IF(A50="Assigned",IF(L50="","",L50*K50*100),IF(A50="Buy",IF(M50="","",(M50-L50)*K50*100),"")))) | Q50: =IF(E50="","",IF(E50-C50<1,1,E50-C50)) | R50: =IFERROR(IF(P50="","",P50/Q50),"") | S50: =IF(E50="","",IFERROR(IF(N50="",P50/O50,P50/N50),"")) | T50: =IFERROR(IF(S50="","",S50/Q50*365/12),"") | U50: =IFERROR(IF(S50="","",S50/Q50*365),"")
H51: =IFERROR(__xludf.DUMMYFUNCTION("IF(F51="""","""",IFERROR(GOOGLEFINANCE(UPPER(F51),""price""),""""))"),"") | J51: =IF(OR(A51="",E51<>""),"",IFERROR(H51-I51,"")) | P51: =IF(A51="","",IF(A51="Sell",IF(M51="","", (L51-M51)*K51*100),IF(A51="Assigned",IF(L51="","",L51*K51*100),IF(A51="Buy",IF(M51="","",(M51-L51)*K51*100),"")))) | Q51: =IF(E51="","",IF(E51-C51<1,1,E51-C51)) | R51: =IFERROR(IF(P51="","",P51/Q51),"") | S51: =IF(E51="","",IFERROR(IF(N51="",P51/O51,P51/N51),"")) | T51: =IFERROR(IF(S51="","",S51/Q51*365/12),"") | U51: =IFERROR(IF(S51="","",S51/Q51*365),"")
H52: =IFERROR(__xludf.DUMMYFUNCTION("IF(F52="""","""",IFERROR(GOOGLEFINANCE(UPPER(F52),""price""),""""))"),"") | J52: =IF(OR(A52="",E52<>""),"",IFERROR(H52-I52,"")) | P52: =IF(A52="","",IF(A52="Sell",IF(M52="","", (L52-M52)*K52*100),IF(A52="Assigned",IF(L52="","",L52*K52*100),IF(A52="Buy",IF(M52="","",(M52-L52)*K52*100),"")))) | Q52: =IF(E52="","",IF(E52-C52<1,1,E52-C52)) | R52: =IFERROR(IF(P52="","",P52/Q52),"") | S52: =IF(E52="","",IFERROR(IF(N52="",P52/O52,P52/N52),"")) | T52: =IFERROR(IF(S52="","",S52/Q52*365/12),"") | U52: =IFERROR(IF(S52="","",S52/Q52*365),"")
H53: =IFERROR(__xludf.DUMMYFUNCTION("IF(F53="""","""",IFERROR(GOOGLEFINANCE(UPPER(F53),""price""),""""))"),"") | J53: =IF(OR(A53="",E53<>""),"",IFERROR(H53-I53,"")) | P53: =IF(A53="","",IF(A53="Sell",IF(M53="","", (L53-M53)*K53*100),IF(A53="Assigned",IF(L53="","",L53*K53*100),IF(A53="Buy",IF(M53="","",(M53-L53)*K53*100),"")))) | Q53: =IF(E53="","",IF(E53-C53<1,1,E53-C53)) | R53: =IFERROR(IF(P53="","",P53/Q53),"") | S53: =IF(E53="","",IFERROR(IF(N53="",P53/O53,P53/N53),"")) | T53: =IFERROR(IF(S53="","",S53/Q53*365/12),"") | U53: =IFERROR(IF(S53="","",S53/Q53*365),"")
H54: =IFERROR(__xludf.DUMMYFUNCTION("IF(F54="""","""",IFERROR(GOOGLEFINANCE(UPPER(F54),""price""),""""))"),"") | J54: =IF(OR(A54="",E54<>""),"",IFERROR(H54-I54,"")) | P54: =IF(A54="","",IF(A54="Sell",IF(M54="","", (L54-M54)*K54*100),IF(A54="Assigned",IF(L54="","",L54*K54*100),IF(A54="Buy",IF(M54="","",(M54-L54)*K54*100),"")))) | Q54: =IF(E54="","",IF(E54-C54<1,1,E54-C54)) | R54: =IFERROR(IF(P54="","",P54/Q54),"") | S54: =IF(E54="","",IFERROR(IF(N54="",P54/O54,P54/N54),"")) | T54: =IFERROR(IF(S54="","",S54/Q54*365/12),"") | U54: =IFERROR(IF(S54="","",S54/Q54*365),"")
H55: =IFERROR(__xludf.DUMMYFUNCTION("IF(F55="""","""",IFERROR(GOOGLEFINANCE(UPPER(F55),""price""),""""))"),"") | J55: =IF(OR(A55="",E55<>""),"",IFERROR(H55-I55,"")) | P55: =IF(A55="","",IF(A55="Sell",IF(M55="","", (L55-M55)*K55*100),IF(A55="Assigned",IF(L55="","",L55*K55*100),IF(A55="Buy",IF(M55="","",(M55-L55)*K55*100),"")))) | Q55: =IF(E55="","",IF(E55-C55<1,1,E55-C55)) | R55: =IFERROR(IF(P55="","",P55/Q55),"") | S55: =IF(E55="","",IFERROR(IF(N55="",P55/O55,P55/N55),"")) | T55: =IFERROR(IF(S55="","",S55/Q55*365/12),"") | U55: =IFERROR(IF(S55="","",S55/Q55*365),"")
H56: =IFERROR(__xludf.DUMMYFUNCTION("IF(F56="""","""",IFERROR(GOOGLEFINANCE(UPPER(F56),""price""),""""))"),"") | J56: =IF(OR(A56="",E56<>""),"",IFERROR(H56-I56,"")) | P56: =IF(A56="","",IF(A56="Sell",IF(M56="","", (L56-M56)*K56*100),IF(A56="Assigned",IF(L56="","",L56*K56*100),IF(A56="Buy",IF(M56="","",(M56-L56)*K56*100),"")))) | Q56: =IF(E56="","",IF(E56-C56<1,1,E56-C56)) | R56: =IFERROR(IF(P56="","",P56/Q56),"") | S56: =IF(E56="","",IFERROR(IF(N56="",P56/O56,P56/N56),"")) | T56: =IFERROR(IF(S56="","",S56/Q56*365/12),"") | U56: =IFERROR(IF(S56="","",S56/Q56*365),"")
H57: =IFERROR(__xludf.DUMMYFUNCTION("IF(F57="""","""",IFERROR(GOOGLEFINANCE(UPPER(F57),""price""),""""))"),"") | J57: =IF(OR(A57="",E57<>""),"",IFERROR(H57-I57,"")) | P57: =IF(A57="","",IF(A57="Sell",IF(M57="","", (L57-M57)*K57*100),IF(A57="Assigned",IF(L57="","",L57*K57*100),IF(A57="Buy",IF(M57="","",(M57-L57)*K57*100),"")))) | Q57: =IF(E57="","",IF(E57-C57<1,1,E57-C57)) | R57: =IFERROR(IF(P57="","",P57/Q57),"") | S57: =IF(E57="","",IFERROR(IF(N57="",P57/O57,P57/N57),"")) | T57: =IFERROR(IF(S57="","",S57/Q57*365/12),"") | U57: =IFERROR(IF(S57="","",S57/Q57*365),"")
H58: =IFERROR(__xludf.DUMMYFUNCTION("IF(F58="""","""",IFERROR(GOOGLEFINANCE(UPPER(F58),""price""),""""))"),"") | J58: =IF(OR(A58="",E58<>""),"",IFERROR(H58-I58,"")) | P58: =IF(A58="","",IF(A58="Sell",IF(M58="","", (L58-M58)*K58*100),IF(A58="Assigned",IF(L58="","",L58*K58*100),IF(A58="Buy",IF(M58="","",(M58-L58)*K58*100),"")))) | Q58: =IF(E58="","",IF(E58-C58<1,1,E58-C58)) | R58: =IFERROR(IF(P58="","",P58/Q58),"") | S58: =IF(E58="","",IFERROR(IF(N58="",P58/O58,P58/N58),"")) | T58: =IFERROR(IF(S58="","",S58/Q58*365/12),"") | U58: =IFERROR(IF(S58="","",S58/Q58*365),"")
H59: =IFERROR(__xludf.DUMMYFUNCTION("IF(F59="""","""",IFERROR(GOOGLEFINANCE(UPPER(F59),""price""),""""))"),"") | J59: =IF(OR(A59="",E59<>""),"",IFERROR(H59-I59,"")) | P59: =IF(A59="","",IF(A59="Sell",IF(M59="","", (L59-M59)*K59*100),IF(A59="Assigned",IF(L59="","",L59*K59*100),IF(A59="Buy",IF(M59="","",(M59-L59)*K59*100),"")))) | Q59: =IF(E59="","",IF(E59-C59<1,1,E59-C59)) | R59: =IFERROR(IF(P59="","",P59/Q59),"") | S59: =IF(E59="","",IFERROR(IF(N59="",P59/O59,P59/N59),"")) | T59: =IFERROR(IF(S59="","",S59/Q59*365/12),"") | U59: =IFERROR(IF(S59="","",S59/Q59*365),"")
H60: =IFERROR(__xludf.DUMMYFUNCTION("IF(F60="""","""",IFERROR(GOOGLEFINANCE(UPPER(F60),""price""),""""))"),"") | J60: =IF(OR(A60="",E60<>""),"",IFERROR(H60-I60,"")) | P60: =IF(A60="","",IF(A60="Sell",IF(M60="","", (L60-M60)*K60*100),IF(A60="Assigned",IF(L60="","",L60*K60*100),IF(A60="Buy",IF(M60="","",(M60-L60)*K60*100),"")))) | Q60: =IF(E60="","",IF(E60-C60<1,1,E60-C60)) | R60: =IFERROR(IF(P60="","",P60/Q60),"") | S60: =IF(E60="","",IFERROR(IF(N60="",P60/O60,P60/N60),"")) | T60: =IFERROR(IF(S60="","",S60/Q60*365/12),"") | U60: =IFERROR(IF(S60="","",S60/Q60*365),"")
H61: =IFERROR(__xludf.DUMMYFUNCTION("IF(F61="""","""",IFERROR(GOOGLEFINANCE(UPPER(F61),""price""),""""))"),"") | J61: =IF(OR(A61="",E61<>""),"",IFERROR(H61-I61,"")) | P61: =IF(A61="","",IF(A61="Sell",IF(M61="","", (L61-M61)*K61*100),IF(A61="Assigned",IF(L61="","",L61*K61*100),IF(A61="Buy",IF(M61="","",(M61-L61)*K61*100),"")))) | Q61: =IF(E61="","",IF(E61-C61<1,1,E61-C61)) | R61: =IFERROR(IF(P61="","",P61/Q61),"") | S61: =IF(E61="","",IFERROR(IF(N61="",P61/O61,P61/N61),"")) | T61: =IFERROR(IF(S61="","",S61/Q61*365/12),"") | U61: =IFERROR(IF(S61="","",S61/Q61*365),"")
H62: =IFERROR(__xludf.DUMMYFUNCTION("IF(F62="""","""",IFERROR(GOOGLEFINANCE(UPPER(F62),""price""),""""))"),"") | J62: =IF(OR(A62="",E62<>""),"",IFERROR(H62-I62,"")) | P62: =IF(A62="","",IF(A62="Sell",IF(M62="","", (L62-M62)*K62*100),IF(A62="Assigned",IF(L62="","",L62*K62*100),IF(A62="Buy",IF(M62="","",(M62-L62)*K62*100),"")))) | Q62: =IF(E62="","",IF(E62-C62<1,1,E62-C62)) | R62: =IFERROR(IF(P62="","",P62/Q62),"") | S62: =IF(E62="","",IFERROR(IF(N62="",P62/O62,P62/N62),"")) | T62: =IFERROR(IF(S62="","",S62/Q62*365/12),"") | U62: =IFERROR(IF(S62="","",S62/Q62*365),"")
H63: =IFERROR(__xludf.DUMMYFUNCTION("IF(F63="""","""",IFERROR(GOOGLEFINANCE(UPPER(F63),""price""),""""))"),"") | J63: =IF(OR(A63="",E63<>""),"",IFERROR(H63-I63,"")) | P63: =IF(A63="","",IF(A63="Sell",IF(M63="","", (L63-M63)*K63*100),IF(A63="Assigned",IF(L63="","",L63*K63*100),IF(A63="Buy",IF(M63="","",(M63-L63)*K63*100),"")))) | Q63: =IF(E63="","",IF(E63-C63<1,1,E63-C63)) | R63: =IFERROR(IF(P63="","",P63/Q63),"") | S63: =IF(E63="","",IFERROR(IF(N63="",P63/O63,P63/N63),"")) | T63: =IFERROR(IF(S63="","",S63/Q63*365/12),"") | U63: =IFERROR(IF(S63="","",S63/Q63*365),"")
H64: =IFERROR(__xludf.DUMMYFUNCTION("IF(F64="""","""",IFERROR(GOOGLEFINANCE(UPPER(F64),""price""),""""))"),"") | J64: =IF(OR(A64="",E64<>""),"",IFERROR(H64-I64,"")) | P64: =IF(A64="","",IF(A64="Sell",IF(M64="","", (L64-M64)*K64*100),IF(A64="Assigned",IF(L64="","",L64*K64*100),IF(A64="Buy",IF(M64="","",(M64-L64)*K64*100),"")))) | Q64: =IF(E64="","",IF(E64-C64<1,1,E64-C64)) | R64: =IFERROR(IF(P64="","",P64/Q64),"") | S64: =IF(E64="","",IFERROR(IF(N64="",P64/O64,P64/N64),"")) | T64: =IFERROR(IF(S64="","",S64/Q64*365/12),"") | U64: =IFERROR(IF(S64="","",S64/Q64*365),"")
H65: =IFERROR(__xludf.DUMMYFUNCTION("IF(F65="""","""",IFERROR(GOOGLEFINANCE(UPPER(F65),""price""),""""))"),"") | J65: =IF(OR(A65="",E65<>""),"",IFERROR(H65-I65,"")) | P65: =IF(A65="","",IF(A65="Sell",IF(M65="","", (L65-M65)*K65*100),IF(A65="Assigned",IF(L65="","",L65*K65*100),IF(A65="Buy",IF(M65="","",(M65-L65)*K65*100),"")))) | Q65: =IF(E65="","",IF(E65-C65<1,1,E65-C65)) | R65: =IFERROR(IF(P65="","",P65/Q65),"") | S65: =IF(E65="","",IFERROR(IF(N65="",P65/O65,P65/N65),"")) | T65: =IFERROR(IF(S65="","",S65/Q65*365/12),"") | U65: =IFERROR(IF(S65="","",S65/Q65*365),"")
H66: =IFERROR(__xludf.DUMMYFUNCTION("IF(F66="""","""",IFERROR(GOOGLEFINANCE(UPPER(F66),""price""),""""))"),"") | J66: =IF(OR(A66="",E66<>""),"",IFERROR(H66-I66,"")) | P66: =IF(A66="","",IF(A66="Sell",IF(M66="","", (L66-M66)*K66*100),IF(A66="Assigned",IF(L66="","",L66*K66*100),IF(A66="Buy",IF(M66="","",(M66-L66)*K66*100),"")))) | Q66: =IF(E66="","",IF(E66-C66<1,1,E66-C66)) | R66: =IFERROR(IF(P66="","",P66/Q66),"") | S66: =IF(E66="","",IFERROR(IF(N66="",P66/O66,P66/N66),"")) | T66: =IFERROR(IF(S66="","",S66/Q66*365/12),"") | U66: =IFERROR(IF(S66="","",S66/Q66*365),"")
H67: =IFERROR(__xludf.DUMMYFUNCTION("IF(F67="""","""",IFERROR(GOOGLEFINANCE(UPPER(F67),""price""),""""))"),"") | J67: =IF(OR(A67="",E67<>""),"",IFERROR(H67-I67,"")) | P67: =IF(A67="","",IF(A67="Sell",IF(M67="","", (L67-M67)*K67*100),IF(A67="Assigned",IF(L67="","",L67*K67*100),IF(A67="Buy",IF(M67="","",(M67-L67)*K67*100),"")))) | Q67: =IF(E67="","",IF(E67-C67<1,1,E67-C67)) | R67: =IFERROR(IF(P67="","",P67/Q67),"") | S67: =IF(E67="","",IFERROR(IF(N67="",P67/O67,P67/N67),"")) | T67: =IFERROR(IF(S67="","",S67/Q67*365/12),"") | U67: =IFERROR(IF(S67="","",S67/Q67*365),"")
H68: =IFERROR(__xludf.DUMMYFUNCTION("IF(F68="""","""",IFERROR(GOOGLEFINANCE(UPPER(F68),""price""),""""))"),"") | J68: =IF(OR(A68="",E68<>""),"",IFERROR(H68-I68,"")) | P68: =IF(A68="","",IF(A68="Sell",IF(M68="","", (L68-M68)*K68*100),IF(A68="Assigned",IF(L68="","",L68*K68*100),IF(A68="Buy",IF(M68="","",(M68-L68)*K68*100),"")))) | Q68: =IF(E68="","",IF(E68-C68<1,1,E68-C68)) | R68: =IFERROR(IF(P68="","",P68/Q68),"") | S68: =IF(E68="","",IFERROR(IF(N68="",P68/O68,P68/N68),"")) | T68: =IFERROR(IF(S68="","",S68/Q68*365/12),"") | U68: =IFERROR(IF(S68="","",S68/Q68*365),"")
H69: =IFERROR(__xludf.DUMMYFUNCTION("IF(F69="""","""",IFERROR(GOOGLEFINANCE(UPPER(F69),""price""),""""))"),"") | J69: =IF(OR(A69="",E69<>""),"",IFERROR(H69-I69,"")) | P69: =IF(A69="","",IF(A69="Sell",IF(M69="","", (L69-M69)*K69*100),IF(A69="Assigned",IF(L69="","",L69*K69*100),IF(A69="Buy",IF(M69="","",(M69-L69)*K69*100),"")))) | Q69: =IF(E69="","",IF(E69-C69<1,1,E69-C69)) | R69: =IFERROR(IF(P69="","",P69/Q69),"") | S69: =IF(E69="","",IFERROR(IF(N69="",P69/O69,P69/N69),"")) | T69: =IFERROR(IF(S69="","",S69/Q69*365/12),"") | U69: =IFERROR(IF(S69="","",S69/Q69*365),"")
H70: =IFERROR(__xludf.DUMMYFUNCTION("IF(F70="""","""",IFERROR(GOOGLEFINANCE(UPPER(F70),""price""),""""))"),"") | J70: =IF(OR(A70="",E70<>""),"",IFERROR(H70-I70,"")) | P70: =IF(A70="","",IF(A70="Sell",IF(M70="","", (L70-M70)*K70*100),IF(A70="Assigned",IF(L70="","",L70*K70*100),IF(A70="Buy",IF(M70="","",(M70-L70)*K70*100),"")))) | Q70: =IF(E70="","",IF(E70-C70<1,1,E70-C70)) | R70: =IFERROR(IF(P70="","",P70/Q70),"") | S70: =IF(E70="","",IFERROR(IF(N70="",P70/O70,P70/N70),"")) | T70: =IFERROR(IF(S70="","",S70/Q70*365/12),"") | U70: =IFERROR(IF(S70="","",S70/Q70*365),"")
H71: =IFERROR(__xludf.DUMMYFUNCTION("IF(F71="""","""",IFERROR(GOOGLEFINANCE(UPPER(F71),""price""),""""))"),"") | J71: =IF(OR(A71="",E71<>""),"",IFERROR(H71-I71,"")) | P71: =IF(A71="","",IF(A71="Sell",IF(M71="","", (L71-M71)*K71*100),IF(A71="Assigned",IF(L71="","",L71*K71*100),IF(A71="Buy",IF(M71="","",(M71-L71)*K71*100),"")))) | Q71: =IF(E71="","",IF(E71-C71<1,1,E71-C71)) | R71: =IFERROR(IF(P71="","",P71/Q71),"") | S71: =IF(E71="","",IFERROR(IF(N71="",P71/O71,P71/N71),"")) | T71: =IFERROR(IF(S71="","",S71/Q71*365/12),"") | U71: =IFERROR(IF(S71="","",S71/Q71*365),"")
H72: =IFERROR(__xludf.DUMMYFUNCTION("IF(F72="""","""",IFERROR(GOOGLEFINANCE(UPPER(F72),""price""),""""))"),"") | J72: =IF(OR(A72="",E72<>""),"",IFERROR(H72-I72,"")) | P72: =IF(A72="","",IF(A72="Sell",IF(M72="","", (L72-M72)*K72*100),IF(A72="Assigned",IF(L72="","",L72*K72*100),IF(A72="Buy",IF(M72="","",(M72-L72)*K72*100),"")))) | Q72: =IF(E72="","",IF(E72-C72<1,1,E72-C72)) | R72: =IFERROR(IF(P72="","",P72/Q72),"") | S72: =IF(E72="","",IFERROR(IF(N72="",P72/O72,P72/N72),"")) | T72: =IFERROR(IF(S72="","",S72/Q72*365/12),"") | U72: =IFERROR(IF(S72="","",S72/Q72*365),"")
H73: =IFERROR(__xludf.DUMMYFUNCTION("IF(F73="""","""",IFERROR(GOOGLEFINANCE(UPPER(F73),""price""),""""))"),"") | J73: =IF(OR(A73="",E73<>""),"",IFERROR(H73-I73,"")) | P73: =IF(A73="","",IF(A73="Sell",IF(M73="","", (L73-M73)*K73*100),IF(A73="Assigned",IF(L73="","",L73*K73*100),IF(A73="Buy",IF(M73="","",(M73-L73)*K73*100),"")))) | Q73: =IF(E73="","",IF(E73-C73<1,1,E73-C73)) | R73: =IFERROR(IF(P73="","",P73/Q73),"") | S73: =IF(E73="","",IFERROR(IF(N73="",P73/O73,P73/N73),"")) | T73: =IFERROR(IF(S73="","",S73/Q73*365/12),"") | U73: =IFERROR(IF(S73="","",S73/Q73*365),"")
H74: =IFERROR(__xludf.DUMMYFUNCTION("IF(F74="""","""",IFERROR(GOOGLEFINANCE(UPPER(F74),""price""),""""))"),"") | J74: =IF(OR(A74="",E74<>""),"",IFERROR(H74-I74,"")) | P74: =IF(A74="","",IF(A74="Sell",IF(M74="","", (L74-M74)*K74*100),IF(A74="Assigned",IF(L74="","",L74*K74*100),IF(A74="Buy",IF(M74="","",(M74-L74)*K74*100),"")))) | Q74: =IF(E74="","",IF(E74-C74<1,1,E74-C74)) | R74: =IFERROR(IF(P74="","",P74/Q74),"") | S74: =IF(E74="","",IFERROR(IF(N74="",P74/O74,P74/N74),"")) | T74: =IFERROR(IF(S74="","",S74/Q74*365/12),"") | U74: =IFERROR(IF(S74="","",S74/Q74*365),"")
H75: =IFERROR(__xludf.DUMMYFUNCTION("IF(F75="""","""",IFERROR(GOOGLEFINANCE(UPPER(F75),""price""),""""))"),"") | J75: =IF(OR(A75="",E75<>""),"",IFERROR(H75-I75,"")) | P75: =IF(A75="","",IF(A75="Sell",IF(M75="","", (L75-M75)*K75*100),IF(A75="Assigned",IF(L75="","",L75*K75*100),IF(A75="Buy",IF(M75="","",(M75-L75)*K75*100),"")))) | Q75: =IF(E75="","",IF(E75-C75<1,1,E75-C75)) | R75: =IFERROR(IF(P75="","",P75/Q75),"") | S75: =IF(E75="","",IFERROR(IF(N75="",P75/O75,P75/N75),"")) | T75: =IFERROR(IF(S75="","",S75/Q75*365/12),"") | U75: =IFERROR(IF(S75="","",S75/Q75*365),"")
H76: =IFERROR(__xludf.DUMMYFUNCTION("IF(F76="""","""",IFERROR(GOOGLEFINANCE(UPPER(F76),""price""),""""))"),"") | J76: =IF(OR(A76="",E76<>""),"",IFERROR(H76-I76,"")) | P76: =IF(A76="","",IF(A76="Sell",IF(M76="","", (L76-M76)*K76*100),IF(A76="Assigned",IF(L76="","",L76*K76*100),IF(A76="Buy",IF(M76="","",(M76-L76)*K76*100),"")))) | Q76: =IF(E76="","",IF(E76-C76<1,1,E76-C76)) | R76: =IFERROR(IF(P76="","",P76/Q76),"") | S76: =IF(E76="","",IFERROR(IF(N76="",P76/O76,P76/N76),"")) | T76: =IFERROR(IF(S76="","",S76/Q76*365/12),"") | U76: =IFERROR(IF(S76="","",S76/Q76*365),"")
H77: =IFERROR(__xludf.DUMMYFUNCTION("IF(F77="""","""",IFERROR(GOOGLEFINANCE(UPPER(F77),""price""),""""))"),"") | J77: =IF(OR(A77="",E77<>""),"",IFERROR(H77-I77,"")) | P77: =IF(A77="","",IF(A77="Sell",IF(M77="","", (L77-M77)*K77*100),IF(A77="Assigned",IF(L77="","",L77*K77*100),IF(A77="Buy",IF(M77="","",(M77-L77)*K77*100),"")))) | Q77: =IF(E77="","",IF(E77-C77<1,1,E77-C77)) | R77: =IFERROR(IF(P77="","",P77/Q77),"") | S77: =IF(E77="","",IFERROR(IF(N77="",P77/O77,P77/N77),"")) | T77: =IFERROR(IF(S77="","",S77/Q77*365/12),"") | U77: =IFERROR(IF(S77="","",S77/Q77*365),"")
H78: =IFERROR(__xludf.DUMMYFUNCTION("IF(F78="""","""",IFERROR(GOOGLEFINANCE(UPPER(F78),""price""),""""))"),"") | J78: =IF(OR(A78="",E78<>""),"",IFERROR(H78-I78,"")) | P78: =IF(A78="","",IF(A78="Sell",IF(M78="","", (L78-M78)*K78*100),IF(A78="Assigned",IF(L78="","",L78*K78*100),IF(A78="Buy",IF(M78="","",(M78-L78)*K78*100),"")))) | Q78: =IF(E78="","",IF(E78-C78<1,1,E78-C78)) | R78: =IFERROR(IF(P78="","",P78/Q78),"") | S78: =IF(E78="","",IFERROR(IF(N78="",P78/O78,P78/N78),"")) | T78: =IFERROR(IF(S78="","",S78/Q78*365/12),"") | U78: =IFERROR(IF(S78="","",S78/Q78*365),"")
H79: =IFERROR(__xludf.DUMMYFUNCTION("IF(F79="""","""",IFERROR(GOOGLEFINANCE(UPPER(F79),""price""),""""))"),"") | J79: =IF(OR(A79="",E79<>""),"",IFERROR(H79-I79,"")) | P79: =IF(A79="","",IF(A79="Sell",IF(M79="","", (L79-M79)*K79*100),IF(A79="Assigned",IF(L79="","",L79*K79*100),IF(A79="Buy",IF(M79="","",(M79-L79)*K79*100),"")))) | Q79: =IF(E79="","",IF(E79-C79<1,1,E79-C79)) | R79: =IFERROR(IF(P79="","",P79/Q79),"") | S79: =IF(E79="","",IFERROR(IF(N79="",P79/O79,P79/N79),"")) | T79: =IFERROR(IF(S79="","",S79/Q79*365/12),"") | U79: =IFERROR(IF(S79="","",S79/Q79*365),"")
H80: =IFERROR(__xludf.DUMMYFUNCTION("IF(F80="""","""",IFERROR(GOOGLEFINANCE(UPPER(F80),""price""),""""))"),"") | J80: =IF(OR(A80="",E80<>""),"",IFERROR(H80-I80,"")) | P80: =IF(A80="","",IF(A80="Sell",IF(M80="","", (L80-M80)*K80*100),IF(A80="Assigned",IF(L80="","",L80*K80*100),IF(A80="Buy",IF(M80="","",(M80-L80)*K80*100),"")))) | Q80: =IF(E80="","",IF(E80-C80<1,1,E80-C80)) | R80: =IFERROR(IF(P80="","",P80/Q80),"") | S80: =IF(E80="","",IFERROR(IF(N80="",P80/O80,P80/N80),"")) | T80: =IFERROR(IF(S80="","",S80/Q80*365/12),"") | U80: =IFERROR(IF(S80="","",S80/Q80*365),"")
H81: =IFERROR(__xludf.DUMMYFUNCTION("IF(F81="""","""",IFERROR(GOOGLEFINANCE(UPPER(F81),""price""),""""))"),"") | J81: =IF(OR(A81="",E81<>""),"",IFERROR(H81-I81,"")) | P81: =IF(A81="","",IF(A81="Sell",IF(M81="","", (L81-M81)*K81*100),IF(A81="Assigned",IF(L81="","",L81*K81*100),IF(A81="Buy",IF(M81="","",(M81-L81)*K81*100),"")))) | Q81: =IF(E81="","",IF(E81-C81<1,1,E81-C81)) | R81: =IFERROR(IF(P81="","",P81/Q81),"") | S81: =IF(E81="","",IFERROR(IF(N81="",P81/O81,P81/N81),"")) | T81: =IFERROR(IF(S81="","",S81/Q81*365/12),"") | U81: =IFERROR(IF(S81="","",S81/Q81*365),"")
H82: =IFERROR(__xludf.DUMMYFUNCTION("IF(F82="""","""",IFERROR(GOOGLEFINANCE(UPPER(F82),""price""),""""))"),"") | J82: =IF(OR(A82="",E82<>""),"",IFERROR(H82-I82,"")) | P82: =IF(A82="","",IF(A82="Sell",IF(M82="","", (L82-M82)*K82*100),IF(A82="Assigned",IF(L82="","",L82*K82*100),IF(A82="Buy",IF(M82="","",(M82-L82)*K82*100),"")))) | Q82: =IF(E82="","",IF(E82-C82<1,1,E82-C82)) | R82: =IFERROR(IF(P82="","",P82/Q82),"") | S82: =IF(E82="","",IFERROR(IF(N82="",P82/O82,P82/N82),"")) | T82: =IFERROR(IF(S82="","",S82/Q82*365/12),"") | U82: =IFERROR(IF(S82="","",S82/Q82*365),"")
H83: =IFERROR(__xludf.DUMMYFUNCTION("IF(F83="""","""",IFERROR(GOOGLEFINANCE(UPPER(F83),""price""),""""))"),"") | J83: =IF(OR(A83="",E83<>""),"",IFERROR(H83-I83,"")) | P83: =IF(A83="","",IF(A83="Sell",IF(M83="","", (L83-M83)*K83*100),IF(A83="Assigned",IF(L83="","",L83*K83*100),IF(A83="Buy",IF(M83="","",(M83-L83)*K83*100),"")))) | Q83: =IF(E83="","",IF(E83-C83<1,1,E83-C83)) | R83: =IFERROR(IF(P83="","",P83/Q83),"") | S83: =IF(E83="","",IFERROR(IF(N83="",P83/O83,P83/N83),"")) | T83: =IFERROR(IF(S83="","",S83/Q83*365/12),"") | U83: =IFERROR(IF(S83="","",S83/Q83*365),"")
H84: =IFERROR(__xludf.DUMMYFUNCTION("IF(F84="""","""",IFERROR(GOOGLEFINANCE(UPPER(F84),""price""),""""))"),"") | J84: =IF(OR(A84="",E84<>""),"",IFERROR(H84-I84,"")) | P84: =IF(A84="","",IF(A84="Sell",IF(M84="","", (L84-M84)*K84*100),IF(A84="Assigned",IF(L84="","",L84*K84*100),IF(A84="Buy",IF(M84="","",(M84-L84)*K84*100),"")))) | Q84: =IF(E84="","",IF(E84-C84<1,1,E84-C84)) | R84: =IFERROR(IF(P84="","",P84/Q84),"") | S84: =IF(E84="","",IFERROR(IF(N84="",P84/O84,P84/N84),"")) | T84: =IFERROR(IF(S84="","",S84/Q84*365/12),"") | U84: =IFERROR(IF(S84="","",S84/Q84*365),"")
H85: =IFERROR(__xludf.DUMMYFUNCTION("IF(F85="""","""",IFERROR(GOOGLEFINANCE(UPPER(F85),""price""),""""))"),"") | J85: =IF(OR(A85="",E85<>""),"",IFERROR(H85-I85,"")) | P85: =IF(A85="","",IF(A85="Sell",IF(M85="","", (L85-M85)*K85*100),IF(A85="Assigned",IF(L85="","",L85*K85*100),IF(A85="Buy",IF(M85="","",(M85-L85)*K85*100),"")))) | Q85: =IF(E85="","",IF(E85-C85<1,1,E85-C85)) | R85: =IFERROR(IF(P85="","",P85/Q85),"") | S85: =IF(E85="","",IFERROR(IF(N85="",P85/O85,P85/N85),"")) | T85: =IFERROR(IF(S85="","",S85/Q85*365/12),"") | U85: =IFERROR(IF(S85="","",S85/Q85*365),"")
H86: =IFERROR(__xludf.DUMMYFUNCTION("IF(F86="""","""",IFERROR(GOOGLEFINANCE(UPPER(F86),""price""),""""))"),"") | J86: =IF(OR(A86="",E86<>""),"",IFERROR(H86-I86,"")) | P86: =IF(A86="","",IF(A86="Sell",IF(M86="","", (L86-M86)*K86*100),IF(A86="Assigned",IF(L86="","",L86*K86*100),IF(A86="Buy",IF(M86="","",(M86-L86)*K86*100),"")))) | Q86: =IF(E86="","",IF(E86-C86<1,1,E86-C86)) | R86: =IFERROR(IF(P86="","",P86/Q86),"") | S86: =IF(E86="","",IFERROR(IF(N86="",P86/O86,P86/N86),"")) | T86: =IFERROR(IF(S86="","",S86/Q86*365/12),"") | U86: =IFERROR(IF(S86="","",S86/Q86*365),"")
H87: =IFERROR(__xludf.DUMMYFUNCTION("IF(F87="""","""",IFERROR(GOOGLEFINANCE(UPPER(F87),""price""),""""))"),"") | J87: =IF(OR(A87="",E87<>""),"",IFERROR(H87-I87,"")) | P87: =IF(A87="","",IF(A87="Sell",IF(M87="","", (L87-M87)*K87*100),IF(A87="Assigned",IF(L87="","",L87*K87*100),IF(A87="Buy",IF(M87="","",(M87-L87)*K87*100),"")))) | Q87: =IF(E87="","",IF(E87-C87<1,1,E87-C87)) | R87: =IFERROR(IF(P87="","",P87/Q87),"") | S87: =IF(E87="","",IFERROR(IF(N87="",P87/O87,P87/N87),"")) | T87: =IFERROR(IF(S87="","",S87/Q87*365/12),"") | U87: =IFERROR(IF(S87="","",S87/Q87*365),"")
H88: =IFERROR(__xludf.DUMMYFUNCTION("IF(F88="""","""",IFERROR(GOOGLEFINANCE(UPPER(F88),""price""),""""))"),"") | J88: =IF(OR(A88="",E88<>""),"",IFERROR(H88-I88,"")) | P88: =IF(A88="","",IF(A88="Sell",IF(M88="","", (L88-M88)*K88*100),IF(A88="Assigned",IF(L88="","",L88*K88*100),IF(A88="Buy",IF(M88="","",(M88-L88)*K88*100),"")))) | Q88: =IF(E88="","",IF(E88-C88<1,1,E88-C88)) | R88: =IFERROR(IF(P88="","",P88/Q88),"") | S88: =IF(E88="","",IFERROR(IF(N88="",P88/O88,P88/N88),"")) | T88: =IFERROR(IF(S88="","",S88/Q88*365/12),"") | U88: =IFERROR(IF(S88="","",S88/Q88*365),"")
H89: =IFERROR(__xludf.DUMMYFUNCTION("IF(F89="""","""",IFERROR(GOOGLEFINANCE(UPPER(F89),""price""),""""))"),"") | J89: =IF(OR(A89="",E89<>""),"",IFERROR(H89-I89,"")) | P89: =IF(A89="","",IF(A89="Sell",IF(M89="","", (L89-M89)*K89*100),IF(A89="Assigned",IF(L89="","",L89*K89*100),IF(A89="Buy",IF(M89="","",(M89-L89)*K89*100),"")))) | Q89: =IF(E89="","",IF(E89-C89<1,1,E89-C89)) | R89: =IFERROR(IF(P89="","",P89/Q89),"") | S89: =IF(E89="","",IFERROR(IF(N89="",P89/O89,P89/N89),"")) | T89: =IFERROR(IF(S89="","",S89/Q89*365/12),"") | U89: =IFERROR(IF(S89="","",S89/Q89*365),"")
H90: =IFERROR(__xludf.DUMMYFUNCTION("IF(F90="""","""",IFERROR(GOOGLEFINANCE(UPPER(F90),""price""),""""))"),"") | J90: =IF(OR(A90="",E90<>""),"",IFERROR(H90-I90,"")) | P90: =IF(A90="","",IF(A90="Sell",IF(M90="","", (L90-M90)*K90*100),IF(A90="Assigned",IF(L90="","",L90*K90*100),IF(A90="Buy",IF(M90="","",(M90-L90)*K90*100),"")))) | Q90: =IF(E90="","",IF(E90-C90<1,1,E90-C90)) | R90: =IFERROR(IF(P90="","",P90/Q90),"") | S90: =IF(E90="","",IFERROR(IF(N90="",P90/O90,P90/N90),"")) | T90: =IFERROR(IF(S90="","",S90/Q90*365/12),"") | U90: =IFERROR(IF(S90="","",S90/Q90*365),"")
H91: =IFERROR(__xludf.DUMMYFUNCTION("IF(F91="""","""",IFERROR(GOOGLEFINANCE(UPPER(F91),""price""),""""))"),"") | J91: =IF(OR(A91="",E91<>""),"",IFERROR(H91-I91,"")) | P91: =IF(A91="","",IF(A91="Sell",IF(M91="","", (L91-M91)*K91*100),IF(A91="Assigned",IF(L91="","",L91*K91*100),IF(A91="Buy",IF(M91="","",(M91-L91)*K91*100),"")))) | Q91: =IF(E91="","",IF(E91-C91<1,1,E91-C91)) | R91: =IFERROR(IF(P91="","",P91/Q91),"") | S91: =IF(E91="","",IFERROR(IF(N91="",P91/O91,P91/N91),"")) | T91: =IFERROR(IF(S91="","",S91/Q91*365/12),"") | U91: =IFERROR(IF(S91="","",S91/Q91*365),"")
H92: =IFERROR(__xludf.DUMMYFUNCTION("IF(F92="""","""",IFERROR(GOOGLEFINANCE(UPPER(F92),""price""),""""))"),"") | J92: =IF(OR(A92="",E92<>""),"",IFERROR(H92-I92,"")) | P92: =IF(A92="","",IF(A92="Sell",IF(M92="","", (L92-M92)*K92*100),IF(A92="Assigned",IF(L92="","",L92*K92*100),IF(A92="Buy",IF(M92="","",(M92-L92)*K92*100),"")))) | Q92: =IF(E92="","",IF(E92-C92<1,1,E92-C92)) | R92: =IFERROR(IF(P92="","",P92/Q92),"") | S92: =IF(E92="","",IFERROR(IF(N92="",P92/O92,P92/N92),"")) | T92: =IFERROR(IF(S92="","",S92/Q92*365/12),"") | U92: =IFERROR(IF(S92="","",S92/Q92*365),"")
H93: =IFERROR(__xludf.DUMMYFUNCTION("IF(F93="""","""",IFERROR(GOOGLEFINANCE(UPPER(F93),""price""),""""))"),"") | J93: =IF(OR(A93="",E93<>""),"",IFERROR(H93-I93,"")) | P93: =IF(A93="","",IF(A93="Sell",IF(M93="","", (L93-M93)*K93*100),IF(A93="Assigned",IF(L93="","",L93*K93*100),IF(A93="Buy",IF(M93="","",(M93-L93)*K93*100),"")))) | Q93: =IF(E93="","",IF(E93-C93<1,1,E93-C93)) | R93: =IFERROR(IF(P93="","",P93/Q93),"") | S93: =IF(E93="","",IFERROR(IF(N93="",P93/O93,P93/N93),"")) | T93: =IFERROR(IF(S93="","",S93/Q93*365/12),"") | U93: =IFERROR(IF(S93="","",S93/Q93*365),"")
H94: =IFERROR(__xludf.DUMMYFUNCTION("IF(F94="""","""",IFERROR(GOOGLEFINANCE(UPPER(F94),""price""),""""))"),"") | J94: =IF(OR(A94="",E94<>""),"",IFERROR(H94-I94,"")) | P94: =IF(A94="","",IF(A94="Sell",IF(M94="","", (L94-M94)*K94*100),IF(A94="Assigned",IF(L94="","",L94*K94*100),IF(A94="Buy",IF(M94="","",(M94-L94)*K94*100),"")))) | Q94: =IF(E94="","",IF(E94-C94<1,1,E94-C94)) | R94: =IFERROR(IF(P94="","",P94/Q94),"") | S94: =IF(E94="","",IFERROR(IF(N94="",P94/O94,P94/N94),"")) | T94: =IFERROR(IF(S94="","",S94/Q94*365/12),"") | U94: =IFERROR(IF(S94="","",S94/Q94*365),"")
H95: =IFERROR(__xludf.DUMMYFUNCTION("IF(F95="""","""",IFERROR(GOOGLEFINANCE(UPPER(F95),""price""),""""))"),"") | J95: =IF(OR(A95="",E95<>""),"",IFERROR(H95-I95,"")) | P95: =IF(A95="","",IF(A95="Sell",IF(M95="","", (L95-M95)*K95*100),IF(A95="Assigned",IF(L95="","",L95*K95*100),IF(A95="Buy",IF(M95="","",(M95-L95)*K95*100),"")))) | Q95: =IF(E95="","",IF(E95-C95<1,1,E95-C95)) | R95: =IFERROR(IF(P95="","",P95/Q95),"") | S95: =IF(E95="","",IFERROR(IF(N95="",P95/O95,P95/N95),"")) | T95: =IFERROR(IF(S95="","",S95/Q95*365/12),"") | U95: =IFERROR(IF(S95="","",S95/Q95*365),"")
H96: =IFERROR(__xludf.DUMMYFUNCTION("IF(F96="""","""",IFERROR(GOOGLEFINANCE(UPPER(F96),""price""),""""))"),"") | J96: =IF(OR(A96="",E96<>""),"",IFERROR(H96-I96,"")) | P96: =IF(A96="","",IF(A96="Sell",IF(M96="","", (L96-M96)*K96*100),IF(A96="Assigned",IF(L96="","",L96*K96*100),IF(A96="Buy",IF(M96="","",(M96-L96)*K96*100),"")))) | Q96: =IF(E96="","",IF(E96-C96<1,1,E96-C96)) | R96: =IFERROR(IF(P96="","",P96/Q96),"") | S96: =IF(E96="","",IFERROR(IF(N96="",P96/O96,P96/N96),"")) | T96: =IFERROR(IF(S96="","",S96/Q96*365/12),"") | U96: =IFERROR(IF(S96="","",S96/Q96*365),"")
H97: =IFERROR(__xludf.DUMMYFUNCTION("IF(F97="""","""",IFERROR(GOOGLEFINANCE(UPPER(F97),""price""),""""))"),"") | J97: =IF(OR(A97="",E97<>""),"",IFERROR(H97-I97,"")) | P97: =IF(A97="","",IF(A97="Sell",IF(M97="","", (L97-M97)*K97*100),IF(A97="Assigned",IF(L97="","",L97*K97*100),IF(A97="Buy",IF(M97="","",(M97-L97)*K97*100),"")))) | Q97: =IF(E97="","",IF(E97-C97<1,1,E97-C97)) | R97: =IFERROR(IF(P97="","",P97/Q97),"") | S97: =IF(E97="","",IFERROR(IF(N97="",P97/O97,P97/N97),"")) | T97: =IFERROR(IF(S97="","",S97/Q97*365/12),"") | U97: =IFERROR(IF(S97="","",S97/Q97*365),"")
H98: =IFERROR(__xludf.DUMMYFUNCTION("IF(F98="""","""",IFERROR(GOOGLEFINANCE(UPPER(F98),""price""),""""))"),"") | J98: =IF(OR(A98="",E98<>""),"",IFERROR(H98-I98,"")) | P98: =IF(A98="","",IF(A98="Sell",IF(M98="","", (L98-M98)*K98*100),IF(A98="Assigned",IF(L98="","",L98*K98*100),IF(A98="Buy",IF(M98="","",(M98-L98)*K98*100),"")))) | Q98: =IF(E98="","",IF(E98-C98<1,1,E98-C98)) | R98: =IFERROR(IF(P98="","",P98/Q98),"") | S98: =IF(E98="","",IFERROR(IF(N98="",P98/O98,P98/N98),"")) | T98: =IFERROR(IF(S98="","",S98/Q98*365/12),"") | U98: =IFERROR(IF(S98="","",S98/Q98*365),"")
H99: =IFERROR(__xludf.DUMMYFUNCTION("IF(F99="""","""",IFERROR(GOOGLEFINANCE(UPPER(F99),""price""),""""))"),"") | J99: =IF(OR(A99="",E99<>""),"",IFERROR(H99-I99,"")) | P99: =IF(A99="","",IF(A99="Sell",IF(M99="","", (L99-M99)*K99*100),IF(A99="Assigned",IF(L99="","",L99*K99*100),IF(A99="Buy",IF(M99="","",(M99-L99)*K99*100),"")))) | Q99: =IF(E99="","",IF(E99-C99<1,1,E99-C99)) | R99: =IFERROR(IF(P99="","",P99/Q99),"") | S99: =IF(E99="","",IFERROR(IF(N99="",P99/O99,P99/N99),"")) | T99: =IFERROR(IF(S99="","",S99/Q99*365/12),"") | U99: =IFERROR(IF(S99="","",S99/Q99*365),"")
H100: =IFERROR(__xludf.DUMMYFUNCTION("IF(F100="""","""",IFERROR(GOOGLEFINANCE(UPPER(F100),""price""),""""))"),"") | J100: =IF(OR(A100="",E100<>""),"",IFERROR(H100-I100,"")) | P100: =IF(A100="","",IF(A100="Sell",IF(M100="","", (L100-M100)*K100*100),IF(A100="Assigned",IF(L100="","",L100*K100*100),IF(A100="Buy",IF(M100="","",(M100-L100)*K100*100),"")))) | Q100: =IF(E100="","",IF(E100-C100<1,1,E100-C100)) | R100: =IFERROR(IF(P100="","",P100/Q100),"") | S100: =IF(E100="","",IFERROR(IF(N100="",P100/O100,P100/N100),"")) | T100: =IFERROR(IF(S100="","",S100/Q100*365/12),"") | U100: =IFERROR(IF(S100="","",S100/Q100*365),"")
...

Sheet Call & Puts
A1: Practical Income Investing - calls & puts
A2: TOTAL PROFIT | E2: =SUM(P5:P304) -> 0 | J2: COLLATERAL USED | N2: =IFERROR(SUMIF(E5:E304,"<>",O5:O304),0) -> 0 | P2: TOTAL ROC | S2: =IFERROR(E2/N2,0) -> 0 | V2: Locked Cells | W2: Manually Enter
A3: WINS | C3: =COUNTIF(P5:P304,">0") -> 0 | D3: LOSSES | F3: =COUNTIF(P5:P304,"<0") -> 0 | H3: WIN RATE | K3: =IFERROR(C3/(C3+F3),0) -> 0 | M3: AVG WIN | O3: =IFERROR(AVERAGEIF(P5:P304,">0"),0) -> 0 | Q3: AVG LOSS | S3: =IFERROR(AVERAGEIF(P5:P304,"<0"),0) -> 0 | V3: Cell Use Guide
A4: TYPE | B4: STRATEGY | C4: OPEN DATE | D4: EXP DATE | E4: CLOSE DATE | F4: TICKER | G4: BROKERAGE | H4: TODAY'S PRICE | I4: STRIKE $ | J4: BREACH ALERT | K4: QTY | L4: PREMIUM $ | M4: CLOSE $ | N4: CC COLLATERAL | O4: COLLATERAL $ | P4: P / L | Q4: #DAYS | R4: PROFIT PER DAY | S4: RETURN ON CAPITAL | T4: MONTHLY RETURN % | U4: ANNUAL RETURN % | V4: NOTES
H5: =IFERROR(__xludf.DUMMYFUNCTION("IF(F5="""","""",IFERROR(GOOGLEFINANCE(UPPER(F5),""price""),""""))"),"") | J5: =IF(OR(A5="",E5<>""),"",IFERROR(H5-I5,"")) | O5: =IF(A5="Buy",IF(L5="","",L5*K5*100),IF(A5="Assigned",IF(L5="","",L5*K5*100),IF(A5="Sell",IF(OR(I5="",K5=""),"",I5*K5*100),""))) | P5: =IF(M5="","",IF(A5="Sell",(L5-M5)*K5*100,IF(OR(A5="Buy",A5="Assigned"),(M5-L5)*K5*100,""))) | Q5: =IF(E5="","",IF(E5-C5<1,1,E5-C5)) | R5: =IFERROR(IF(P5="","",P5/Q5),"") | S5: =IF(E5="","",IFERROR(IF(N5="",P5/O5,P5/N5),"")) | T5: =IFERROR(IF(S5="","",S5/Q5*365/12),"") | U5: =IFERROR(IF(S5="","",S5/Q5*365),"")
H6: =IFERROR(__xludf.DUMMYFUNCTION("IF(F6="""","""",IFERROR(GOOGLEFINANCE(UPPER(F6),""price""),""""))"),"") | J6: =IF(OR(A6="",E6<>""),"",IFERROR(H6-I6,"")) | O6: =IF(A6="Buy",IF(L6="","",L6*K6*100),IF(A6="Assigned",IF(L6="","",L6*K6*100),IF(A6="Sell",IF(OR(I6="",K6=""),"",I6*K6*100),""))) | P6: =IF(M6="","",IF(A6="Sell",(L6-M6)*K6*100,IF(OR(A6="Buy",A6="Assigned"),(M6-L6)*K6*100,""))) | Q6: =IF(E6="","",IF(E6-C6<1,1,E6-C6)) | R6: =IFERROR(IF(P6="","",P6/Q6),"") | S6: =IF(E6="","",IFERROR(IF(N6="",P6/O6,P6/N6),"")) | T6: =IFERROR(IF(S6="","",S6/Q6*365/12),"") | U6: =IFERROR(IF(S6="","",S6/Q6*365),"")
H7: =IFERROR(__xludf.DUMMYFUNCTION("IF(F7="""","""",IFERROR(GOOGLEFINANCE(UPPER(F7),""price""),""""))"),"") | J7: =IF(OR(A7="",E7<>""),"",IFERROR(H7-I7,"")) | O7: =IF(A7="Buy",IF(L7="","",L7*K7*100),IF(A7="Assigned",IF(L7="","",L7*K7*100),IF(A7="Sell",IF(OR(I7="",K7=""),"",I7*K7*100),""))) | P7: =IF(M7="","",IF(A7="Sell",(L7-M7)*K7*100,IF(OR(A7="Buy",A7="Assigned"),(M7-L7)*K7*100,""))) | Q7: =IF(E7="","",IF(E7-C7<1,1,E7-C7)) | R7: =IFERROR(IF(P7="","",P7/Q7),"") | S7: =IF(E7="","",IFERROR(IF(N7="",P7/O7,P7/N7),"")) | T7: =IFERROR(IF(S7="","",S7/Q7*365/12),"") | U7: =IFERROR(IF(S7="","",S7/Q7*365),"")
H8: =IFERROR(__xludf.DUMMYFUNCTION("IF(F8="""","""",IFERROR(GOOGLEFINANCE(UPPER(F8),""price""),""""))"),"") | J8: =IF(OR(A8="",E8<>""),"",IFERROR(H8-I8,"")) | O8: =IF(A8="Buy",IF(L8="","",L8*K8*100),IF(A8="Assigned",IF(L8="","",L8*K8*100),IF(A8="Sell",IF(OR(I8="",K8=""),"",I8*K8*100),""))) | P8: =IF(M8="","",IF(A8="Sell",(L8-M8)*K8*100,IF(OR(A8="Buy",A8="Assigned"),(M8-L8)*K8*100,""))) | Q8: =IF(E8="","",IF(E8-C8<1,1,E8-C8)) | R8: =IFERROR(IF(P8="","",P8/Q8),"") | S8: =IF(E8="","",IFERROR(IF(N8="",P8/O8,P8/N8),"")) | T8: =IFERROR(IF(S8="","",S8/Q8*365/12),"") | U8: =IFERROR(IF(S8="","",S8/Q8*365),"")
H9: =IFERROR(__xludf.DUMMYFUNCTION("IF(F9="""","""",IFERROR(GOOGLEFINANCE(UPPER(F9),""price""),""""))"),"") | J9: =IF(OR(A9="",E9<>""),"",IFERROR(H9-I9,"")) | O9: =IF(A9="Buy",IF(L9="","",L9*K9*100),IF(A9="Assigned",IF(L9="","",L9*K9*100),IF(A9="Sell",IF(OR(I9="",K9=""),"",I9*K9*100),""))) | P9: =IF(M9="","",IF(A9="Sell",(L9-M9)*K9*100,IF(OR(A9="Buy",A9="Assigned"),(M9-L9)*K9*100,""))) | Q9: =IF(E9="","",IF(E9-C9<1,1,E9-C9)) | R9: =IFERROR(IF(P9="","",P9/Q9),"") | S9: =IF(E9="","",IFERROR(IF(N9="",P9/O9,P9/N9),"")) | T9: =IFERROR(IF(S9="","",S9/Q9*365/12),"") | U9: =IFERROR(IF(S9="","",S9/Q9*365),"")
H10: =IFERROR(__xludf.DUMMYFUNCTION("IF(F10="""","""",IFERROR(GOOGLEFINANCE(UPPER(F10),""price""),""""))"),"") | J10: =IF(OR(A10="",E10<>""),"",IFERROR(H10-I10,"")) | O10: =IF(A10="Buy",IF(L10="","",L10*K10*100),IF(A10="Assigned",IF(L10="","",L10*K10*100),IF(A10="Sell",IF(OR(I10="",K10=""),"",I10*K10*100),""))) | P10: =IF(M10="","",IF(A10="Sell",(L10-M10)*K10*100,IF(OR(A10="Buy",A10="Assigned"),(M10-L10)*K10*100,""))) | Q10: =IF(E10="","",IF(E10-C10<1,1,E10-C10)) | R10: =IFERROR(IF(P10="","",P10/Q10),"") | S10: =IF(E10="","",IFERROR(IF(N10="",P10/O10,P10/N10),"")) | T10: =IFERROR(IF(S10="","",S10/Q10*365/12),"") | U10: =IFERROR(IF(S10="","",S10/Q10*365),"")
H11: =IFERROR(__xludf.DUMMYFUNCTION("IF(F11="""","""",IFERROR(GOOGLEFINANCE(UPPER(F11),""price""),""""))"),"") | J11: =IF(OR(A11="",E11<>""),"",IFERROR(H11-I11,"")) | O11: =IF(A11="Buy",IF(L11="","",L11*K11*100),IF(A11="Assigned",IF(L11="","",L11*K11*100),IF(A11="Sell",IF(OR(I11="",K11=""),"",I11*K11*100),""))) | P11: =IF(M11="","",IF(A11="Sell",(L11-M11)*K11*100,IF(OR(A11="Buy",A11="Assigned"),(M11-L11)*K11*100,""))) | Q11: =IF(E11="","",IF(E11-C11<1,1,E11-C11)) | R11: =IFERROR(IF(P11="","",P11/Q11),"") | S11: =IF(E11="","",IFERROR(IF(N11="",P11/O11,P11/N11),"")) | T11: =IFERROR(IF(S11="","",S11/Q11*365/12),"") | U11: =IFERROR(IF(S11="","",S11/Q11*365),"")
H12: =IFERROR(__xludf.DUMMYFUNCTION("IF(F12="""","""",IFERROR(GOOGLEFINANCE(UPPER(F12),""price""),""""))"),"") | J12: =IF(OR(A12="",E12<>""),"",IFERROR(H12-I12,"")) | O12: =IF(A12="Buy",IF(L12="","",L12*K12*100),IF(A12="Assigned",IF(L12="","",L12*K12*100),IF(A12="Sell",IF(OR(I12="",K12=""),"",I12*K12*100),""))) | P12: =IF(M12="","",IF(A12="Sell",(L12-M12)*K12*100,IF(OR(A12="Buy",A12="Assigned"),(M12-L12)*K12*100,""))) | Q12: =IF(E12="","",IF(E12-C12<1,1,E12-C12)) | R12: =IFERROR(IF(P12="","",P12/Q12),"") | S12: =IF(E12="","",IFERROR(IF(N12="",P12/O12,P12/N12),"")) | T12: =IFERROR(IF(S12="","",S12/Q12*365/12),"") | U12: =IFERROR(IF(S12="","",S12/Q12*365),"")
H13: =IFERROR(__xludf.DUMMYFUNCTION("IF(F13="""","""",IFERROR(GOOGLEFINANCE(UPPER(F13),""price""),""""))"),"") | J13: =IF(OR(A13="",E13<>""),"",IFERROR(H13-I13,"")) | O13: =IF(A13="Buy",IF(L13="","",L13*K13*100),IF(A13="Assigned",IF(L13="","",L13*K13*100),IF(A13="Sell",IF(OR(I13="",K13=""),"",I13*K13*100),""))) | P13: =IF(M13="","",IF(A13="Sell",(L13-M13)*K13*100,IF(OR(A13="Buy",A13="Assigned"),(M13-L13)*K13*100,""))) | Q13: =IF(E13="","",IF(E13-C13<1,1,E13-C13)) | R13: =IFERROR(IF(P13="","",P13/Q13),"") | S13: =IF(E13="","",IFERROR(IF(N13="",P13/O13,P13/N13),"")) | T13: =IFERROR(IF(S13="","",S13/Q13*365/12),"") | U13: =IFERROR(IF(S13="","",S13/Q13*365),"")
H14: =IFERROR(__xludf.DUMMYFUNCTION("IF(F14="""","""",IFERROR(GOOGLEFINANCE(UPPER(F14),""price""),""""))"),"") | J14: =IF(OR(A14="",E14<>""),"",IFERROR(H14-I14,"")) | O14: =IF(A14="Buy",IF(L14="","",L14*K14*100),IF(A14="Assigned",IF(L14="","",L14*K14*100),IF(A14="Sell",IF(OR(I14="",K14=""),"",I14*K14*100),""))) | P14: =IF(M14="","",IF(A14="Sell",(L14-M14)*K14*100,IF(OR(A14="Buy",A14="Assigned"),(M14-L14)*K14*100,""))) | Q14: =IF(E14="","",IF(E14-C14<1,1,E14-C14)) | R14: =IFERROR(IF(P14="","",P14/Q14),"") | S14: =IF(E14="","",IFERROR(IF(N14="",P14/O14,P14/N14),"")) | T14: =IFERROR(IF(S14="","",S14/Q14*365/12),"") | U14: =IFERROR(IF(S14="","",S14/Q14*365),"")
H15: =IFERROR(__xludf.DUMMYFUNCTION("IF(F15="""","""",IFERROR(GOOGLEFINANCE(UPPER(F15),""price""),""""))"),"") | J15: =IF(OR(A15="",E15<>""),"",IFERROR(H15-I15,"")) | O15: =IF(A15="Buy",IF(L15="","",L15*K15*100),IF(A15="Assigned",IF(L15="","",L15*K15*100),IF(A15="Sell",IF(OR(I15="",K15=""),"",I15*K15*100),""))) | P15: =IF(M15="","",IF(A15="Sell",(L15-M15)*K15*100,IF(OR(A15="Buy",A15="Assigned"),(M15-L15)*K15*100,""))) | Q15: =IF(E15="","",IF(E15-C15<1,1,E15-C15)) | R15: =IFERROR(IF(P15="","",P15/Q15),"") | S15: =IF(E15="","",IFERROR(IF(N15="",P15/O15,P15/N15),"")) | T15: =IFERROR(IF(S15="","",S15/Q15*365/12),"") | U15: =IFERROR(IF(S15="","",S15/Q15*365),"")
H16: =IFERROR(__xludf.DUMMYFUNCTION("IF(F16="""","""",IFERROR(GOOGLEFINANCE(UPPER(F16),""price""),""""))"),"") | J16: =IF(OR(A16="",E16<>""),"",IFERROR(H16-I16,"")) | O16: =IF(A16="Buy",IF(L16="","",L16*K16*100),IF(A16="Assigned",IF(L16="","",L16*K16*100),IF(A16="Sell",IF(OR(I16="",K16=""),"",I16*K16*100),""))) | P16: =IF(M16="","",IF(A16="Sell",(L16-M16)*K16*100,IF(OR(A16="Buy",A16="Assigned"),(M16-L16)*K16*100,""))) | Q16: =IF(E16="","",IF(E16-C16<1,1,E16-C16)) | R16: =IFERROR(IF(P16="","",P16/Q16),"") | S16: =IF(E16="","",IFERROR(IF(N16="",P16/O16,P16/N16),"")) | T16: =IFERROR(IF(S16="","",S16/Q16*365/12),"") | U16: =IFERROR(IF(S16="","",S16/Q16*365),"")
H17: =IFERROR(__xludf.DUMMYFUNCTION("IF(F17="""","""",IFERROR(GOOGLEFINANCE(UPPER(F17),""price""),""""))"),"") | J17: =IF(OR(A17="",E17<>""),"",IFERROR(H17-I17,"")) | O17: =IF(A17="Buy",IF(L17="","",L17*K17*100),IF(A17="Assigned",IF(L17="","",L17*K17*100),IF(A17="Sell",IF(OR(I17="",K17=""),"",I17*K17*100),""))) | P17: =IF(M17="","",IF(A17="Sell",(L17-M17)*K17*100,IF(OR(A17="Buy",A17="Assigned"),(M17-L17)*K17*100,""))) | Q17: =IF(E17="","",IF(E17-C17<1,1,E17-C17)) | R17: =IFERROR(IF(P17="","",P17/Q17),"") | S17: =IF(E17="","",IFERROR(IF(N17="",P17/O17,P17/N17),"")) | T17: =IFERROR(IF(S17="","",S17/Q17*365/12),"") | U17: =IFERROR(IF(S17="","",S17/Q17*365),"")
H18: =IFERROR(__xludf.DUMMYFUNCTION("IF(F18="""","""",IFERROR(GOOGLEFINANCE(UPPER(F18),""price""),""""))"),"") | J18: =IF(OR(A18="",E18<>""),"",IFERROR(H18-I18,"")) | O18: =IF(A18="Buy",IF(L18="","",L18*K18*100),IF(A18="Assigned",IF(L18="","",L18*K18*100),IF(A18="Sell",IF(OR(I18="",K18=""),"",I18*K18*100),""))) | P18: =IF(M18="","",IF(A18="Sell",(L18-M18)*K18*100,IF(OR(A18="Buy",A18="Assigned"),(M18-L18)*K18*100,""))) | Q18: =IF(E18="","",IF(E18-C18<1,1,E18-C18)) | R18: =IFERROR(IF(P18="","",P18/Q18),"") | S18: =IF(E18="","",IFERROR(IF(N18="",P18/O18,P18/N18),"")) | T18: =IFERROR(IF(S18="","",S18/Q18*365/12),"") | U18: =IFERROR(IF(S18="","",S18/Q18*365),"")
H19: =IFERROR(__xludf.DUMMYFUNCTION("IF(F19="""","""",IFERROR(GOOGLEFINANCE(UPPER(F19),""price""),""""))"),"") | J19: =IF(OR(A19="",E19<>""),"",IFERROR(H19-I19,"")) | O19: =IF(A19="Buy",IF(L19="","",L19*K19*100),IF(A19="Assigned",IF(L19="","",L19*K19*100),IF(A19="Sell",IF(OR(I19="",K19=""),"",I19*K19*100),""))) | P19: =IF(M19="","",IF(A19="Sell",(L19-M19)*K19*100,IF(OR(A19="Buy",A19="Assigned"),(M19-L19)*K19*100,""))) | Q19: =IF(E19="","",IF(E19-C19<1,1,E19-C19)) | R19: =IFERROR(IF(P19="","",P19/Q19),"") | S19: =IF(E19="","",IFERROR(IF(N19="",P19/O19,P19/N19),"")) | T19: =IFERROR(IF(S19="","",S19/Q19*365/12),"") | U19: =IFERROR(IF(S19="","",S19/Q19*365),"")
H20: =IFERROR(__xludf.DUMMYFUNCTION("IF(F20="""","""",IFERROR(GOOGLEFINANCE(UPPER(F20),""price""),""""))"),"") | J20: =IF(OR(A20="",E20<>""),"",IFERROR(H20-I20,"")) | O20: =IF(A20="Buy",IF(L20="","",L20*K20*100),IF(A20="Assigned",IF(L20="","",L20*K20*100),IF(A20="Sell",IF(OR(I20="",K20=""),"",I20*K20*100),""))) | P20: =IF(M20="","",IF(A20="Sell",(L20-M20)*K20*100,IF(OR(A20="Buy",A20="Assigned"),(M20-L20)*K20*100,""))) | Q20: =IF(E20="","",IF(E20-C20<1,1,E20-C20)) | R20: =IFERROR(IF(P20="","",P20/Q20),"") | S20: =IF(E20="","",IFERROR(IF(N20="",P20/O20,P20/N20),"")) | T20: =IFERROR(IF(S20="","",S20/Q20*365/12),"") | U20: =IFERROR(IF(S20="","",S20/Q20*365),"")
H21: =IFERROR(__xludf.DUMMYFUNCTION("IF(F21="""","""",IFERROR(GOOGLEFINANCE(UPPER(F21),""price""),""""))"),"") | J21: =IF(OR(A21="",E21<>""),"",IFERROR(H21-I21,"")) | O21: =IF(A21="Buy",IF(L21="","",L21*K21*100),IF(A21="Assigned",IF(L21="","",L21*K21*100),IF(A21="Sell",IF(OR(I21="",K21=""),"",I21*K21*100),""))) | P21: =IF(M21="","",IF(A21="Sell",(L21-M21)*K21*100,IF(OR(A21="Buy",A21="Assigned"),(M21-L21)*K21*100,""))) | Q21: =IF(E21="","",IF(E21-C21<1,1,E21-C21)) | R21: =IFERROR(IF(P21="","",P21/Q21),"") | S21: =IF(E21="","",IFERROR(IF(N21="",P21/O21,P21/N21),"")) | T21: =IFERROR(IF(S21="","",S21/Q21*365/12),"") | U21: =IFERROR(IF(S21="","",S21/Q21*365),"")
H22: =IFERROR(__xludf.DUMMYFUNCTION("IF(F22="""","""",IFERROR(GOOGLEFINANCE(UPPER(F22),""price""),""""))"),"") | J22: =IF(OR(A22="",E22<>""),"",IFERROR(H22-I22,"")) | O22: =IF(A22="Buy",IF(L22="","",L22*K22*100),IF(A22="Assigned",IF(L22="","",L22*K22*100),IF(A22="Sell",IF(OR(I22="",K22=""),"",I22*K22*100),""))) | P22: =IF(M22="","",IF(A22="Sell",(L22-M22)*K22*100,IF(OR(A22="Buy",A22="Assigned"),(M22-L22)*K22*100,""))) | Q22: =IF(E22="","",IF(E22-C22<1,1,E22-C22)) | R22: =IFERROR(IF(P22="","",P22/Q22),"") | S22: =IF(E22="","",IFERROR(IF(N22="",P22/O22,P22/N22),"")) | T22: =IFERROR(IF(S22="","",S22/Q22*365/12),"") | U22: =IFERROR(IF(S22="","",S22/Q22*365),"")
H23: =IFERROR(__xludf.DUMMYFUNCTION("IF(F23="""","""",IFERROR(GOOGLEFINANCE(UPPER(F23),""price""),""""))"),"") | J23: =IF(OR(A23="",E23<>""),"",IFERROR(H23-I23,"")) | O23: =IF(A23="Buy",IF(L23="","",L23*K23*100),IF(A23="Assigned",IF(L23="","",L23*K23*100),IF(A23="Sell",IF(OR(I23="",K23=""),"",I23*K23*100),""))) | P23: =IF(M23="","",IF(A23="Sell",(L23-M23)*K23*100,IF(OR(A23="Buy",A23="Assigned"),(M23-L23)*K23*100,""))) | Q23: =IF(E23="","",IF(E23-C23<1,1,E23-C23)) | R23: =IFERROR(IF(P23="","",P23/Q23),"") | S23: =IF(E23="","",IFERROR(IF(N23="",P23/O23,P23/N23),"")) | T23: =IFERROR(IF(S23="","",S23/Q23*365/12),"") | U23: =IFERROR(IF(S23="","",S23/Q23*365),"")
H24: =IFERROR(__xludf.DUMMYFUNCTION("IF(F24="""","""",IFERROR(GOOGLEFINANCE(UPPER(F24),""price""),""""))"),"") | J24: =IF(OR(A24="",E24<>""),"",IFERROR(H24-I24,"")) | O24: =IF(A24="Buy",IF(L24="","",L24*K24*100),IF(A24="Assigned",IF(L24="","",L24*K24*100),IF(A24="Sell",IF(OR(I24="",K24=""),"",I24*K24*100),""))) | P24: =IF(M24="","",IF(A24="Sell",(L24-M24)*K24*100,IF(OR(A24="Buy",A24="Assigned"),(M24-L24)*K24*100,""))) | Q24: =IF(E24="","",IF(E24-C24<1,1,E24-C24)) | R24: =IFERROR(IF(P24="","",P24/Q24),"") | S24: =IF(E24="","",IFERROR(IF(N24="",P24/O24,P24/N24),"")) | T24: =IFERROR(IF(S24="","",S24/Q24*365/12),"") | U24: =IFERROR(IF(S24="","",S24/Q24*365),"")
H25: =IFERROR(__xludf.DUMMYFUNCTION("IF(F25="""","""",IFERROR(GOOGLEFINANCE(UPPER(F25),""price""),""""))"),"") | J25: =IF(OR(A25="",E25<>""),"",IFERROR(H25-I25,"")) | O25: =IF(A25="Buy",IF(L25="","",L25*K25*100),IF(A25="Assigned",IF(L25="","",L25*K25*100),IF(A25="Sell",IF(OR(I25="",K25=""),"",I25*K25*100),""))) | P25: =IF(M25="","",IF(A25="Sell",(L25-M25)*K25*100,IF(OR(A25="Buy",A25="Assigned"),(M25-L25)*K25*100,""))) | Q25: =IF(E25="","",IF(E25-C25<1,1,E25-C25)) | R25: =IFERROR(IF(P25="","",P25/Q25),"") | S25: =IF(E25="","",IFERROR(IF(N25="",P25/O25,P25/N25),"")) | T25: =IFERROR(IF(S25="","",S25/Q25*365/12),"") | U25: =IFERROR(IF(S25="","",S25/Q25*365),"")
H26: =IFERROR(__xludf.DUMMYFUNCTION("IF(F26="""","""",IFERROR(GOOGLEFINANCE(UPPER(F26),""price""),""""))"),"") | J26: =IF(OR(A26="",E26<>""),"",IFERROR(H26-I26,"")) | O26: =IF(A26="Buy",IF(L26="","",L26*K26*100),IF(A26="Assigned",IF(L26="","",L26*K26*100),IF(A26="Sell",IF(OR(I26="",K26=""),"",I26*K26*100),""))) | P26: =IF(M26="","",IF(A26="Sell",(L26-M26)*K26*100,IF(OR(A26="Buy",A26="Assigned"),(M26-L26)*K26*100,""))) | Q26: =IF(E26="","",IF(E26-C26<1,1,E26-C26)) | R26: =IFERROR(IF(P26="","",P26/Q26),"") | S26: =IF(E26="","",IFERROR(IF(N26="",P26/O26,P26/N26),"")) | T26: =IFERROR(IF(S26="","",S26/Q26*365/12),"") | U26: =IFERROR(IF(S26="","",S26/Q26*365),"")
H27: =IFERROR(__xludf.DUMMYFUNCTION("IF(F27="""","""",IFERROR(GOOGLEFINANCE(UPPER(F27),""price""),""""))"),"") | J27: =IF(OR(A27="",E27<>""),"",IFERROR(H27-I27,"")) | O27: =IF(A27="Buy",IF(L27="","",L27*K27*100),IF(A27="Assigned",IF(L27="","",L27*K27*100),IF(A27="Sell",IF(OR(I27="",K27=""),"",I27*K27*100),""))) | P27: =IF(M27="","",IF(A27="Sell",(L27-M27)*K27*100,IF(OR(A27="Buy",A27="Assigned"),(M27-L27)*K27*100,""))) | Q27: =IF(E27="","",IF(E27-C27<1,1,E27-C27)) | R27: =IFERROR(IF(P27="","",P27/Q27),"") | S27: =IF(E27="","",IFERROR(IF(N27="",P27/O27,P27/N27),"")) | T27: =IFERROR(IF(S27="","",S27/Q27*365/12),"") | U27: =IFERROR(IF(S27="","",S27/Q27*365),"")
H28: =IFERROR(__xludf.DUMMYFUNCTION("IF(F28="""","""",IFERROR(GOOGLEFINANCE(UPPER(F28),""price""),""""))"),"") | J28: =IF(OR(A28="",E28<>""),"",IFERROR(H28-I28,"")) | O28: =IF(A28="Buy",IF(L28="","",L28*K28*100),IF(A28="Assigned",IF(L28="","",L28*K28*100),IF(A28="Sell",IF(OR(I28="",K28=""),"",I28*K28*100),""))) | P28: =IF(M28="","",IF(A28="Sell",(L28-M28)*K28*100,IF(OR(A28="Buy",A28="Assigned"),(M28-L28)*K28*100,""))) | Q28: =IF(E28="","",IF(E28-C28<1,1,E28-C28)) | R28: =IFERROR(IF(P28="","",P28/Q28),"") | S28: =IF(E28="","",IFERROR(IF(N28="",P28/O28,P28/N28),"")) | T28: =IFERROR(IF(S28="","",S28/Q28*365/12),"") | U28: =IFERROR(IF(S28="","",S28/Q28*365),"")
H29: =IFERROR(__xludf.DUMMYFUNCTION("IF(F29="""","""",IFERROR(GOOGLEFINANCE(UPPER(F29),""price""),""""))"),"") | J29: =IF(OR(A29="",E29<>""),"",IFERROR(H29-I29,"")) | O29: =IF(A29="Buy",IF(L29="","",L29*K29*100),IF(A29="Assigned",IF(L29="","",L29*K29*100),IF(A29="Sell",IF(OR(I29="",K29=""),"",I29*K29*100),""))) | P29: =IF(M29="","",IF(A29="Sell",(L29-M29)*K29*100,IF(OR(A29="Buy",A29="Assigned"),(M29-L29)*K29*100,""))) | Q29: =IF(E29="","",IF(E29-C29<1,1,E29-C29)) | R29: =IFERROR(IF(P29="","",P29/Q29),"") | S29: =IF(E29="","",IFERROR(IF(N29="",P29/O29,P29/N29),"")) | T29: =IFERROR(IF(S29="","",S29/Q29*365/12),"") | U29: =IFERROR(IF(S29="","",S29/Q29*365),"")
H30: =IFERROR(__xludf.DUMMYFUNCTION("IF(F30="""","""",IFERROR(GOOGLEFINANCE(UPPER(F30),""price""),""""))"),"") | J30: =IF(OR(A30="",E30<>""),"",IFERROR(H30-I30,"")) | O30: =IF(A30="Buy",IF(L30="","",L30*K30*100),IF(A30="Assigned",IF(L30="","",L30*K30*100),IF(A30="Sell",IF(OR(I30="",K30=""),"",I30*K30*100),""))) | P30: =IF(M30="","",IF(A30="Sell",(L30-M30)*K30*100,IF(OR(A30="Buy",A30="Assigned"),(M30-L30)*K30*100,""))) | Q30: =IF(E30="","",IF(E30-C30<1,1,E30-C30)) | R30: =IFERROR(IF(P30="","",P30/Q30),"") | S30: =IF(E30="","",IFERROR(IF(N30="",P30/O30,P30/N30),"")) | T30: =IFERROR(IF(S30="","",S30/Q30*365/12),"") | U30: =IFERROR(IF(S30="","",S30/Q30*365),"")
H31: =IFERROR(__xludf.DUMMYFUNCTION("IF(F31="""","""",IFERROR(GOOGLEFINANCE(UPPER(F31),""price""),""""))"),"") | J31: =IF(OR(A31="",E31<>""),"",IFERROR(H31-I31,"")) | O31: =IF(A31="Buy",IF(L31="","",L31*K31*100),IF(A31="Assigned",IF(L31="","",L31*K31*100),IF(A31="Sell",IF(OR(I31="",K31=""),"",I31*K31*100),""))) | P31: =IF(M31="","",IF(A31="Sell",(L31-M31)*K31*100,IF(OR(A31="Buy",A31="Assigned"),(M31-L31)*K31*100,""))) | Q31: =IF(E31="","",IF(E31-C31<1,1,E31-C31)) | R31: =IFERROR(IF(P31="","",P31/Q31),"") | S31: =IF(E31="","",IFERROR(IF(N31="",P31/O31,P31/N31),"")) | T31: =IFERROR(IF(S31="","",S31/Q31*365/12),"") | U31: =IFERROR(IF(S31="","",S31/Q31*365),"")
H32: =IFERROR(__xludf.DUMMYFUNCTION("IF(F32="""","""",IFERROR(GOOGLEFINANCE(UPPER(F32),""price""),""""))"),"") | J32: =IF(OR(A32="",E32<>""),"",IFERROR(H32-I32,"")) | O32: =IF(A32="Buy",IF(L32="","",L32*K32*100),IF(A32="Assigned",IF(L32="","",L32*K32*100),IF(A32="Sell",IF(OR(I32="",K32=""),"",I32*K32*100),""))) | P32: =IF(M32="","",IF(A32="Sell",(L32-M32)*K32*100,IF(OR(A32="Buy",A32="Assigned"),(M32-L32)*K32*100,""))) | Q32: =IF(E32="","",IF(E32-C32<1,1,E32-C32)) | R32: =IFERROR(IF(P32="","",P32/Q32),"") | S32: =IF(E32="","",IFERROR(IF(N32="",P32/O32,P32/N32),"")) | T32: =IFERROR(IF(S32="","",S32/Q32*365/12),"") | U32: =IFERROR(IF(S32="","",S32/Q32*365),"")
H33: =IFERROR(__xludf.DUMMYFUNCTION("IF(F33="""","""",IFERROR(GOOGLEFINANCE(UPPER(F33),""price""),""""))"),"") | J33: =IF(OR(A33="",E33<>""),"",IFERROR(H33-I33,"")) | O33: =IF(A33="Buy",IF(L33="","",L33*K33*100),IF(A33="Assigned",IF(L33="","",L33*K33*100),IF(A33="Sell",IF(OR(I33="",K33=""),"",I33*K33*100),""))) | P33: =IF(M33="","",IF(A33="Sell",(L33-M33)*K33*100,IF(OR(A33="Buy",A33="Assigned"),(M33-L33)*K33*100,""))) | Q33: =IF(E33="","",IF(E33-C33<1,1,E33-C33)) | R33: =IFERROR(IF(P33="","",P33/Q33),"") | S33: =IF(E33="","",IFERROR(IF(N33="",P33/O33,P33/N33),"")) | T33: =IFERROR(IF(S33="","",S33/Q33*365/12),"") | U33: =IFERROR(IF(S33="","",S33/Q33*365),"")
H34: =IFERROR(__xludf.DUMMYFUNCTION("IF(F34="""","""",IFERROR(GOOGLEFINANCE(UPPER(F34),""price""),""""))"),"") | J34: =IF(OR(A34="",E34<>""),"",IFERROR(H34-I34,"")) | O34: =IF(A34="Buy",IF(L34="","",L34*K34*100),IF(A34="Assigned",IF(L34="","",L34*K34*100),IF(A34="Sell",IF(OR(I34="",K34=""),"",I34*K34*100),""))) | P34: =IF(M34="","",IF(A34="Sell",(L34-M34)*K34*100,IF(OR(A34="Buy",A34="Assigned"),(M34-L34)*K34*100,""))) | Q34: =IF(E34="","",IF(E34-C34<1,1,E34-C34)) | R34: =IFERROR(IF(P34="","",P34/Q34),"") | S34: =IF(E34="","",IFERROR(IF(N34="",P34/O34,P34/N34),"")) | T34: =IFERROR(IF(S34="","",S34/Q34*365/12),"") | U34: =IFERROR(IF(S34="","",S34/Q34*365),"")
H35: =IFERROR(__xludf.DUMMYFUNCTION("IF(F35="""","""",IFERROR(GOOGLEFINANCE(UPPER(F35),""price""),""""))"),"") | J35: =IF(OR(A35="",E35<>""),"",IFERROR(H35-I35,"")) | O35: =IF(A35="Buy",IF(L35="","",L35*K35*100),IF(A35="Assigned",IF(L35="","",L35*K35*100),IF(A35="Sell",IF(OR(I35="",K35=""),"",I35*K35*100),""))) | P35: =IF(M35="","",IF(A35="Sell",(L35-M35)*K35*100,IF(OR(A35="Buy",A35="Assigned"),(M35-L35)*K35*100,""))) | Q35: =IF(E35="","",IF(E35-C35<1,1,E35-C35)) | R35: =IFERROR(IF(P35="","",P35/Q35),"") | S35: =IF(E35="","",IFERROR(IF(N35="",P35/O35,P35/N35),"")) | T35: =IFERROR(IF(S35="","",S35/Q35*365/12),"") | U35: =IFERROR(IF(S35="","",S35/Q35*365),"")
H36: =IFERROR(__xludf.DUMMYFUNCTION("IF(F36="""","""",IFERROR(GOOGLEFINANCE(UPPER(F36),""price""),""""))"),"") | J36: =IF(OR(A36="",E36<>""),"",IFERROR(H36-I36,"")) | O36: =IF(A36="Buy",IF(L36="","",L36*K36*100),IF(A36="Assigned",IF(L36="","",L36*K36*100),IF(A36="Sell",IF(OR(I36="",K36=""),"",I36*K36*100),""))) | P36: =IF(M36="","",IF(A36="Sell",(L36-M36)*K36*100,IF(OR(A36="Buy",A36="Assigned"),(M36-L36)*K36*100,""))) | Q36: =IF(E36="","",IF(E36-C36<1,1,E36-C36)) | R36: =IFERROR(IF(P36="","",P36/Q36),"") | S36: =IF(E36="","",IFERROR(IF(N36="",P36/O36,P36/N36),"")) | T36: =IFERROR(IF(S36="","",S36/Q36*365/12),"") | U36: =IFERROR(IF(S36="","",S36/Q36*365),"")
H37: =IFERROR(__xludf.DUMMYFUNCTION("IF(F37="""","""",IFERROR(GOOGLEFINANCE(UPPER(F37),""price""),""""))"),"") | J37: =IF(OR(A37="",E37<>""),"",IFERROR(H37-I37,"")) | O37: =IF(A37="Buy",IF(L37="","",L37*K37*100),IF(A37="Assigned",IF(L37="","",L37*K37*100),IF(A37="Sell",IF(OR(I37="",K37=""),"",I37*K37*100),""))) | P37: =IF(M37="","",IF(A37="Sell",(L37-M37)*K37*100,IF(OR(A37="Buy",A37="Assigned"),(M37-L37)*K37*100,""))) | Q37: =IF(E37="","",IF(E37-C37<1,1,E37-C37)) | R37: =IFERROR(IF(P37="","",P37/Q37),"") | S37: =IF(E37="","",IFERROR(IF(N37="",P37/O37,P37/N37),"")) | T37: =IFERROR(IF(S37="","",S37/Q37*365/12),"") | U37: =IFERROR(IF(S37="","",S37/Q37*365),"")
H38: =IFERROR(__xludf.DUMMYFUNCTION("IF(F38="""","""",IFERROR(GOOGLEFINANCE(UPPER(F38),""price""),""""))"),"") | J38: =IF(OR(A38="",E38<>""),"",IFERROR(H38-I38,"")) | O38: =IF(A38="Buy",IF(L38="","",L38*K38*100),IF(A38="Assigned",IF(L38="","",L38*K38*100),IF(A38="Sell",IF(OR(I38="",K38=""),"",I38*K38*100),""))) | P38: =IF(M38="","",IF(A38="Sell",(L38-M38)*K38*100,IF(OR(A38="Buy",A38="Assigned"),(M38-L38)*K38*100,""))) | Q38: =IF(E38="","",IF(E38-C38<1,1,E38-C38)) | R38: =IFERROR(IF(P38="","",P38/Q38),"") | S38: =IF(E38="","",IFERROR(IF(N38="",P38/O38,P38/N38),"")) | T38: =IFERROR(IF(S38="","",S38/Q38*365/12),"") | U38: =IFERROR(IF(S38="","",S38/Q38*365),"")
H39: =IFERROR(__xludf.DUMMYFUNCTION("IF(F39="""","""",IFERROR(GOOGLEFINANCE(UPPER(F39),""price""),""""))"),"") | J39: =IF(OR(A39="",E39<>""),"",IFERROR(H39-I39,"")) | O39: =IF(A39="Buy",IF(L39="","",L39*K39*100),IF(A39="Assigned",IF(L39="","",L39*K39*100),IF(A39="Sell",IF(OR(I39="",K39=""),"",I39*K39*100),""))) | P39: =IF(M39="","",IF(A39="Sell",(L39-M39)*K39*100,IF(OR(A39="Buy",A39="Assigned"),(M39-L39)*K39*100,""))) | Q39: =IF(E39="","",IF(E39-C39<1,1,E39-C39)) | R39: =IFERROR(IF(P39="","",P39/Q39),"") | S39: =IF(E39="","",IFERROR(IF(N39="",P39/O39,P39/N39),"")) | T39: =IFERROR(IF(S39="","",S39/Q39*365/12),"") | U39: =IFERROR(IF(S39="","",S39/Q39*365),"")
H40: =IFERROR(__xludf.DUMMYFUNCTION("IF(F40="""","""",IFERROR(GOOGLEFINANCE(UPPER(F40),""price""),""""))"),"") | J40: =IF(OR(A40="",E40<>""),"",IFERROR(H40-I40,"")) | O40: =IF(A40="Buy",IF(L40="","",L40*K40*100),IF(A40="Assigned",IF(L40="","",L40*K40*100),IF(A40="Sell",IF(OR(I40="",K40=""),"",I40*K40*100),""))) | P40: =IF(M40="","",IF(A40="Sell",(L40-M40)*K40*100,IF(OR(A40="Buy",A40="Assigned"),(M40-L40)*K40*100,""))) | Q40: =IF(E40="","",IF(E40-C40<1,1,E40-C40)) | R40: =IFERROR(IF(P40="","",P40/Q40),"") | S40: =IF(E40="","",IFERROR(IF(N40="",P40/O40,P40/N40),"")) | T40: =IFERROR(IF(S40="","",S40/Q40*365/12),"") | U40: =IFERROR(IF(S40="","",S40/Q40*365),"")
H41: =IFERROR(__xludf.DUMMYFUNCTION("IF(F41="""","""",IFERROR(GOOGLEFINANCE(UPPER(F41),""price""),""""))"),"") | J41: =IF(OR(A41="",E41<>""),"",IFERROR(H41-I41,"")) | O41: =IF(A41="Buy",IF(L41="","",L41*K41*100),IF(A41="Assigned",IF(L41="","",L41*K41*100),IF(A41="Sell",IF(OR(I41="",K41=""),"",I41*K41*100),""))) | P41: =IF(M41="","",IF(A41="Sell",(L41-M41)*K41*100,IF(OR(A41="Buy",A41="Assigned"),(M41-L41)*K41*100,""))) | Q41: =IF(E41="","",IF(E41-C41<1,1,E41-C41)) | R41: =IFERROR(IF(P41="","",P41/Q41),"") | S41: =IF(E41="","",IFERROR(IF(N41="",P41/O41,P41/N41),"")) | T41: =IFERROR(IF(S41="","",S41/Q41*365/12),"") | U41: =IFERROR(IF(S41="","",S41/Q41*365),"")
H42: =IFERROR(__xludf.DUMMYFUNCTION("IF(F42="""","""",IFERROR(GOOGLEFINANCE(UPPER(F42),""price""),""""))"),"") | J42: =IF(OR(A42="",E42<>""),"",IFERROR(H42-I42,"")) | O42: =IF(A42="Buy",IF(L42="","",L42*K42*100),IF(A42="Assigned",IF(L42="","",L42*K42*100),IF(A42="Sell",IF(OR(I42="",K42=""),"",I42*K42*100),""))) | P42: =IF(M42="","",IF(A42="Sell",(L42-M42)*K42*100,IF(OR(A42="Buy",A42="Assigned"),(M42-L42)*K42*100,""))) | Q42: =IF(E42="","",IF(E42-C42<1,1,E42-C42)) | R42: =IFERROR(IF(P42="","",P42/Q42),"") | S42: =IF(E42="","",IFERROR(IF(N42="",P42/O42,P42/N42),"")) | T42: =IFERROR(IF(S42="","",S42/Q42*365/12),"") | U42: =IFERROR(IF(S42="","",S42/Q42*365),"")
H43: =IFERROR(__xludf.DUMMYFUNCTION("IF(F43="""","""",IFERROR(GOOGLEFINANCE(UPPER(F43),""price""),""""))"),"") | J43: =IF(OR(A43="",E43<>""),"",IFERROR(H43-I43,"")) | O43: =IF(A43="Buy",IF(L43="","",L43*K43*100),IF(A43="Assigned",IF(L43="","",L43*K43*100),IF(A43="Sell",IF(OR(I43="",K43=""),"",I43*K43*100),""))) | P43: =IF(M43="","",IF(A43="Sell",(L43-M43)*K43*100,IF(OR(A43="Buy",A43="Assigned"),(M43-L43)*K43*100,""))) | Q43: =IF(E43="","",IF(E43-C43<1,1,E43-C43)) | R43: =IFERROR(IF(P43="","",P43/Q43),"") | S43: =IF(E43="","",IFERROR(IF(N43="",P43/O43,P43/N43),"")) | T43: =IFERROR(IF(S43="","",S43/Q43*365/12),"") | U43: =IFERROR(IF(S43="","",S43/Q43*365),"")
H44: =IFERROR(__xludf.DUMMYFUNCTION("IF(F44="""","""",IFERROR(GOOGLEFINANCE(UPPER(F44),""price""),""""))"),"") | J44: =IF(OR(A44="",E44<>""),"",IFERROR(H44-I44,"")) | O44: =IF(A44="Buy",IF(L44="","",L44*K44*100),IF(A44="Assigned",IF(L44="","",L44*K44*100),IF(A44="Sell",IF(OR(I44="",K44=""),"",I44*K44*100),""))) | P44: =IF(M44="","",IF(A44="Sell",(L44-M44)*K44*100,IF(OR(A44="Buy",A44="Assigned"),(M44-L44)*K44*100,""))) | Q44: =IF(E44="","",IF(E44-C44<1,1,E44-C44)) | R44: =IFERROR(IF(P44="","",P44/Q44),"") | S44: =IF(E44="","",IFERROR(IF(N44="",P44/O44,P44/N44),"")) | T44: =IFERROR(IF(S44="","",S44/Q44*365/12),"") | U44: =IFERROR(IF(S44="","",S44/Q44*365),"")
H45: =IFERROR(__xludf.DUMMYFUNCTION("IF(F45="""","""",IFERROR(GOOGLEFINANCE(UPPER(F45),""price""),""""))"),"") | J45: =IF(OR(A45="",E45<>""),"",IFERROR(H45-I45,"")) | O45: =IF(A45="Buy",IF(L45="","",L45*K45*100),IF(A45="Assigned",IF(L45="","",L45*K45*100),IF(A45="Sell",IF(OR(I45="",K45=""),"",I45*K45*100),""))) | P45: =IF(M45="","",IF(A45="Sell",(L45-M45)*K45*100,IF(OR(A45="Buy",A45="Assigned"),(M45-L45)*K45*100,""))) | Q45: =IF(E45="","",IF(E45-C45<1,1,E45-C45)) | R45: =IFERROR(IF(P45="","",P45/Q45),"") | S45: =IF(E45="","",IFERROR(IF(N45="",P45/O45,P45/N45),"")) | T45: =IFERROR(IF(S45="","",S45/Q45*365/12),"") | U45: =IFERROR(IF(S45="","",S45/Q45*365),"")
H46: =IFERROR(__xludf.DUMMYFUNCTION("IF(F46="""","""",IFERROR(GOOGLEFINANCE(UPPER(F46),""price""),""""))"),"") | J46: =IF(OR(A46="",E46<>""),"",IFERROR(H46-I46,"")) | O46: =IF(A46="Buy",IF(L46="","",L46*K46*100),IF(A46="Assigned",IF(L46="","",L46*K46*100),IF(A46="Sell",IF(OR(I46="",K46=""),"",I46*K46*100),""))) | P46: =IF(M46="","",IF(A46="Sell",(L46-M46)*K46*100,IF(OR(A46="Buy",A46="Assigned"),(M46-L46)*K46*100,""))) | Q46: =IF(E46="","",IF(E46-C46<1,1,E46-C46)) | R46: =IFERROR(IF(P46="","",P46/Q46),"") | S46: =IF(E46="","",IFERROR(IF(N46="",P46/O46,P46/N46),"")) | T46: =IFERROR(IF(S46="","",S46/Q46*365/12),"") | U46: =IFERROR(IF(S46="","",S46/Q46*365),"")
H47: =IFERROR(__xludf.DUMMYFUNCTION("IF(F47="""","""",IFERROR(GOOGLEFINANCE(UPPER(F47),""price""),""""))"),"") | J47: =IF(OR(A47="",E47<>""),"",IFERROR(H47-I47,"")) | O47: =IF(A47="Buy",IF(L47="","",L47*K47*100),IF(A47="Assigned",IF(L47="","",L47*K47*100),IF(A47="Sell",IF(OR(I47="",K47=""),"",I47*K47*100),""))) | P47: =IF(M47="","",IF(A47="Sell",(L47-M47)*K47*100,IF(OR(A47="Buy",A47="Assigned"),(M47-L47)*K47*100,""))) | Q47: =IF(E47="","",IF(E47-C47<1,1,E47-C47)) | R47: =IFERROR(IF(P47="","",P47/Q47),"") | S47: =IF(E47="","",IFERROR(IF(N47="",P47/O47,P47/N47),"")) | T47: =IFERROR(IF(S47="","",S47/Q47*365/12),"") | U47: =IFERROR(IF(S47="","",S47/Q47*365),"")
H48: =IFERROR(__xludf.DUMMYFUNCTION("IF(F48="""","""",IFERROR(GOOGLEFINANCE(UPPER(F48),""price""),""""))"),"") | J48: =IF(OR(A48="",E48<>""),"",IFERROR(H48-I48,"")) | O48: =IF(A48="Buy",IF(L48="","",L48*K48*100),IF(A48="Assigned",IF(L48="","",L48*K48*100),IF(A48="Sell",IF(OR(I48="",K48=""),"",I48*K48*100),""))) | P48: =IF(M48="","",IF(A48="Sell",(L48-M48)*K48*100,IF(OR(A48="Buy",A48="Assigned"),(M48-L48)*K48*100,""))) | Q48: =IF(E48="","",IF(E48-C48<1,1,E48-C48)) | R48: =IFERROR(IF(P48="","",P48/Q48),"") | S48: =IF(E48="","",IFERROR(IF(N48="",P48/O48,P48/N48),"")) | T48: =IFERROR(IF(S48="","",S48/Q48*365/12),"") | U48: =IFERROR(IF(S48="","",S48/Q48*365),"")
H49: =IFERROR(__xludf.DUMMYFUNCTION("IF(F49="""","""",IFERROR(GOOGLEFINANCE(UPPER(F49),""price""),""""))"),"") | J49: =IF(OR(A49="",E49<>""),"",IFERROR(H49-I49,"")) | O49: =IF(A49="Buy",IF(L49="","",L49*K49*100),IF(A49="Assigned",IF(L49="","",L49*K49*100),IF(A49="Sell",IF(OR(I49="",K49=""),"",I49*K49*100),""))) | P49: =IF(M49="","",IF(A49="Sell",(L49-M49)*K49*100,IF(OR(A49="Buy",A49="Assigned"),(M49-L49)*K49*100,""))) | Q49: =IF(E49="","",IF(E49-C49<1,1,E49-C49)) | R49: =IFERROR(IF(P49="","",P49/Q49),"") | S49: =IF(E49="","",IFERROR(IF(N49="",P49/O49,P49/N49),"")) | T49: =IFERROR(IF(S49="","",S49/Q49*365/12),"") | U49: =IFERROR(IF(S49="","",S49/Q49*365),"")
H50: =IFERROR(__xludf.DUMMYFUNCTION("IF(F50="""","""",IFERROR(GOOGLEFINANCE(UPPER(F50),""price""),""""))"),"") | J50: =IF(OR(A50="",E50<>""),"",IFERROR(H50-I50,"")) | O50: =IF(A50="Buy",IF(L50="","",L50*K50*100),IF(A50="Assigned",IF(L50="","",L50*K50*100),IF(A50="Sell",IF(OR(I50="",K50=""),"",I50*K50*100),""))) | P50: =IF(M50="","",IF(A50="Sell",(L50-M50)*K50*100,IF(OR(A50="Buy",A50="Assigned"),(M50-L50)*K50*100,""))) | Q50: =IF(E50="","",IF(E50-C50<1,1,E50-C50)) | R50: =IFERROR(IF(P50="","",P50/Q50),"") | S50: =IF(E50="","",IFERROR(IF(N50="",P50/O50,P50/N50),"")) | T50: =IFERROR(IF(S50="","",S50/Q50*365/12),"") | U50: =IFERROR(IF(S50="","",S50/Q50*365),"")
H51: =IFERROR(__xludf.DUMMYFUNCTION("IF(F51="""","""",IFERROR(GOOGLEFINANCE(UPPER(F51),""price""),""""))"),"") | J51: =IF(OR(A51="",E51<>""),"",IFERROR(H51-I51,"")) | O51: =IF(A51="Buy",IF(L51="","",L51*K51*100),IF(A51="Assigned",IF(L51="","",L51*K51*100),IF(A51="Sell",IF(OR(I51="",K51=""),"",I51*K51*100),""))) | P51: =IF(M51="","",IF(A51="Sell",(L51-M51)*K51*100,IF(OR(A51="Buy",A51="Assigned"),(M51-L51)*K51*100,""))) | Q51: =IF(E51="","",IF(E51-C51<1,1,E51-C51)) | R51: =IFERROR(IF(P51="","",P51/Q51),"") | S51: =IF(E51="","",IFERROR(IF(N51="",P51/O51,P51/N51),"")) | T51: =IFERROR(IF(S51="","",S51/Q51*365/12),"") | U51: =IFERROR(IF(S51="","",S51/Q51*365),"")
H52: =IFERROR(__xludf.DUMMYFUNCTION("IF(F52="""","""",IFERROR(GOOGLEFINANCE(UPPER(F52),""price""),""""))"),"") | J52: =IF(OR(A52="",E52<>""),"",IFERROR(H52-I52,"")) | O52: =IF(A52="Buy",IF(L52="","",L52*K52*100),IF(A52="Assigned",IF(L52="","",L52*K52*100),IF(A52="Sell",IF(OR(I52="",K52=""),"",I52*K52*100),""))) | P52: =IF(M52="","",IF(A52="Sell",(L52-M52)*K52*100,IF(OR(A52="Buy",A52="Assigned"),(M52-L52)*K52*100,""))) | Q52: =IF(E52="","",IF(E52-C52<1,1,E52-C52)) | R52: =IFERROR(IF(P52="","",P52/Q52),"") | S52: =IF(E52="","",IFERROR(IF(N52="",P52/O52,P52/N52),"")) | T52: =IFERROR(IF(S52="","",S52/Q52*365/12),"") | U52: =IFERROR(IF(S52="","",S52/Q52*365),"")
H53: =IFERROR(__xludf.DUMMYFUNCTION("IF(F53="""","""",IFERROR(GOOGLEFINANCE(UPPER(F53),""price""),""""))"),"") | J53: =IF(OR(A53="",E53<>""),"",IFERROR(H53-I53,"")) | O53: =IF(A53="Buy",IF(L53="","",L53*K53*100),IF(A53="Assigned",IF(L53="","",L53*K53*100),IF(A53="Sell",IF(OR(I53="",K53=""),"",I53*K53*100),""))) | P53: =IF(M53="","",IF(A53="Sell",(L53-M53)*K53*100,IF(OR(A53="Buy",A53="Assigned"),(M53-L53)*K53*100,""))) | Q53: =IF(E53="","",IF(E53-C53<1,1,E53-C53)) | R53: =IFERROR(IF(P53="","",P53/Q53),"") | S53: =IF(E53="","",IFERROR(IF(N53="",P53/O53,P53/N53),"")) | T53: =IFERROR(IF(S53="","",S53/Q53*365/12),"") | U53: =IFERROR(IF(S53="","",S53/Q53*365),"")
H54: =IFERROR(__xludf.DUMMYFUNCTION("IF(F54="""","""",IFERROR(GOOGLEFINANCE(UPPER(F54),""price""),""""))"),"") | J54: =IF(OR(A54="",E54<>""),"",IFERROR(H54-I54,"")) | O54: =IF(A54="Buy",IF(L54="","",L54*K54*100),IF(A54="Assigned",IF(L54="","",L54*K54*100),IF(A54="Sell",IF(OR(I54="",K54=""),"",I54*K54*100),""))) | P54: =IF(M54="","",IF(A54="Sell",(L54-M54)*K54*100,IF(OR(A54="Buy",A54="Assigned"),(M54-L54)*K54*100,""))) | Q54: =IF(E54="","",IF(E54-C54<1,1,E54-C54)) | R54: =IFERROR(IF(P54="","",P54/Q54),"") | S54: =IF(E54="","",IFERROR(IF(N54="",P54/O54,P54/N54),"")) | T54: =IFERROR(IF(S54="","",S54/Q54*365/12),"") | U54: =IFERROR(IF(S54="","",S54/Q54*365),"")
H55: =IFERROR(__xludf.DUMMYFUNCTION("IF(F55="""","""",IFERROR(GOOGLEFINANCE(UPPER(F55),""price""),""""))"),"") | J55: =IF(OR(A55="",E55<>""),"",IFERROR(H55-I55,"")) | O55: =IF(A55="Buy",IF(L55="","",L55*K55*100),IF(A55="Assigned",IF(L55="","",L55*K55*100),IF(A55="Sell",IF(OR(I55="",K55=""),"",I55*K55*100),""))) | P55: =IF(M55="","",IF(A55="Sell",(L55-M55)*K55*100,IF(OR(A55="Buy",A55="Assigned"),(M55-L55)*K55*100,""))) | Q55: =IF(E55="","",IF(E55-C55<1,1,E55-C55)) | R55: =IFERROR(IF(P55="","",P55/Q55),"") | S55: =IF(E55="","",IFERROR(IF(N55="",P55/O55,P55/N55),"")) | T55: =IFERROR(IF(S55="","",S55/Q55*365/12),"") | U55: =IFERROR(IF(S55="","",S55/Q55*365),"")
H56: =IFERROR(__xludf.DUMMYFUNCTION("IF(F56="""","""",IFERROR(GOOGLEFINANCE(UPPER(F56),""price""),""""))"),"") | J56: =IF(OR(A56="",E56<>""),"",IFERROR(H56-I56,"")) | O56: =IF(A56="Buy",IF(L56="","",L56*K56*100),IF(A56="Assigned",IF(L56="","",L56*K56*100),IF(A56="Sell",IF(OR(I56="",K56=""),"",I56*K56*100),""))) | P56: =IF(M56="","",IF(A56="Sell",(L56-M56)*K56*100,IF(OR(A56="Buy",A56="Assigned"),(M56-L56)*K56*100,""))) | Q56: =IF(E56="","",IF(E56-C56<1,1,E56-C56)) | R56: =IFERROR(IF(P56="","",P56/Q56),"") | S56: =IF(E56="","",IFERROR(IF(N56="",P56/O56,P56/N56),"")) | T56: =IFERROR(IF(S56="","",S56/Q56*365/12),"") | U56: =IFERROR(IF(S56="","",S56/Q56*365),"")
H57: =IFERROR(__xludf.DUMMYFUNCTION("IF(F57="""","""",IFERROR(GOOGLEFINANCE(UPPER(F57),""price""),""""))"),"") | J57: =IF(OR(A57="",E57<>""),"",IFERROR(H57-I57,"")) | O57: =IF(A57="Buy",IF(L57="","",L57*K57*100),IF(A57="Assigned",IF(L57="","",L57*K57*100),IF(A57="Sell",IF(OR(I57="",K57=""),"",I57*K57*100),""))) | P57: =IF(M57="","",IF(A57="Sell",(L57-M57)*K57*100,IF(OR(A57="Buy",A57="Assigned"),(M57-L57)*K57*100,""))) | Q57: =IF(E57="","",IF(E57-C57<1,1,E57-C57)) | R57: =IFERROR(IF(P57="","",P57/Q57),"") | S57: =IF(E57="","",IFERROR(IF(N57="",P57/O57,P57/N57),"")) | T57: =IFERROR(IF(S57="","",S57/Q57*365/12),"") | U57: =IFERROR(IF(S57="","",S57/Q57*365),"")
H58: =IFERROR(__xludf.DUMMYFUNCTION("IF(F58="""","""",IFERROR(GOOGLEFINANCE(UPPER(F58),""price""),""""))"),"") | J58: =IF(OR(A58="",E58<>""),"",IFERROR(H58-I58,"")) | O58: =IF(A58="Buy",IF(L58="","",L58*K58*100),IF(A58="Assigned",IF(L58="","",L58*K58*100),IF(A58="Sell",IF(OR(I58="",K58=""),"",I58*K58*100),""))) | P58: =IF(M58="","",IF(A58="Sell",(L58-M58)*K58*100,IF(OR(A58="Buy",A58="Assigned"),(M58-L58)*K58*100,""))) | Q58: =IF(E58="","",IF(E58-C58<1,1,E58-C58)) | R58: =IFERROR(IF(P58="","",P58/Q58),"") | S58: =IF(E58="","",IFERROR(IF(N58="",P58/O58,P58/N58),"")) | T58: =IFERROR(IF(S58="","",S58/Q58*365/12),"") | U58: =IFERROR(IF(S58="","",S58/Q58*365),"")
H59: =IFERROR(__xludf.DUMMYFUNCTION("IF(F59="""","""",IFERROR(GOOGLEFINANCE(UPPER(F59),""price""),""""))"),"") | J59: =IF(OR(A59="",E59<>""),"",IFERROR(H59-I59,"")) | O59: =IF(A59="Buy",IF(L59="","",L59*K59*100),IF(A59="Assigned",IF(L59="","",L59*K59*100),IF(A59="Sell",IF(OR(I59="",K59=""),"",I59*K59*100),""))) | P59: =IF(M59="","",IF(A59="Sell",(L59-M59)*K59*100,IF(OR(A59="Buy",A59="Assigned"),(M59-L59)*K59*100,""))) | Q59: =IF(E59="","",IF(E59-C59<1,1,E59-C59)) | R59: =IFERROR(IF(P59="","",P59/Q59),"") | S59: =IF(E59="","",IFERROR(IF(N59="",P59/O59,P59/N59),"")) | T59: =IFERROR(IF(S59="","",S59/Q59*365/12),"") | U59: =IFERROR(IF(S59="","",S59/Q59*365),"")
H60: =IFERROR(__xludf.DUMMYFUNCTION("IF(F60="""","""",IFERROR(GOOGLEFINANCE(UPPER(F60),""price""),""""))"),"") | J60: =IF(OR(A60="",E60<>""),"",IFERROR(H60-I60,"")) | O60: =IF(A60="Buy",IF(L60="","",L60*K60*100),IF(A60="Assigned",IF(L60="","",L60*K60*100),IF(A60="Sell",IF(OR(I60="",K60=""),"",I60*K60*100),""))) | P60: =IF(M60="","",IF(A60="Sell",(L60-M60)*K60*100,IF(OR(A60="Buy",A60="Assigned"),(M60-L60)*K60*100,""))) | Q60: =IF(E60="","",IF(E60-C60<1,1,E60-C60)) | R60: =IFERROR(IF(P60="","",P60/Q60),"") | S60: =IF(E60="","",IFERROR(IF(N60="",P60/O60,P60/N60),"")) | T60: =IFERROR(IF(S60="","",S60/Q60*365/12),"") | U60: =IFERROR(IF(S60="","",S60/Q60*365),"")
H61: =IFERROR(__xludf.DUMMYFUNCTION("IF(F61="""","""",IFERROR(GOOGLEFINANCE(UPPER(F61),""price""),""""))"),"") | J61: =IF(OR(A61="",E61<>""),"",IFERROR(H61-I61,"")) | O61: =IF(A61="Buy",IF(L61="","",L61*K61*100),IF(A61="Assigned",IF(L61="","",L61*K61*100),IF(A61="Sell",IF(OR(I61="",K61=""),"",I61*K61*100),""))) | P61: =IF(M61="","",IF(A61="Sell",(L61-M61)*K61*100,IF(OR(A61="Buy",A61="Assigned"),(M61-L61)*K61*100,""))) | Q61: =IF(E61="","",IF(E61-C61<1,1,E61-C61)) | R61: =IFERROR(IF(P61="","",P61/Q61),"") | S61: =IF(E61="","",IFERROR(IF(N61="",P61/O61,P61/N61),"")) | T61: =IFERROR(IF(S61="","",S61/Q61*365/12),"") | U61: =IFERROR(IF(S61="","",S61/Q61*365),"")
H62: =IFERROR(__xludf.DUMMYFUNCTION("IF(F62="""","""",IFERROR(GOOGLEFINANCE(UPPER(F62),""price""),""""))"),"") | J62: =IF(OR(A62="",E62<>""),"",IFERROR(H62-I62,"")) | O62: =IF(A62="Buy",IF(L62="","",L62*K62*100),IF(A62="Assigned",IF(L62="","",L62*K62*100),IF(A62="Sell",IF(OR(I62="",K62=""),"",I62*K62*100),""))) | P62: =IF(M62="","",IF(A62="Sell",(L62-M62)*K62*100,IF(OR(A62="Buy",A62="Assigned"),(M62-L62)*K62*100,""))) | Q62: =IF(E62="","",IF(E62-C62<1,1,E62-C62)) | R62: =IFERROR(IF(P62="","",P62/Q62),"") | S62: =IF(E62="","",IFERROR(IF(N62="",P62/O62,P62/N62),"")) | T62: =IFERROR(IF(S62="","",S62/Q62*365/12),"") | U62: =IFERROR(IF(S62="","",S62/Q62*365),"")
H63: =IFERROR(__xludf.DUMMYFUNCTION("IF(F63="""","""",IFERROR(GOOGLEFINANCE(UPPER(F63),""price""),""""))"),"") | J63: =IF(OR(A63="",E63<>""),"",IFERROR(H63-I63,"")) | O63: =IF(A63="Buy",IF(L63="","",L63*K63*100),IF(A63="Assigned",IF(L63="","",L63*K63*100),IF(A63="Sell",IF(OR(I63="",K63=""),"",I63*K63*100),""))) | P63: =IF(M63="","",IF(A63="Sell",(L63-M63)*K63*100,IF(OR(A63="Buy",A63="Assigned"),(M63-L63)*K63*100,""))) | Q63: =IF(E63="","",IF(E63-C63<1,1,E63-C63)) | R63: =IFERROR(IF(P63="","",P63/Q63),"") | S63: =IF(E63="","",IFERROR(IF(N63="",P63/O63,P63/N63),"")) | T63: =IFERROR(IF(S63="","",S63/Q63*365/12),"") | U63: =IFERROR(IF(S63="","",S63/Q63*365),"")
H64: =IFERROR(__xludf.DUMMYFUNCTION("IF(F64="""","""",IFERROR(GOOGLEFINANCE(UPPER(F64),""price""),""""))"),"") | J64: =IF(OR(A64="",E64<>""),"",IFERROR(H64-I64,"")) | O64: =IF(A64="Buy",IF(L64="","",L64*K64*100),IF(A64="Assigned",IF(L64="","",L64*K64*100),IF(A64="Sell",IF(OR(I64="",K64=""),"",I64*K64*100),""))) | P64: =IF(M64="","",IF(A64="Sell",(L64-M64)*K64*100,IF(OR(A64="Buy",A64="Assigned"),(M64-L64)*K64*100,""))) | Q64: =IF(E64="","",IF(E64-C64<1,1,E64-C64)) | R64: =IFERROR(IF(P64="","",P64/Q64),"") | S64: =IF(E64="","",IFERROR(IF(N64="",P64/O64,P64/N64),"")) | T64: =IFERROR(IF(S64="","",S64/Q64*365/12),"") | U64: =IFERROR(IF(S64="","",S64/Q64*365),"")
H65: =IFERROR(__xludf.DUMMYFUNCTION("IF(F65="""","""",IFERROR(GOOGLEFINANCE(UPPER(F65),""price""),""""))"),"") | J65: =IF(OR(A65="",E65<>""),"",IFERROR(H65-I65,"")) | O65: =IF(A65="Buy",IF(L65="","",L65*K65*100),IF(A65="Assigned",IF(L65="","",L65*K65*100),IF(A65="Sell",IF(OR(I65="",K65=""),"",I65*K65*100),""))) | P65: =IF(M65="","",IF(A65="Sell",(L65-M65)*K65*100,IF(OR(A65="Buy",A65="Assigned"),(M65-L65)*K65*100,""))) | Q65: =IF(E65="","",IF(E65-C65<1,1,E65-C65)) | R65: =IFERROR(IF(P65="","",P65/Q65),"") | S65: =IF(E65="","",IFERROR(IF(N65="",P65/O65,P65/N65),"")) | T65: =IFERROR(IF(S65="","",S65/Q65*365/12),"") | U65: =IFERROR(IF(S65="","",S65/Q65*365),"")
H66: =IFERROR(__xludf.DUMMYFUNCTION("IF(F66="""","""",IFERROR(GOOGLEFINANCE(UPPER(F66),""price""),""""))"),"") | J66: =IF(OR(A66="",E66<>""),"",IFERROR(H66-I66,"")) | O66: =IF(A66="Buy",IF(L66="","",L66*K66*100),IF(A66="Assigned",IF(L66="","",L66*K66*100),IF(A66="Sell",IF(OR(I66="",K66=""),"",I66*K66*100),""))) | P66: =IF(M66="","",IF(A66="Sell",(L66-M66)*K66*100,IF(OR(A66="Buy",A66="Assigned"),(M66-L66)*K66*100,""))) | Q66: =IF(E66="","",IF(E66-C66<1,1,E66-C66)) | R66: =IFERROR(IF(P66="","",P66/Q66),"") | S66: =IF(E66="","",IFERROR(IF(N66="",P66/O66,P66/N66),"")) | T66: =IFERROR(IF(S66="","",S66/Q66*365/12),"") | U66: =IFERROR(IF(S66="","",S66/Q66*365),"")
H67: =IFERROR(__xludf.DUMMYFUNCTION("IF(F67="""","""",IFERROR(GOOGLEFINANCE(UPPER(F67),""price""),""""))"),"") | J67: =IF(OR(A67="",E67<>""),"",IFERROR(H67-I67,"")) | O67: =IF(A67="Buy",IF(L67="","",L67*K67*100),IF(A67="Assigned",IF(L67="","",L67*K67*100),IF(A67="Sell",IF(OR(I67="",K67=""),"",I67*K67*100),""))) | P67: =IF(M67="","",IF(A67="Sell",(L67-M67)*K67*100,IF(OR(A67="Buy",A67="Assigned"),(M67-L67)*K67*100,""))) | Q67: =IF(E67="","",IF(E67-C67<1,1,E67-C67)) | R67: =IFERROR(IF(P67="","",P67/Q67),"") | S67: =IF(E67="","",IFERROR(IF(N67="",P67/O67,P67/N67),"")) | T67: =IFERROR(IF(S67="","",S67/Q67*365/12),"") | U67: =IFERROR(IF(S67="","",S67/Q67*365),"")
H68: =IFERROR(__xludf.DUMMYFUNCTION("IF(F68="""","""",IFERROR(GOOGLEFINANCE(UPPER(F68),""price""),""""))"),"") | J68: =IF(OR(A68="",E68<>""),"",IFERROR(H68-I68,"")) | O68: =IF(A68="Buy",IF(L68="","",L68*K68*100),IF(A68="Assigned",IF(L68="","",L68*K68*100),IF(A68="Sell",IF(OR(I68="",K68=""),"",I68*K68*100),""))) | P68: =IF(M68="","",IF(A68="Sell",(L68-M68)*K68*100,IF(OR(A68="Buy",A68="Assigned"),(M68-L68)*K68*100,""))) | Q68: =IF(E68="","",IF(E68-C68<1,1,E68-C68)) | R68: =IFERROR(IF(P68="","",P68/Q68),"") | S68: =IF(E68="","",IFERROR(IF(N68="",P68/O68,P68/N68),"")) | T68: =IFERROR(IF(S68="","",S68/Q68*365/12),"") | U68: =IFERROR(IF(S68="","",S68/Q68*365),"")
H69: =IFERROR(__xludf.DUMMYFUNCTION("IF(F69="""","""",IFERROR(GOOGLEFINANCE(UPPER(F69),""price""),""""))"),"") | J69: =IF(OR(A69="",E69<>""),"",IFERROR(H69-I69,"")) | O69: =IF(A69="Buy",IF(L69="","",L69*K69*100),IF(A69="Assigned",IF(L69="","",L69*K69*100),IF(A69="Sell",IF(OR(I69="",K69=""),"",I69*K69*100),""))) | P69: =IF(M69="","",IF(A69="Sell",(L69-M69)*K69*100,IF(OR(A69="Buy",A69="Assigned"),(M69-L69)*K69*100,""))) | Q69: =IF(E69="","",IF(E69-C69<1,1,E69-C69)) | R69: =IFERROR(IF(P69="","",P69/Q69),"") | S69: =IF(E69="","",IFERROR(IF(N69="",P69/O69,P69/N69),"")) | T69: =IFERROR(IF(S69="","",S69/Q69*365/12),"") | U69: =IFERROR(IF(S69="","",S69/Q69*365),"")
H70: =IFERROR(__xludf.DUMMYFUNCTION("IF(F70="""","""",IFERROR(GOOGLEFINANCE(UPPER(F70),""price""),""""))"),"") | J70: =IF(OR(A70="",E70<>""),"",IFERROR(H70-I70,"")) | O70: =IF(A70="Buy",IF(L70="","",L70*K70*100),IF(A70="Assigned",IF(L70="","",L70*K70*100),IF(A70="Sell",IF(OR(I70="",K70=""),"",I70*K70*100),""))) | P70: =IF(M70="","",IF(A70="Sell",(L70-M70)*K70*100,IF(OR(A70="Buy",A70="Assigned"),(M70-L70)*K70*100,""))) | Q70: =IF(E70="","",IF(E70-C70<1,1,E70-C70)) | R70: =IFERROR(IF(P70="","",P70/Q70),"") | S70: =IF(E70="","",IFERROR(IF(N70="",P70/O70,P70/N70),"")) | T70: =IFERROR(IF(S70="","",S70/Q70*365/12),"") | U70: =IFERROR(IF(S70="","",S70/Q70*365),"")
H71: =IFERROR(__xludf.DUMMYFUNCTION("IF(F71="""","""",IFERROR(GOOGLEFINANCE(UPPER(F71),""price""),""""))"),"") | J71: =IF(OR(A71="",E71<>""),"",IFERROR(H71-I71,"")) | O71: =IF(A71="Buy",IF(L71="","",L71*K71*100),IF(A71="Assigned",IF(L71="","",L71*K71*100),IF(A71="Sell",IF(OR(I71="",K71=""),"",I71*K71*100),""))) | P71: =IF(M71="","",IF(A71="Sell",(L71-M71)*K71*100,IF(OR(A71="Buy",A71="Assigned"),(M71-L71)*K71*100,""))) | Q71: =IF(E71="","",IF(E71-C71<1,1,E71-C71)) | R71: =IFERROR(IF(P71="","",P71/Q71),"") | S71: =IF(E71="","",IFERROR(IF(N71="",P71/O71,P71/N71),"")) | T71: =IFERROR(IF(S71="","",S71/Q71*365/12),"") | U71: =IFERROR(IF(S71="","",S71/Q71*365),"")
H72: =IFERROR(__xludf.DUMMYFUNCTION("IF(F72="""","""",IFERROR(GOOGLEFINANCE(UPPER(F72),""price""),""""))"),"") | J72: =IF(OR(A72="",E72<>""),"",IFERROR(H72-I72,"")) | O72: =IF(A72="Buy",IF(L72="","",L72*K72*100),IF(A72="Assigned",IF(L72="","",L72*K72*100),IF(A72="Sell",IF(OR(I72="",K72=""),"",I72*K72*100),""))) | P72: =IF(M72="","",IF(A72="Sell",(L72-M72)*K72*100,IF(OR(A72="Buy",A72="Assigned"),(M72-L72)*K72*100,""))) | Q72: =IF(E72="","",IF(E72-C72<1,1,E72-C72)) | R72: =IFERROR(IF(P72="","",P72/Q72),"") | S72: =IF(E72="","",IFERROR(IF(N72="",P72/O72,P72/N72),"")) | T72: =IFERROR(IF(S72="","",S72/Q72*365/12),"") | U72: =IFERROR(IF(S72="","",S72/Q72*365),"")
H73: =IFERROR(__xludf.DUMMYFUNCTION("IF(F73="""","""",IFERROR(GOOGLEFINANCE(UPPER(F73),""price""),""""))"),"") | J73: =IF(OR(A73="",E73<>""),"",IFERROR(H73-I73,"")) | O73: =IF(A73="Buy",IF(L73="","",L73*K73*100),IF(A73="Assigned",IF(L73="","",L73*K73*100),IF(A73="Sell",IF(OR(I73="",K73=""),"",I73*K73*100),""))) | P73: =IF(M73="","",IF(A73="Sell",(L73-M73)*K73*100,IF(OR(A73="Buy",A73="Assigned"),(M73-L73)*K73*100,""))) | Q73: =IF(E73="","",IF(E73-C73<1,1,E73-C73)) | R73: =IFERROR(IF(P73="","",P73/Q73),"") | S73: =IF(E73="","",IFERROR(IF(N73="",P73/O73,P73/N73),"")) | T73: =IFERROR(IF(S73="","",S73/Q73*365/12),"") | U73: =IFERROR(IF(S73="","",S73/Q73*365),"")
H74: =IFERROR(__xludf.DUMMYFUNCTION("IF(F74="""","""",IFERROR(GOOGLEFINANCE(UPPER(F74),""price""),""""))"),"") | J74: =IF(OR(A74="",E74<>""),"",IFERROR(H74-I74,"")) | O74: =IF(A74="Buy",IF(L74="","",L74*K74*100),IF(A74="Assigned",IF(L74="","",L74*K74*100),IF(A74="Sell",IF(OR(I74="",K74=""),"",I74*K74*100),""))) | P74: =IF(M74="","",IF(A74="Sell",(L74-M74)*K74*100,IF(OR(A74="Buy",A74="Assigned"),(M74-L74)*K74*100,""))) | Q74: =IF(E74="","",IF(E74-C74<1,1,E74-C74)) | R74: =IFERROR(IF(P74="","",P74/Q74),"") | S74: =IF(E74="","",IFERROR(IF(N74="",P74/O74,P74/N74),"")) | T74: =IFERROR(IF(S74="","",S74/Q74*365/12),"") | U74: =IFERROR(IF(S74="","",S74/Q74*365),"")
H75: =IFERROR(__xludf.DUMMYFUNCTION("IF(F75="""","""",IFERROR(GOOGLEFINANCE(UPPER(F75),""price""),""""))"),"") | J75: =IF(OR(A75="",E75<>""),"",IFERROR(H75-I75,"")) | O75: =IF(A75="Buy",IF(L75="","",L75*K75*100),IF(A75="Assigned",IF(L75="","",L75*K75*100),IF(A75="Sell",IF(OR(I75="",K75=""),"",I75*K75*100),""))) | P75: =IF(M75="","",IF(A75="Sell",(L75-M75)*K75*100,IF(OR(A75="Buy",A75="Assigned"),(M75-L75)*K75*100,""))) | Q75: =IF(E75="","",IF(E75-C75<1,1,E75-C75)) | R75: =IFERROR(IF(P75="","",P75/Q75),"") | S75: =IF(E75="","",IFERROR(IF(N75="",P75/O75,P75/N75),"")) | T75: =IFERROR(IF(S75="","",S75/Q75*365/12),"") | U75: =IFERROR(IF(S75="","",S75/Q75*365),"")
H76: =IFERROR(__xludf.DUMMYFUNCTION("IF(F76="""","""",IFERROR(GOOGLEFINANCE(UPPER(F76),""price""),""""))"),"") | J76: =IF(OR(A76="",E76<>""),"",IFERROR(H76-I76,"")) | O76: =IF(A76="Buy",IF(L76="","",L76*K76*100),IF(A76="Assigned",IF(L76="","",L76*K76*100),IF(A76="Sell",IF(OR(I76="",K76=""),"",I76*K76*100),""))) | P76: =IF(M76="","",IF(A76="Sell",(L76-M76)*K76*100,IF(OR(A76="Buy",A76="Assigned"),(M76-L76)*K76*100,""))) | Q76: =IF(E76="","",IF(E76-C76<1,1,E76-C76)) | R76: =IFERROR(IF(P76="","",P76/Q76),"") | S76: =IF(E76="","",IFERROR(IF(N76="",P76/O76,P76/N76),"")) | T76: =IFERROR(IF(S76="","",S76/Q76*365/12),"") | U76: =IFERROR(IF(S76="","",S76/Q76*365),"")
H77: =IFERROR(__xludf.DUMMYFUNCTION("IF(F77="""","""",IFERROR(GOOGLEFINANCE(UPPER(F77),""price""),""""))"),"") | J77: =IF(OR(A77="",E77<>""),"",IFERROR(H77-I77,"")) | O77: =IF(A77="Buy",IF(L77="","",L77*K77*100),IF(A77="Assigned",IF(L77="","",L77*K77*100),IF(A77="Sell",IF(OR(I77="",K77=""),"",I77*K77*100),""))) | P77: =IF(M77="","",IF(A77="Sell",(L77-M77)*K77*100,IF(OR(A77="Buy",A77="Assigned"),(M77-L77)*K77*100,""))) | Q77: =IF(E77="","",IF(E77-C77<1,1,E77-C77)) | R77: =IFERROR(IF(P77="","",P77/Q77),"") | S77: =IF(E77="","",IFERROR(IF(N77="",P77/O77,P77/N77),"")) | T77: =IFERROR(IF(S77="","",S77/Q77*365/12),"") | U77: =IFERROR(IF(S77="","",S77/Q77*365),"")
H78: =IFERROR(__xludf.DUMMYFUNCTION("IF(F78="""","""",IFERROR(GOOGLEFINANCE(UPPER(F78),""price""),""""))"),"") | J78: =IF(OR(A78="",E78<>""),"",IFERROR(H78-I78,"")) | O78: =IF(A78="Buy",IF(L78="","",L78*K78*100),IF(A78="Assigned",IF(L78="","",L78*K78*100),IF(A78="Sell",IF(OR(I78="",K78=""),"",I78*K78*100),""))) | P78: =IF(M78="","",IF(A78="Sell",(L78-M78)*K78*100,IF(OR(A78="Buy",A78="Assigned"),(M78-L78)*K78*100,""))) | Q78: =IF(E78="","",IF(E78-C78<1,1,E78-C78)) | R78: =IFERROR(IF(P78="","",P78/Q78),"") | S78: =IF(E78="","",IFERROR(IF(N78="",P78/O78,P78/N78),"")) | T78: =IFERROR(IF(S78="","",S78/Q78*365/12),"") | U78: =IFERROR(IF(S78="","",S78/Q78*365),"")
H79: =IFERROR(__xludf.DUMMYFUNCTION("IF(F79="""","""",IFERROR(GOOGLEFINANCE(UPPER(F79),""price""),""""))"),"") | J79: =IF(OR(A79="",E79<>""),"",IFERROR(H79-I79,"")) | O79: =IF(A79="Buy",IF(L79="","",L79*K79*100),IF(A79="Assigned",IF(L79="","",L79*K79*100),IF(A79="Sell",IF(OR(I79="",K79=""),"",I79*K79*100),""))) | P79: =IF(M79="","",IF(A79="Sell",(L79-M79)*K79*100,IF(OR(A79="Buy",A79="Assigned"),(M79-L79)*K79*100,""))) | Q79: =IF(E79="","",IF(E79-C79<1,1,E79-C79)) | R79: =IFERROR(IF(P79="","",P79/Q79),"") | S79: =IF(E79="","",IFERROR(IF(N79="",P79/O79,P79/N79),"")) | T79: =IFERROR(IF(S79="","",S79/Q79*365/12),"") | U79: =IFERROR(IF(S79="","",S79/Q79*365),"")
H80: =IFERROR(__xludf.DUMMYFUNCTION("IF(F80="""","""",IFERROR(GOOGLEFINANCE(UPPER(F80),""price""),""""))"),"") | J80: =IF(OR(A80="",E80<>""),"",IFERROR(H80-I80,"")) | O80: =IF(A80="Buy",IF(L80="","",L80*K80*100),IF(A80="Assigned",IF(L80="","",L80*K80*100),IF(A80="Sell",IF(OR(I80="",K80=""),"",I80*K80*100),""))) | P80: =IF(M80="","",IF(A80="Sell",(L80-M80)*K80*100,IF(OR(A80="Buy",A80="Assigned"),(M80-L80)*K80*100,""))) | Q80: =IF(E80="","",IF(E80-C80<1,1,E80-C80)) | R80: =IFERROR(IF(P80="","",P80/Q80),"") | S80: =IF(E80="","",IFERROR(IF(N80="",P80/O80,P80/N80),"")) | T80: =IFERROR(IF(S80="","",S80/Q80*365/12),"") | U80: =IFERROR(IF(S80="","",S80/Q80*365),"")
H81: =IFERROR(__xludf.DUMMYFUNCTION("IF(F81="""","""",IFERROR(GOOGLEFINANCE(UPPER(F81),""price""),""""))"),"") | J81: =IF(OR(A81="",E81<>""),"",IFERROR(H81-I81,"")) | O81: =IF(A81="Buy",IF(L81="","",L81*K81*100),IF(A81="Assigned",IF(L81="","",L81*K81*100),IF(A81="Sell",IF(OR(I81="",K81=""),"",I81*K81*100),""))) | P81: =IF(M81="","",IF(A81="Sell",(L81-M81)*K81*100,IF(OR(A81="Buy",A81="Assigned"),(M81-L81)*K81*100,""))) | Q81: =IF(E81="","",IF(E81-C81<1,1,E81-C81)) | R81: =IFERROR(IF(P81="","",P81/Q81),"") | S81: =IF(E81="","",IFERROR(IF(N81="",P81/O81,P81/N81),"")) | T81: =IFERROR(IF(S81="","",S81/Q81*365/12),"") | U81: =IFERROR(IF(S81="","",S81/Q81*365),"")
H82: =IFERROR(__xludf.DUMMYFUNCTION("IF(F82="""","""",IFERROR(GOOGLEFINANCE(UPPER(F82),""price""),""""))"),"") | J82: =IF(OR(A82="",E82<>""),"",IFERROR(H82-I82,"")) | O82: =IF(A82="Buy",IF(L82="","",L82*K82*100),IF(A82="Assigned",IF(L82="","",L82*K82*100),IF(A82="Sell",IF(OR(I82="",K82=""),"",I82*K82*100),""))) | P82: =IF(M82="","",IF(A82="Sell",(L82-M82)*K82*100,IF(OR(A82="Buy",A82="Assigned"),(M82-L82)*K82*100,""))) | Q82: =IF(E82="","",IF(E82-C82<1,1,E82-C82)) | R82: =IFERROR(IF(P82="","",P82/Q82),"") | S82: =IF(E82="","",IFERROR(IF(N82="",P82/O82,P82/N82),"")) | T82: =IFERROR(IF(S82="","",S82/Q82*365/12),"") | U82: =IFERROR(IF(S82="","",S82/Q82*365),"")
H83: =IFERROR(__xludf.DUMMYFUNCTION("IF(F83="""","""",IFERROR(GOOGLEFINANCE(UPPER(F83),""price""),""""))"),"") | J83: =IF(OR(A83="",E83<>""),"",IFERROR(H83-I83,"")) | O83: =IF(A83="Buy",IF(L83="","",L83*K83*100),IF(A83="Assigned",IF(L83="","",L83*K83*100),IF(A83="Sell",IF(OR(I83="",K83=""),"",I83*K83*100),""))) | P83: =IF(M83="","",IF(A83="Sell",(L83-M83)*K83*100,IF(OR(A83="Buy",A83="Assigned"),(M83-L83)*K83*100,""))) | Q83: =IF(E83="","",IF(E83-C83<1,1,E83-C83)) | R83: =IFERROR(IF(P83="","",P83/Q83),"") | S83: =IF(E83="","",IFERROR(IF(N83="",P83/O83,P83/N83),"")) | T83: =IFERROR(IF(S83="","",S83/Q83*365/12),"") | U83: =IFERROR(IF(S83="","",S83/Q83*365),"")
H84: =IFERROR(__xludf.DUMMYFUNCTION("IF(F84="""","""",IFERROR(GOOGLEFINANCE(UPPER(F84),""price""),""""))"),"") | J84: =IF(OR(A84="",E84<>""),"",IFERROR(H84-I84,"")) | O84: =IF(A84="Buy",IF(L84="","",L84*K84*100),IF(A84="Assigned",IF(L84="","",L84*K84*100),IF(A84="Sell",IF(OR(I84="",K84=""),"",I84*K84*100),""))) | P84: =IF(M84="","",IF(A84="Sell",(L84-M84)*K84*100,IF(OR(A84="Buy",A84="Assigned"),(M84-L84)*K84*100,""))) | Q84: =IF(E84="","",IF(E84-C84<1,1,E84-C84)) | R84: =IFERROR(IF(P84="","",P84/Q84),"") | S84: =IF(E84="","",IFERROR(IF(N84="",P84/O84,P84/N84),"")) | T84: =IFERROR(IF(S84="","",S84/Q84*365/12),"") | U84: =IFERROR(IF(S84="","",S84/Q84*365),"")
H85: =IFERROR(__xludf.DUMMYFUNCTION("IF(F85="""","""",IFERROR(GOOGLEFINANCE(UPPER(F85),""price""),""""))"),"") | J85: =IF(OR(A85="",E85<>""),"",IFERROR(H85-I85,"")) | O85: =IF(A85="Buy",IF(L85="","",L85*K85*100),IF(A85="Assigned",IF(L85="","",L85*K85*100),IF(A85="Sell",IF(OR(I85="",K85=""),"",I85*K85*100),""))) | P85: =IF(M85="","",IF(A85="Sell",(L85-M85)*K85*100,IF(OR(A85="Buy",A85="Assigned"),(M85-L85)*K85*100,""))) | Q85: =IF(E85="","",IF(E85-C85<1,1,E85-C85)) | R85: =IFERROR(IF(P85="","",P85/Q85),"") | S85: =IF(E85="","",IFERROR(IF(N85="",P85/O85,P85/N85),"")) | T85: =IFERROR(IF(S85="","",S85/Q85*365/12),"") | U85: =IFERROR(IF(S85="","",S85/Q85*365),"")
H86: =IFERROR(__xludf.DUMMYFUNCTION("IF(F86="""","""",IFERROR(GOOGLEFINANCE(UPPER(F86),""price""),""""))"),"") | J86: =IF(OR(A86="",E86<>""),"",IFERROR(H86-I86,"")) | O86: =IF(A86="Buy",IF(L86="","",L86*K86*100),IF(A86="Assigned",IF(L86="","",L86*K86*100),IF(A86="Sell",IF(OR(I86="",K86=""),"",I86*K86*100),""))) | P86: =IF(M86="","",IF(A86="Sell",(L86-M86)*K86*100,IF(OR(A86="Buy",A86="Assigned"),(M86-L86)*K86*100,""))) | Q86: =IF(E86="","",IF(E86-C86<1,1,E86-C86)) | R86: =IFERROR(IF(P86="","",P86/Q86),"") | S86: =IF(E86="","",IFERROR(IF(N86="",P86/O86,P86/N86),"")) | T86: =IFERROR(IF(S86="","",S86/Q86*365/12),"") | U86: =IFERROR(IF(S86="","",S86/Q86*365),"")
H87: =IFERROR(__xludf.DUMMYFUNCTION("IF(F87="""","""",IFERROR(GOOGLEFINANCE(UPPER(F87),""price""),""""))"),"") | J87: =IF(OR(A87="",E87<>""),"",IFERROR(H87-I87,"")) | O87: =IF(A87="Buy",IF(L87="","",L87*K87*100),IF(A87="Assigned",IF(L87="","",L87*K87*100),IF(A87="Sell",IF(OR(I87="",K87=""),"",I87*K87*100),""))) | P87: =IF(M87="","",IF(A87="Sell",(L87-M87)*K87*100,IF(OR(A87="Buy",A87="Assigned"),(M87-L87)*K87*100,""))) | Q87: =IF(E87="","",IF(E87-C87<1,1,E87-C87)) | R87: =IFERROR(IF(P87="","",P87/Q87),"") | S87: =IF(E87="","",IFERROR(IF(N87="",P87/O87,P87/N87),"")) | T87: =IFERROR(IF(S87="","",S87/Q87*365/12),"") | U87: =IFERROR(IF(S87="","",S87/Q87*365),"")
H88: =IFERROR(__xludf.DUMMYFUNCTION("IF(F88="""","""",IFERROR(GOOGLEFINANCE(UPPER(F88),""price""),""""))"),"") | J88: =IF(OR(A88="",E88<>""),"",IFERROR(H88-I88,"")) | O88: =IF(A88="Buy",IF(L88="","",L88*K88*100),IF(A88="Assigned",IF(L88="","",L88*K88*100),IF(A88="Sell",IF(OR(I88="",K88=""),"",I88*K88*100),""))) | P88: =IF(M88="","",IF(A88="Sell",(L88-M88)*K88*100,IF(OR(A88="Buy",A88="Assigned"),(M88-L88)*K88*100,""))) | Q88: =IF(E88="","",IF(E88-C88<1,1,E88-C88)) | R88: =IFERROR(IF(P88="","",P88/Q88),"") | S88: =IF(E88="","",IFERROR(IF(N88="",P88/O88,P88/N88),"")) | T88: =IFERROR(IF(S88="","",S88/Q88*365/12),"") | U88: =IFERROR(IF(S88="","",S88/Q88*365),"")
H89: =IFERROR(__xludf.DUMMYFUNCTION("IF(F89="""","""",IFERROR(GOOGLEFINANCE(UPPER(F89),""price""),""""))"),"") | J89: =IF(OR(A89="",E89<>""),"",IFERROR(H89-I89,"")) | O89: =IF(A89="Buy",IF(L89="","",L89*K89*100),IF(A89="Assigned",IF(L89="","",L89*K89*100),IF(A89="Sell",IF(OR(I89="",K89=""),"",I89*K89*100),""))) | P89: =IF(M89="","",IF(A89="Sell",(L89-M89)*K89*100,IF(OR(A89="Buy",A89="Assigned"),(M89-L89)*K89*100,""))) | Q89: =IF(E89="","",IF(E89-C89<1,1,E89-C89)) | R89: =IFERROR(IF(P89="","",P89/Q89),"") | S89: =IF(E89="","",IFERROR(IF(N89="",P89/O89,P89/N89),"")) | T89: =IFERROR(IF(S89="","",S89/Q89*365/12),"") | U89: =IFERROR(IF(S89="","",S89/Q89*365),"")
H90: =IFERROR(__xludf.DUMMYFUNCTION("IF(F90="""","""",IFERROR(GOOGLEFINANCE(UPPER(F90),""price""),""""))"),"") | J90: =IF(OR(A90="",E90<>""),"",IFERROR(H90-I90,"")) | O90: =IF(A90="Buy",IF(L90="","",L90*K90*100),IF(A90="Assigned",IF(L90="","",L90*K90*100),IF(A90="Sell",IF(OR(I90="",K90=""),"",I90*K90*100),""))) | P90: =IF(M90="","",IF(A90="Sell",(L90-M90)*K90*100,IF(OR(A90="Buy",A90="Assigned"),(M90-L90)*K90*100,""))) | Q90: =IF(E90="","",IF(E90-C90<1,1,E90-C90)) | R90: =IFERROR(IF(P90="","",P90/Q90),"") | S90: =IF(E90="","",IFERROR(IF(N90="",P90/O90,P90/N90),"")) | T90: =IFERROR(IF(S90="","",S90/Q90*365/12),"") | U90: =IFERROR(IF(S90="","",S90/Q90*365),"")
H91: =IFERROR(__xludf.DUMMYFUNCTION("IF(F91="""","""",IFERROR(GOOGLEFINANCE(UPPER(F91),""price""),""""))"),"") | J91: =IF(OR(A91="",E91<>""),"",IFERROR(H91-I91,"")) | O91: =IF(A91="Buy",IF(L91="","",L91*K91*100),IF(A91="Assigned",IF(L91="","",L91*K91*100),IF(A91="Sell",IF(OR(I91="",K91=""),"",I91*K91*100),""))) | P91: =IF(M91="","",IF(A91="Sell",(L91-M91)*K91*100,IF(OR(A91="Buy",A91="Assigned"),(M91-L91)*K91*100,""))) | Q91: =IF(E91="","",IF(E91-C91<1,1,E91-C91)) | R91: =IFERROR(IF(P91="","",P91/Q91),"") | S91: =IF(E91="","",IFERROR(IF(N91="",P91/O91,P91/N91),"")) | T91: =IFERROR(IF(S91="","",S91/Q91*365/12),"") | U91: =IFERROR(IF(S91="","",S91/Q91*365),"")
H92: =IFERROR(__xludf.DUMMYFUNCTION("IF(F92="""","""",IFERROR(GOOGLEFINANCE(UPPER(F92),""price""),""""))"),"") | J92: =IF(OR(A92="",E92<>""),"",IFERROR(H92-I92,"")) | O92: =IF(A92="Buy",IF(L92="","",L92*K92*100),IF(A92="Assigned",IF(L92="","",L92*K92*100),IF(A92="Sell",IF(OR(I92="",K92=""),"",I92*K92*100),""))) | P92: =IF(M92="","",IF(A92="Sell",(L92-M92)*K92*100,IF(OR(A92="Buy",A92="Assigned"),(M92-L92)*K92*100,""))) | Q92: =IF(E92="","",IF(E92-C92<1,1,E92-C92)) | R92: =IFERROR(IF(P92="","",P92/Q92),"") | S92: =IF(E92="","",IFERROR(IF(N92="",P92/O92,P92/N92),"")) | T92: =IFERROR(IF(S92="","",S92/Q92*365/12),"") | U92: =IFERROR(IF(S92="","",S92/Q92*365),"")
H93: =IFERROR(__xludf.DUMMYFUNCTION("IF(F93="""","""",IFERROR(GOOGLEFINANCE(UPPER(F93),""price""),""""))"),"") | J93: =IF(OR(A93="",E93<>""),"",IFERROR(H93-I93,"")) | O93: =IF(A93="Buy",IF(L93="","",L93*K93*100),IF(A93="Assigned",IF(L93="","",L93*K93*100),IF(A93="Sell",IF(OR(I93="",K93=""),"",I93*K93*100),""))) | P93: =IF(M93="","",IF(A93="Sell",(L93-M93)*K93*100,IF(OR(A93="Buy",A93="Assigned"),(M93-L93)*K93*100,""))) | Q93: =IF(E93="","",IF(E93-C93<1,1,E93-C93)) | R93: =IFERROR(IF(P93="","",P93/Q93),"") | S93: =IF(E93="","",IFERROR(IF(N93="",P93/O93,P93/N93),"")) | T93: =IFERROR(IF(S93="","",S93/Q93*365/12),"") | U93: =IFERROR(IF(S93="","",S93/Q93*365),"")
H94: =IFERROR(__xludf.DUMMYFUNCTION("IF(F94="""","""",IFERROR(GOOGLEFINANCE(UPPER(F94),""price""),""""))"),"") | J94: =IF(OR(A94="",E94<>""),"",IFERROR(H94-I94,"")) | O94: =IF(A94="Buy",IF(L94="","",L94*K94*100),IF(A94="Assigned",IF(L94="","",L94*K94*100),IF(A94="Sell",IF(OR(I94="",K94=""),"",I94*K94*100),""))) | P94: =IF(M94="","",IF(A94="Sell",(L94-M94)*K94*100,IF(OR(A94="Buy",A94="Assigned"),(M94-L94)*K94*100,""))) | Q94: =IF(E94="","",IF(E94-C94<1,1,E94-C94)) | R94: =IFERROR(IF(P94="","",P94/Q94),"") | S94: =IF(E94="","",IFERROR(IF(N94="",P94/O94,P94/N94),"")) | T94: =IFERROR(IF(S94="","",S94/Q94*365/12),"") | U94: =IFERROR(IF(S94="","",S94/Q94*365),"")
H95: =IFERROR(__xludf.DUMMYFUNCTION("IF(F95="""","""",IFERROR(GOOGLEFINANCE(UPPER(F95),""price""),""""))"),"") | J95: =IF(OR(A95="",E95<>""),"",IFERROR(H95-I95,"")) | O95: =IF(A95="Buy",IF(L95="","",L95*K95*100),IF(A95="Assigned",IF(L95="","",L95*K95*100),IF(A95="Sell",IF(OR(I95="",K95=""),"",I95*K95*100),""))) | P95: =IF(M95="","",IF(A95="Sell",(L95-M95)*K95*100,IF(OR(A95="Buy",A95="Assigned"),(M95-L95)*K95*100,""))) | Q95: =IF(E95="","",IF(E95-C95<1,1,E95-C95)) | R95: =IFERROR(IF(P95="","",P95/Q95),"") | S95: =IF(E95="","",IFERROR(IF(N95="",P95/O95,P95/N95),"")) | T95: =IFERROR(IF(S95="","",S95/Q95*365/12),"") | U95: =IFERROR(IF(S95="","",S95/Q95*365),"")
H96: =IFERROR(__xludf.DUMMYFUNCTION("IF(F96="""","""",IFERROR(GOOGLEFINANCE(UPPER(F96),""price""),""""))"),"") | J96: =IF(OR(A96="",E96<>""),"",IFERROR(H96-I96,"")) | O96: =IF(A96="Buy",IF(L96="","",L96*K96*100),IF(A96="Assigned",IF(L96="","",L96*K96*100),IF(A96="Sell",IF(OR(I96="",K96=""),"",I96*K96*100),""))) | P96: =IF(M96="","",IF(A96="Sell",(L96-M96)*K96*100,IF(OR(A96="Buy",A96="Assigned"),(M96-L96)*K96*100,""))) | Q96: =IF(E96="","",IF(E96-C96<1,1,E96-C96)) | R96: =IFERROR(IF(P96="","",P96/Q96),"") | S96: =IF(E96="","",IFERROR(IF(N96="",P96/O96,P96/N96),"")) | T96: =IFERROR(IF(S96="","",S96/Q96*365/12),"") | U96: =IFERROR(IF(S96="","",S96/Q96*365),"")
H97: =IFERROR(__xludf.DUMMYFUNCTION("IF(F97="""","""",IFERROR(GOOGLEFINANCE(UPPER(F97),""price""),""""))"),"") | J97: =IF(OR(A97="",E97<>""),"",IFERROR(H97-I97,"")) | O97: =IF(A97="Buy",IF(L97="","",L97*K97*100),IF(A97="Assigned",IF(L97="","",L97*K97*100),IF(A97="Sell",IF(OR(I97="",K97=""),"",I97*K97*100),""))) | P97: =IF(M97="","",IF(A97="Sell",(L97-M97)*K97*100,IF(OR(A97="Buy",A97="Assigned"),(M97-L97)*K97*100,""))) | Q97: =IF(E97="","",IF(E97-C97<1,1,E97-C97)) | R97: =IFERROR(IF(P97="","",P97/Q97),"") | S97: =IF(E97="","",IFERROR(IF(N97="",P97/O97,P97/N97),"")) | T97: =IFERROR(IF(S97="","",S97/Q97*365/12),"") | U97: =IFERROR(IF(S97="","",S97/Q97*365),"")
H98: =IFERROR(__xludf.DUMMYFUNCTION("IF(F98="""","""",IFERROR(GOOGLEFINANCE(UPPER(F98),""price""),""""))"),"") | J98: =IF(OR(A98="",E98<>""),"",IFERROR(H98-I98,"")) | O98: =IF(A98="Buy",IF(L98="","",L98*K98*100),IF(A98="Assigned",IF(L98="","",L98*K98*100),IF(A98="Sell",IF(OR(I98="",K98=""),"",I98*K98*100),""))) | P98: =IF(M98="","",IF(A98="Sell",(L98-M98)*K98*100,IF(OR(A98="Buy",A98="Assigned"),(M98-L98)*K98*100,""))) | Q98: =IF(E98="","",IF(E98-C98<1,1,E98-C98)) | R98: =IFERROR(IF(P98="","",P98/Q98),"") | S98: =IF(E98="","",IFERROR(IF(N98="",P98/O98,P98/N98),"")) | T98: =IFERROR(IF(S98="","",S98/Q98*365/12),"") | U98: =IFERROR(IF(S98="","",S98/Q98*365),"")
H99: =IFERROR(__xludf.DUMMYFUNCTION("IF(F99="""","""",IFERROR(GOOGLEFINANCE(UPPER(F99),""price""),""""))"),"") | J99: =IF(OR(A99="",E99<>""),"",IFERROR(H99-I99,"")) | O99: =IF(A99="Buy",IF(L99="","",L99*K99*100),IF(A99="Assigned",IF(L99="","",L99*K99*100),IF(A99="Sell",IF(OR(I99="",K99=""),"",I99*K99*100),""))) | P99: =IF(M99="","",IF(A99="Sell",(L99-M99)*K99*100,IF(OR(A99="Buy",A99="Assigned"),(M99-L99)*K99*100,""))) | Q99: =IF(E99="","",IF(E99-C99<1,1,E99-C99)) | R99: =IFERROR(IF(P99="","",P99/Q99),"") | S99: =IF(E99="","",IFERROR(IF(N99="",P99/O99,P99/N99),"")) | T99: =IFERROR(IF(S99="","",S99/Q99*365/12),"") | U99: =IFERROR(IF(S99="","",S99/Q99*365),"")
H100: =IFERROR(__xludf.DUMMYFUNCTION("IF(F100="""","""",IFERROR(GOOGLEFINANCE(UPPER(F100),""price""),""""))"),"") | J100: =IF(OR(A100="",E100<>""),"",IFERROR(H100-I100,"")) | O100: =IF(A100="Buy",IF(L100="","",L100*K100*100),IF(A100="Assigned",IF(L100="","",L100*K100*100),IF(A100="Sell",IF(OR(I100="",K100=""),"",I100*K100*100),""))) | P100: =IF(M100="","",IF(A100="Sell",(L100-M100)*K100*100,IF(OR(A100="Buy",A100="Assigned"),(M100-L100)*K100*100,""))) | Q100: =IF(E100="","",IF(E100-C100<1,1,E100-C100)) | R100: =IFERROR(IF(P100="","",P100/Q100),"") | S100: =IF(E100="","",IFERROR(IF(N100="",P100/O100,P100/N100),"")) | T100: =IFERROR(IF(S100="","",S100/Q100*365/12),"") | U100: =IFERROR(IF(S100="","",S100/Q100*365),"")
...

Sheet Credit Spreads
A1: Practical Income Investing - Credit Spreads
A2: TOTAL PROFIT | E2: =SUM(S5:S304) -> 0 | J2: COLLATERAL USED | N2: =IFERROR(SUM(R5:R304),0) -> 0 | P2: TOTAL ROC | S2: =IFERROR(SUM(S5:S304)/SUM(R5:R304),0) -> 0 | W2: Locked Cells | X2: Manually Enter
A3: WINS | C3: =COUNTIF(S5:S304,">0") -> 0 | D3: LOSSES | F3: =COUNTIF(S5:S304,"<0") -> 0 | H3: WIN RATE | K3: =IFERROR(C3/(C3+F3),0) -> 0 | M3: AVG WIN | O3: =IFERROR(AVERAGEIF(S5:S304,">0"),0) -> 0 | Q3: AVG LOSS | S3: =IFERROR(AVERAGEIF(S5:S304,"<0"),0) -> 0 | W3: Cell Use Guide
A4: TYPE | B4: STRATEGY | C4: OPEN DATE | D4: EXP DATE | E4: CLOSE DATE | F4: TICKER | G4: BROKERAGE | H4: SOLD PUT | I4: BOUGHT PUT | J4: SOLD CALL | K4: BOUGHT CALL | L4: QTY | M4: PREMIUM $/shr | N4: TOTAL PREMIUM $ | O4: CLOSE $/shr | P4: TOTAL CLOSE $ | Q4: FEE | R4: COLLATERAL $ | S4: P / L | T4: ROC % | U4: MONTHLY RETURN % | V4: ANNUAL RETURN % | W4: NOTES
N5: =IF(OR(M5="",L5=""),"",M5*L5*100) | P5: =IF(OR(O5="",L5=""),"",O5*L5*100) | R5: =IF(OR(L5="",N5=""),"",IF(A5="Buy",N5,IF(B5="Put Spread",(H5-I5)*100*L5-N5,IF(B5="Call Spread",(K5-J5)*100*L5-N5,IF(B5="Iron Condor",MAX((H5-I5),(K5-J5))*100*L5-N5,""))))) | S5: =IFERROR(IF(OR(N5="",E5=""),"",IF(A5="Buy",IF(P5="","",P5-N5-IF(Q5="",0,Q5)),IF(P5="","",N5-P5-IF(Q5="",0,Q5)))),"") | T5: =IFERROR(IF(S5="","",S5/R5),"") | U5: =IFERROR(IF(OR(T5="",C5="",E5=""),"",T5/MAX(1,E5-C5)*30),"") | V5: =IFERROR(IF(OR(T5="",C5="",E5=""),"",T5/MAX(1,E5-C5)*365),"")
N6: =IF(OR(M6="",L6=""),"",M6*L6*100) | P6: =IF(OR(O6="",L6=""),"",O6*L6*100) | R6: =IF(OR(L6="",N6=""),"",IF(A6="Buy",N6,IF(B6="Put Spread",(H6-I6)*100*L6-N6,IF(B6="Call Spread",(K6-J6)*100*L6-N6,IF(B6="Iron Condor",MAX((H6-I6),(K6-J6))*100*L6-N6,""))))) | S6: =IFERROR(IF(OR(N6="",E6=""),"",IF(A6="Buy",IF(P6="","",P6-N6-IF(Q6="",0,Q6)),IF(P6="","",N6-P6-IF(Q6="",0,Q6)))),"") | T6: =IFERROR(IF(S6="","",S6/R6),"") | U6: =IFERROR(IF(OR(T6="",C6="",E6=""),"",T6/MAX(1,E6-C6)*30),"") | V6: =IFERROR(IF(OR(T6="",C6="",E6=""),"",T6/MAX(1,E6-C6)*365),"")
N7: =IF(OR(M7="",L7=""),"",M7*L7*100) | P7: =IF(OR(O7="",L7=""),"",O7*L7*100) | R7: =IF(OR(L7="",N7=""),"",IF(A7="Buy",N7,IF(B7="Put Spread",(H7-I7)*100*L7-N7,IF(B7="Call Spread",(K7-J7)*100*L7-N7,IF(B7="Iron Condor",MAX((H7-I7),(K7-J7))*100*L7-N7,""))))) | S7: =IFERROR(IF(OR(N7="",E7=""),"",IF(A7="Buy",IF(P7="","",P7-N7-IF(Q7="",0,Q7)),IF(P7="","",N7-P7-IF(Q7="",0,Q7)))),"") | T7: =IFERROR(IF(S7="","",S7/R7),"") | U7: =IFERROR(IF(OR(T7="",C7="",E7=""),"",T7/MAX(1,E7-C7)*30),"") | V7: =IFERROR(IF(OR(T7="",C7="",E7=""),"",T7/MAX(1,E7-C7)*365),"")
N8: =IF(OR(M8="",L8=""),"",M8*L8*100) | P8: =IF(OR(O8="",L8=""),"",O8*L8*100) | R8: =IF(OR(L8="",N8=""),"",IF(A8="Buy",N8,IF(B8="Put Spread",(H8-I8)*100*L8-N8,IF(B8="Call Spread",(K8-J8)*100*L8-N8,IF(B8="Iron Condor",MAX((H8-I8),(K8-J8))*100*L8-N8,""))))) | S8: =IFERROR(IF(OR(N8="",E8=""),"",IF(A8="Buy",IF(P8="","",P8-N8-IF(Q8="",0,Q8)),IF(P8="","",N8-P8-IF(Q8="",0,Q8)))),"") | T8: =IFERROR(IF(S8="","",S8/R8),"") | U8: =IFERROR(IF(OR(T8="",C8="",E8=""),"",T8/MAX(1,E8-C8)*30),"") | V8: =IFERROR(IF(OR(T8="",C8="",E8=""),"",T8/MAX(1,E8-C8)*365),"")
N9: =IF(OR(M9="",L9=""),"",M9*L9*100) | P9: =IF(OR(O9="",L9=""),"",O9*L9*100) | R9: =IF(OR(L9="",N9=""),"",IF(A9="Buy",N9,IF(B9="Put Spread",(H9-I9)*100*L9-N9,IF(B9="Call Spread",(K9-J9)*100*L9-N9,IF(B9="Iron Condor",MAX((H9-I9),(K9-J9))*100*L9-N9,""))))) | S9: =IFERROR(IF(OR(N9="",E9=""),"",IF(A9="Buy",IF(P9="","",P9-N9-IF(Q9="",0,Q9)),IF(P9="","",N9-P9-IF(Q9="",0,Q9)))),"") | T9: =IFERROR(IF(S9="","",S9/R9),"") | U9: =IFERROR(IF(OR(T9="",C9="",E9=""),"",T9/MAX(1,E9-C9)*30),"") | V9: =IFERROR(IF(OR(T9="",C9="",E9=""),"",T9/MAX(1,E9-C9)*365),"")
N10: =IF(OR(M10="",L10=""),"",M10*L10*100) | P10: =IF(OR(O10="",L10=""),"",O10*L10*100) | R10: =IF(OR(L10="",N10=""),"",IF(A10="Buy",N10,IF(B10="Put Spread",(H10-I10)*100*L10-N10,IF(B10="Call Spread",(K10-J10)*100*L10-N10,IF(B10="Iron Condor",MAX((H10-I10),(K10-J10))*100*L10-N10,""))))) | S10: =IFERROR(IF(OR(N10="",E10=""),"",IF(A10="Buy",IF(P10="","",P10-N10-IF(Q10="",0,Q10)),IF(P10="","",N10-P10-IF(Q10="",0,Q10)))),"") | T10: =IFERROR(IF(S10="","",S10/R10),"") | U10: =IFERROR(IF(OR(T10="",C10="",E10=""),"",T10/MAX(1,E10-C10)*30),"") | V10: =IFERROR(IF(OR(T10="",C10="",E10=""),"",T10/MAX(1,E10-C10)*365),"")
N11: =IF(OR(M11="",L11=""),"",M11*L11*100) | P11: =IF(OR(O11="",L11=""),"",O11*L11*100) | R11: =IF(OR(L11="",N11=""),"",IF(A11="Buy",N11,IF(B11="Put Spread",(H11-I11)*100*L11-N11,IF(B11="Call Spread",(K11-J11)*100*L11-N11,IF(B11="Iron Condor",MAX((H11-I11),(K11-J11))*100*L11-N11,""))))) | S11: =IFERROR(IF(OR(N11="",E11=""),"",IF(A11="Buy",IF(P11="","",P11-N11-IF(Q11="",0,Q11)),IF(P11="","",N11-P11-IF(Q11="",0,Q11)))),"") | T11: =IFERROR(IF(S11="","",S11/R11),"") | U11: =IFERROR(IF(OR(T11="",C11="",E11=""),"",T11/MAX(1,E11-C11)*30),"") | V11: =IFERROR(IF(OR(T11="",C11="",E11=""),"",T11/MAX(1,E11-C11)*365),"")
N12: =IF(OR(M12="",L12=""),"",M12*L12*100) | P12: =IF(OR(O12="",L12=""),"",O12*L12*100) | R12: =IF(OR(L12="",N12=""),"",IF(A12="Buy",N12,IF(B12="Put Spread",(H12-I12)*100*L12-N12,IF(B12="Call Spread",(K12-J12)*100*L12-N12,IF(B12="Iron Condor",MAX((H12-I12),(K12-J12))*100*L12-N12,""))))) | S12: =IFERROR(IF(OR(N12="",E12=""),"",IF(A12="Buy",IF(P12="","",P12-N12-IF(Q12="",0,Q12)),IF(P12="","",N12-P12-IF(Q12="",0,Q12)))),"") | T12: =IFERROR(IF(S12="","",S12/R12),"") | U12: =IFERROR(IF(OR(T12="",C12="",E12=""),"",T12/MAX(1,E12-C12)*30),"") | V12: =IFERROR(IF(OR(T12="",C12="",E12=""),"",T12/MAX(1,E12-C12)*365),"")
N13: =IF(OR(M13="",L13=""),"",M13*L13*100) | P13: =IF(OR(O13="",L13=""),"",O13*L13*100) | R13: =IF(OR(L13="",N13=""),"",IF(A13="Buy",N13,IF(B13="Put Spread",(H13-I13)*100*L13-N13,IF(B13="Call Spread",(K13-J13)*100*L13-N13,IF(B13="Iron Condor",MAX((H13-I13),(K13-J13))*100*L13-N13,""))))) | S13: =IFERROR(IF(OR(N13="",E13=""),"",IF(A13="Buy",IF(P13="","",P13-N13-IF(Q13="",0,Q13)),IF(P13="","",N13-P13-IF(Q13="",0,Q13)))),"") | T13: =IFERROR(IF(S13="","",S13/R13),"") | U13: =IFERROR(IF(OR(T13="",C13="",E13=""),"",T13/MAX(1,E13-C13)*30),"") | V13: =IFERROR(IF(OR(T13="",C13="",E13=""),"",T13/MAX(1,E13-C13)*365),"")
N14: =IF(OR(M14="",L14=""),"",M14*L14*100) | P14: =IF(OR(O14="",L14=""),"",O14*L14*100) | R14: =IF(OR(L14="",N14=""),"",IF(A14="Buy",N14,IF(B14="Put Spread",(H14-I14)*100*L14-N14,IF(B14="Call Spread",(K14-J14)*100*L14-N14,IF(B14="Iron Condor",MAX((H14-I14),(K14-J14))*100*L14-N14,""))))) | S14: =IFERROR(IF(OR(N14="",E14=""),"",IF(A14="Buy",IF(P14="","",P14-N14-IF(Q14="",0,Q14)),IF(P14="","",N14-P14-IF(Q14="",0,Q14)))),"") | T14: =IFERROR(IF(S14="","",S14/R14),"") | U14: =IFERROR(IF(OR(T14="",C14="",E14=""),"",T14/MAX(1,E14-C14)*30),"") | V14: =IFERROR(IF(OR(T14="",C14="",E14=""),"",T14/MAX(1,E14-C14)*365),"")
N15: =IF(OR(M15="",L15=""),"",M15*L15*100) | P15: =IF(OR(O15="",L15=""),"",O15*L15*100) | R15: =IF(OR(L15="",N15=""),"",IF(A15="Buy",N15,IF(B15="Put Spread",(H15-I15)*100*L15-N15,IF(B15="Call Spread",(K15-J15)*100*L15-N15,IF(B15="Iron Condor",MAX((H15-I15),(K15-J15))*100*L15-N15,""))))) | S15: =IFERROR(IF(OR(N15="",E15=""),"",IF(A15="Buy",IF(P15="","",P15-N15-IF(Q15="",0,Q15)),IF(P15="","",N15-P15-IF(Q15="",0,Q15)))),"") | T15: =IFERROR(IF(S15="","",S15/R15),"") | U15: =IFERROR(IF(OR(T15="",C15="",E15=""),"",T15/MAX(1,E15-C15)*30),"") | V15: =IFERROR(IF(OR(T15="",C15="",E15=""),"",T15/MAX(1,E15-C15)*365),"")
N16: =IF(OR(M16="",L16=""),"",M16*L16*100) | P16: =IF(OR(O16="",L16=""),"",O16*L16*100) | R16: =IF(OR(L16="",N16=""),"",IF(A16="Buy",N16,IF(B16="Put Spread",(H16-I16)*100*L16-N16,IF(B16="Call Spread",(K16-J16)*100*L16-N16,IF(B16="Iron Condor",MAX((H16-I16),(K16-J16))*100*L16-N16,""))))) | S16: =IFERROR(IF(OR(N16="",E16=""),"",IF(A16="Buy",IF(P16="","",P16-N16-IF(Q16="",0,Q16)),IF(P16="","",N16-P16-IF(Q16="",0,Q16)))),"") | T16: =IFERROR(IF(S16="","",S16/R16),"") | U16: =IFERROR(IF(OR(T16="",C16="",E16=""),"",T16/MAX(1,E16-C16)*30),"") | V16: =IFERROR(IF(OR(T16="",C16="",E16=""),"",T16/MAX(1,E16-C16)*365),"")
... N304: =IF(OR(M304="",L304=""),"",M304*L304*100) | P304: =IF(OR(O304="",L304=""),"",O304*L304*100) | R304: =IF(OR(L304="",N304=""),"",IF(A304="Buy",N304,IF(B304="Put Spread",(H304-I304)*100*L304-N304,IF(B304="Call Spread",(K304-J304)*100*L304-N304,IF(B304="Iron Condor",MAX((H304-I304),(K304-J304))*100*L304-N304,""))))) | S304: =IFERROR(IF(OR(N304="",E304=""),"",IF(A304="Buy",IF(P304="","",P304-N304-IF(Q304="",0,Q304)),IF(P304="","",N304-P304-IF(Q304="",0,Q304)))),"") | T304: =IFERROR(IF(S304="","",S304/R304),"") | U304: =IFERROR(IF(OR(T304="",C304="",E304=""),"",T304/MAX(1,E304-C304)*30),"") | V304: =IFERROR(IF(OR(T304="",C304="",E304=""),"",T304/MAX(1,E304-C304)*365),"")

Sheet Buy-Writes
A1: Practical Income Investing - Buy-Writes
A2: TOTAL PROFIT | F2: =SUM(S5:S304) -> 0 | J2: COLLATERAL USED | N2: =IFERROR(SUM(P5:P304),0) -> 0 | P2: TOTAL ROC | S2: =IFERROR(SUM(S5:S304)/SUM(P5:P304),0) -> 0 | V2: Locked Cells | W2: Manually Enter
A3: WINS | D3: =COUNTIF(S5:S304,">0") -> 0 | E3: LOSSES | G3: =COUNTIF(S5:S304,"<0") -> 0 | H3: WIN RATE | K3: =IFERROR(D3/(D3+G3),0) -> 0 | M3: AVG WIN | O3: =IFERROR(AVERAGEIF(S5:S304,">0"),0) -> 0 | Q3: AVG LOSS | S3: =IFERROR(AVERAGEIF(S5:S304,"<0"),0) -> 0 | V3: Cell Use Guide
A4: # | B4: TICKER | C4: BROKERAGE | D4: OPEN DATE | E4: EXP DATE | F4: SHARES | G4: STOCK PRICE | H4: STOCK COST | I4: STRIKE $ | J4: QTY (CONTRACTS) | K4: PREMIUM $/shr | L4: TOTAL PREMIUM | M4: OPT CLOSE $/shr | N4: TOTAL OPT CLOSE | O4: STK CLOSE $/shr | P4: COLLATERAL $ | Q4: P/L OPTION | R4: P/L STOCK | S4: TOTAL P/L | T4: ROC % | U4: STATUS | V4: NOTES
A5: 1 | H5: =IF(OR(F5="",G5=""),"",F5*G5) | L5: =IF(OR(K5="",J5=""),"",K5*J5*100) | N5: =IF(OR(M5="",J5=""),"",M5*J5*100) | P5: =IF(H5="","",H5) | Q5: =IF(OR(L5="",N5=""),"",L5-N5) | R5: =IF(OR(O5="",G5="",F5=""),"",( O5-G5)*F5) | S5: =IF(AND(Q5="",R5=""),"",IF(Q5="",0,Q5)+IF(R5="",0,R5)) | T5: =IFERROR(IF(S5="","",S5/P5),"") | U5: =IF(B5="","",IF(OR(M5<>"",O5<>""),"Closed","Open"))
A6: 2 | H6: =IF(OR(F6="",G6=""),"",F6*G6) | L6: =IF(OR(K6="",J6=""),"",K6*J6*100) | N6: =IF(OR(M6="",J6=""),"",M6*J6*100) | P6: =IF(H6="","",H6) | Q6: =IF(OR(L6="",N6=""),"",L6-N6) | R6: =IF(OR(O6="",G6="",F6=""),"",( O6-G6)*F6) | S6: =IF(AND(Q6="",R6=""),"",IF(Q6="",0,Q6)+IF(R6="",0,R6)) | T6: =IFERROR(IF(S6="","",S6/P6),"") | U6: =IF(B6="","",IF(OR(M6<>"",O6<>""),"Closed","Open"))
A7: 3 | H7: =IF(OR(F7="",G7=""),"",F7*G7) | L7: =IF(OR(K7="",J7=""),"",K7*J7*100) | N7: =IF(OR(M7="",J7=""),"",M7*J7*100) | P7: =IF(H7="","",H7) | Q7: =IF(OR(L7="",N7=""),"",L7-N7) | R7: =IF(OR(O7="",G7="",F7=""),"",( O7-G7)*F7) | S7: =IF(AND(Q7="",R7=""),"",IF(Q7="",0,Q7)+IF(R7="",0,R7)) | T7: =IFERROR(IF(S7="","",S7/P7),"") | U7: =IF(B7="","",IF(OR(M7<>"",O7<>""),"Closed","Open"))
A8: 4 | H8: =IF(OR(F8="",G8=""),"",F8*G8) | L8: =IF(OR(K8="",J8=""),"",K8*J8*100) | N8: =IF(OR(M8="",J8=""),"",M8*J8*100) | P8: =IF(H8="","",H8) | Q8: =IF(OR(L8="",N8=""),"",L8-N8) | R8: =IF(OR(O8="",G8="",F8=""),"",( O8-G8)*F8) | S8: =IF(AND(Q8="",R8=""),"",IF(Q8="",0,Q8)+IF(R8="",0,R8)) | T8: =IFERROR(IF(S8="","",S8/P8),"") | U8: =IF(B8="","",IF(OR(M8<>"",O8<>""),"Closed","Open"))
A9: 5 | H9: =IF(OR(F9="",G9=""),"",F9*G9) | L9: =IF(OR(K9="",J9=""),"",K9*J9*100) | N9: =IF(OR(M9="",J9=""),"",M9*J9*100) | P9: =IF(H9="","",H9) | Q9: =IF(OR(L9="",N9=""),"",L9-N9) | R9: =IF(OR(O9="",G9="",F9=""),"",( O9-G9)*F9) | S9: =IF(AND(Q9="",R9=""),"",IF(Q9="",0,Q9)+IF(R9="",0,R9)) | T9: =IFERROR(IF(S9="","",S9/P9),"") | U9: =IF(B9="","",IF(OR(M9<>"",O9<>""),"Closed","Open"))
A10: 6 | H10: =IF(OR(F10="",G10=""),"",F10*G10) | L10: =IF(OR(K10="",J10=""),"",K10*J10*100) | N10: =IF(OR(M10="",J10=""),"",M10*J10*100) | P10: =IF(H10="","",H10) | Q10: =IF(OR(L10="",N10=""),"",L10-N10) | R10: =IF(OR(O10="",G10="",F10=""),"",( O10-G10)*F10) | S10: =IF(AND(Q10="",R10=""),"",IF(Q10="",0,Q10)+IF(R10="",0,R10)) | T10: =IFERROR(IF(S10="","",S10/P10),"") | U10: =IF(B10="","",IF(OR(M10<>"",O10<>""),"Closed","Open"))
A11: 7 | H11: =IF(OR(F11="",G11=""),"",F11*G11) | L11: =IF(OR(K11="",J11=""),"",K11*J11*100) | N11: =IF(OR(M11="",J11=""),"",M11*J11*100) | P11: =IF(H11="","",H11) | Q11: =IF(OR(L11="",N11=""),"",L11-N11) | R11: =IF(OR(O11="",G11="",F11=""),"",( O11-G11)*F11) | S11: =IF(AND(Q11="",R11=""),"",IF(Q11="",0,Q11)+IF(R11="",0,R11)) | T11: =IFERROR(IF(S11="","",S11/P11),"") | U11: =IF(B11="","",IF(OR(M11<>"",O11<>""),"Closed","Open"))
A12: 8 | H12: =IF(OR(F12="",G12=""),"",F12*G12) | L12: =IF(OR(K12="",J12=""),"",K12*J12*100) | N12: =IF(OR(M12="",J12=""),"",M12*J12*100) | P12: =IF(H12="","",H12) | Q12: =IF(OR(L12="",N12=""),"",L12-N12) | R12: =IF(OR(O12="",G12="",F12=""),"",( O12-G12)*F12) | S12: =IF(AND(Q12="",R12=""),"",IF(Q12="",0,Q12)+IF(R12="",0,R12)) | T12: =IFERROR(IF(S12="","",S12/P12),"") | U12: =IF(B12="","",IF(OR(M12<>"",O12<>""),"Closed","Open"))
A13: 9 | H13: =IF(OR(F13="",G13=""),"",F13*G13) | L13: =IF(OR(K13="",J13=""),"",K13*J13*100) | N13: =IF(OR(M13="",J13=""),"",M13*J13*100) | P13: =IF(H13="","",H13) | Q13: =IF(OR(L13="",N13=""),"",L13-N13) | R13: =IF(OR(O13="",G13="",F13=""),"",( O13-G13)*F13) | S13: =IF(AND(Q13="",R13=""),"",IF(Q13="",0,Q13)+IF(R13="",0,R13)) | T13: =IFERROR(IF(S13="","",S13/P13),"") | U13: =IF(B13="","",IF(OR(M13<>"",O13<>""),"Closed","Open"))
A14: 10 | H14: =IF(OR(F14="",G14=""),"",F14*G14) | L14: =IF(OR(K14="",J14=""),"",K14*J14*100) | N14: =IF(OR(M14="",J14=""),"",M14*J14*100) | P14: =IF(H14="","",H14) | Q14: =IF(OR(L14="",N14=""),"",L14-N14) | R14: =IF(OR(O14="",G14="",F14=""),"",( O14-G14)*F14) | S14: =IF(AND(Q14="",R14=""),"",IF(Q14="",0,Q14)+IF(R14="",0,R14)) | T14: =IFERROR(IF(S14="","",S14/P14),"") | U14: =IF(B14="","",IF(OR(M14<>"",O14<>""),"Closed","Open"))
A15: 11 | H15: =IF(OR(F15="",G15=""),"",F15*G15) | L15: =IF(OR(K15="",J15=""),"",K15*J15*100) | N15: =IF(OR(M15="",J15=""),"",M15*J15*100) | P15: =IF(H15="","",H15) | Q15: =IF(OR(L15="",N15=""),"",L15-N15) | R15: =IF(OR(O15="",G15="",F15=""),"",( O15-G15)*F15) | S15: =IF(AND(Q15="",R15=""),"",IF(Q15="",0,Q15)+IF(R15="",0,R15)) | T15: =IFERROR(IF(S15="","",S15/P15),"") | U15: =IF(B15="","",IF(OR(M15<>"",O15<>""),"Closed","Open"))
A16: 12 | H16: =IF(OR(F16="",G16=""),"",F16*G16) | L16: =IF(OR(K16="",J16=""),"",K16*J16*100) | N16: =IF(OR(M16="",J16=""),"",M16*J16*100) | P16: =IF(H16="","",H16) | Q16: =IF(OR(L16="",N16=""),"",L16-N16) | R16: =IF(OR(O16="",G16="",F16=""),"",( O16-G16)*F16) | S16: =IF(AND(Q16="",R16=""),"",IF(Q16="",0,Q16)+IF(R16="",0,R16)) | T16: =IFERROR(IF(S16="","",S16/P16),"") | U16: =IF(B16="","",IF(OR(M16<>"",O16<>""),"Closed","Open"))
... A304: 300 | H304: =IF(OR(F304="",G304=""),"",F304*G304) | L304: =IF(OR(K304="",J304=""),"",K304*J304*100) | N304: =IF(OR(M304="",J304=""),"",M304*J304*100) | P304: =IF(H304="","",H304) | Q304: =IF(OR(L304="",N304=""),"",L304-N304) | R304: =IF(OR(O304="",G304="",F304=""),"",( O304-G304)*F304) | S304: =IF(AND(Q304="",R304=""),"",IF(Q304="",0,Q304)+IF(R304="",0,R304)) | T304: =IFERROR(IF(S304="","",S304/P304),"") | U304: =IF(B304="","",IF(OR(M304<>"",O304<>""),"Closed","Open"))

Sheet Stocks
A1: Practical Income Investing - Stock Portfolio
A2: REALIZED P&L | E2: =IFERROR(SUMIF(R5:R304,"Closed",P5:P304),0) -> 0 | H2: UNREALIZED P&L | K2: =IFERROR(SUMIF(R5:R304,"Open",K5:K304),0) -> 0 | N2: OPEN POSITIONS | Q2: =COUNTIF(R5:R304,"Open") -> 0 | S2: Locked Cells | T2: Manually Enter
A3: TOTAL POSITIONS | D3: =COUNTA(B5:B304) -> 0 | F3: CLOSED | H3: =COUNTIF(R5:R304,"Closed") -> 0 | J3: TOTAL MKT VALUE | L3: =IFERROR(SUMIF(R5:R304,"Open",J5:J304),0) -> 0 | O3: TOTAL COST BASIS | Q3: =IFERROR(SUMIF(R5:R304,"Open",H5:H304),0) -> 0 | S3: Cell Use Guide
A4: # | B4: TICKER | C4: BROKERAGE | D4: BUY DATE | E4: SHARES | F4: BUY PRICE | G4: FEES | H4: COST BASIS | I4: CUR PRICE | J4: MKT VALUE | K4: UNREAL $ | L4: UNREAL % | M4: SELL DATE | N4: SELL PRICE | O4: PROCEEDS | P4: REAL $ | Q4: REAL % | R4: STATUS | S4: NOTES
A5: 1 | H5: =IF(OR(E5="",F5=""),"",E5*F5+IF(G5="",0,G5)) | I5: =IFERROR(__xludf.DUMMYFUNCTION("IF(B5="""","""",IFERROR(GOOGLEFINANCE(UPPER(B5),""price""),""""))"),"") | J5: =IF(OR(E5="",I5="",R5="Closed"),"",E5*I5) | K5: =IF(OR(J5="",H5="",R5="Closed"),"",J5-H5) | L5: =IF(OR(J5="",H5="",H5=0,R5="Closed"),"",(J5-H5)/H5) | O5: =IF(OR(E5="",N5=""),"",E5*N5) | P5: =IF(OR(O5="",H5=""),"",O5-H5) | Q5: =IF(OR(O5="",H5="",H5=0),"",(O5-H5)/H5) | R5: =IF(B5="","",IF(M5="","Open","Closed"))
A6: 2 | H6: =IF(OR(E6="",F6=""),"",E6*F6+IF(G6="",0,G6)) | I6: =IFERROR(__xludf.DUMMYFUNCTION("IF(B6="""","""",IFERROR(GOOGLEFINANCE(UPPER(B6),""price""),""""))"),"") | J6: =IF(OR(E6="",I6="",R6="Closed"),"",E6*I6) | K6: =IF(OR(J6="",H6="",R6="Closed"),"",J6-H6) | L6: =IF(OR(J6="",H6="",H6=0,R6="Closed"),"",(J6-H6)/H6) | O6: =IF(OR(E6="",N6=""),"",E6*N6) | P6: =IF(OR(O6="",H6=""),"",O6-H6) | Q6: =IF(OR(O6="",H6="",H6=0),"",(O6-H6)/H6) | R6: =IF(B6="","",IF(M6="","Open","Closed"))
A7: 3 | H7: =IF(OR(E7="",F7=""),"",E7*F7+IF(G7="",0,G7)) | I7: =IFERROR(__xludf.DUMMYFUNCTION("IF(B7="""","""",IFERROR(GOOGLEFINANCE(UPPER(B7),""price""),""""))"),"") | J7: =IF(OR(E7="",I7="",R7="Closed"),"",E7*I7) | K7: =IF(OR(J7="",H7="",R7="Closed"),"",J7-H7) | L7: =IF(OR(J7="",H7="",H7=0,R7="Closed"),"",(J7-H7)/H7) | O7: =IF(OR(E7="",N7=""),"",E7*N7) | P7: =IF(OR(O7="",H7=""),"",O7-H7) | Q7: =IF(OR(O7="",H7="",H7=0),"",(O7-H7)/H7) | R7: =IF(B7="","",IF(M7="","Open","Closed"))
A8: 4 | H8: =IF(OR(E8="",F8=""),"",E8*F8+IF(G8="",0,G8)) | I8: =IFERROR(__xludf.DUMMYFUNCTION("IF(B8="""","""",IFERROR(GOOGLEFINANCE(UPPER(B8),""price""),""""))"),"") | J8: =IF(OR(E8="",I8="",R8="Closed"),"",E8*I8) | K8: =IF(OR(J8="",H8="",R8="Closed"),"",J8-H8) | L8: =IF(OR(J8="",H8="",H8=0,R8="Closed"),"",(J8-H8)/H8) | O8: =IF(OR(E8="",N8=""),"",E8*N8) | P8: =IF(OR(O8="",H8=""),"",O8-H8) | Q8: =IF(OR(O8="",H8="",H8=0),"",(O8-H8)/H8) | R8: =IF(B8="","",IF(M8="","Open","Closed"))
A9: 5 | H9: =IF(OR(E9="",F9=""),"",E9*F9+IF(G9="",0,G9)) | I9: =IFERROR(__xludf.DUMMYFUNCTION("IF(B9="""","""",IFERROR(GOOGLEFINANCE(UPPER(B9),""price""),""""))"),"") | J9: =IF(OR(E9="",I9="",R9="Closed"),"",E9*I9) | K9: =IF(OR(J9="",H9="",R9="Closed"),"",J9-H9) | L9: =IF(OR(J9="",H9="",H9=0,R9="Closed"),"",(J9-H9)/H9) | O9: =IF(OR(E9="",N9=""),"",E9*N9) | P9: =IF(OR(O9="",H9=""),"",O9-H9) | Q9: =IF(OR(O9="",H9="",H9=0),"",(O9-H9)/H9) | R9: =IF(B9="","",IF(M9="","Open","Closed"))
A10: 6 | H10: =IF(OR(E10="",F10=""),"",E10*F10+IF(G10="",0,G10)) | I10: =IFERROR(__xludf.DUMMYFUNCTION("IF(B10="""","""",IFERROR(GOOGLEFINANCE(UPPER(B10),""price""),""""))"),"") | J10: =IF(OR(E10="",I10="",R10="Closed"),"",E10*I10) | K10: =IF(OR(J10="",H10="",R10="Closed"),"",J10-H10) | L10: =IF(OR(J10="",H10="",H10=0,R10="Closed"),"",(J10-H10)/H10) | O10: =IF(OR(E10="",N10=""),"",E10*N10) | P10: =IF(OR(O10="",H10=""),"",O10-H10) | Q10: =IF(OR(O10="",H10="",H10=0),"",(O10-H10)/H10) | R10: =IF(B10="","",IF(M10="","Open","Closed"))
A11: 7 | H11: =IF(OR(E11="",F11=""),"",E11*F11+IF(G11="",0,G11)) | I11: =IFERROR(__xludf.DUMMYFUNCTION("IF(B11="""","""",IFERROR(GOOGLEFINANCE(UPPER(B11),""price""),""""))"),"") | J11: =IF(OR(E11="",I11="",R11="Closed"),"",E11*I11) | K11: =IF(OR(J11="",H11="",R11="Closed"),"",J11-H11) | L11: =IF(OR(J11="",H11="",H11=0,R11="Closed"),"",(J11-H11)/H11) | O11: =IF(OR(E11="",N11=""),"",E11*N11) | P11: =IF(OR(O11="",H11=""),"",O11-H11) | Q11: =IF(OR(O11="",H11="",H11=0),"",(O11-H11)/H11) | R11: =IF(B11="","",IF(M11="","Open","Closed"))
A12: 8 | H12: =IF(OR(E12="",F12=""),"",E12*F12+IF(G12="",0,G12)) | I12: =IFERROR(__xludf.DUMMYFUNCTION("IF(B12="""","""",IFERROR(GOOGLEFINANCE(UPPER(B12),""price""),""""))"),"") | J12: =IF(OR(E12="",I12="",R12="Closed"),"",E12*I12) | K12: =IF(OR(J12="",H12="",R12="Closed"),"",J12-H12) | L12: =IF(OR(J12="",H12="",H12=0,R12="Closed"),"",(J12-H12)/H12) | O12: =IF(OR(E12="",N12=""),"",E12*N12) | P12: =IF(OR(O12="",H12=""),"",O12-H12) | Q12: =IF(OR(O12="",H12="",H12=0),"",(O12-H12)/H12) | R12: =IF(B12="","",IF(M12="","Open","Closed"))
A13: 9 | H13: =IF(OR(E13="",F13=""),"",E13*F13+IF(G13="",0,G13)) | I13: =IFERROR(__xludf.DUMMYFUNCTION("IF(B13="""","""",IFERROR(GOOGLEFINANCE(UPPER(B13),""price""),""""))"),"") | J13: =IF(OR(E13="",I13="",R13="Closed"),"",E13*I13) | K13: =IF(OR(J13="",H13="",R13="Closed"),"",J13-H13) | L13: =IF(OR(J13="",H13="",H13=0,R13="Closed"),"",(J13-H13)/H13) | O13: =IF(OR(E13="",N13=""),"",E13*N13) | P13: =IF(OR(O13="",H13=""),"",O13-H13) | Q13: =IF(OR(O13="",H13="",H13=0),"",(O13-H13)/H13) | R13: =IF(B13="","",IF(M13="","Open","Closed"))
A14: 10 | H14: =IF(OR(E14="",F14=""),"",E14*F14+IF(G14="",0,G14)) | I14: =IFERROR(__xludf.DUMMYFUNCTION("IF(B14="""","""",IFERROR(GOOGLEFINANCE(UPPER(B14),""price""),""""))"),"") | J14: =IF(OR(E14="",I14="",R14="Closed"),"",E14*I14) | K14: =IF(OR(J14="",H14="",R14="Closed"),"",J14-H14) | L14: =IF(OR(J14="",H14="",H14=0,R14="Closed"),"",(J14-H14)/H14) | O14: =IF(OR(E14="",N14=""),"",E14*N14) | P14: =IF(OR(O14="",H14=""),"",O14-H14) | Q14: =IF(OR(O14="",H14="",H14=0),"",(O14-H14)/H14) | R14: =IF(B14="","",IF(M14="","Open","Closed"))
A15: 11 | H15: =IF(OR(E15="",F15=""),"",E15*F15+IF(G15="",0,G15)) | I15: =IFERROR(__xludf.DUMMYFUNCTION("IF(B15="""","""",IFERROR(GOOGLEFINANCE(UPPER(B15),""price""),""""))"),"") | J15: =IF(OR(E15="",I15="",R15="Closed"),"",E15*I15) | K15: =IF(OR(J15="",H15="",R15="Closed"),"",J15-H15) | L15: =IF(OR(J15="",H15="",H15=0,R15="Closed"),"",(J15-H15)/H15) | O15: =IF(OR(E15="",N15=""),"",E15*N15) | P15: =IF(OR(O15="",H15=""),"",O15-H15) | Q15: =IF(OR(O15="",H15="",H15=0),"",(O15-H15)/H15) | R15: =IF(B15="","",IF(M15="","Open","Closed"))
A16: 12 | H16: =IF(OR(E16="",F16=""),"",E16*F16+IF(G16="",0,G16)) | I16: =IFERROR(__xludf.DUMMYFUNCTION("IF(B16="""","""",IFERROR(GOOGLEFINANCE(UPPER(B16),""price""),""""))"),"") | J16: =IF(OR(E16="",I16="",R16="Closed"),"",E16*I16) | K16: =IF(OR(J16="",H16="",R16="Closed"),"",J16-H16) | L16: =IF(OR(J16="",H16="",H16=0,R16="Closed"),"",(J16-H16)/H16) | O16: =IF(OR(E16="",N16=""),"",E16*N16) | P16: =IF(OR(O16="",H16=""),"",O16-H16) | Q16: =IF(OR(O16="",H16="",H16=0),"",(O16-H16)/H16) | R16: =IF(B16="","",IF(M16="","Open","Closed"))
A17: 13 | H17: =IF(OR(E17="",F17=""),"",E17*F17+IF(G17="",0,G17)) | I17: =IFERROR(__xludf.DUMMYFUNCTION("IF(B17="""","""",IFERROR(GOOGLEFINANCE(UPPER(B17),""price""),""""))"),"") | J17: =IF(OR(E17="",I17="",R17="Closed"),"",E17*I17) | K17: =IF(OR(J17="",H17="",R17="Closed"),"",J17-H17) | L17: =IF(OR(J17="",H17="",H17=0,R17="Closed"),"",(J17-H17)/H17) | O17: =IF(OR(E17="",N17=""),"",E17*N17) | P17: =IF(OR(O17="",H17=""),"",O17-H17) | Q17: =IF(OR(O17="",H17="",H17=0),"",(O17-H17)/H17) | R17: =IF(B17="","",IF(M17="","Open","Closed"))
A18: 14 | H18: =IF(OR(E18="",F18=""),"",E18*F18+IF(G18="",0,G18)) | I18: =IFERROR(__xludf.DUMMYFUNCTION("IF(B18="""","""",IFERROR(GOOGLEFINANCE(UPPER(B18),""price""),""""))"),"") | J18: =IF(OR(E18="",I18="",R18="Closed"),"",E18*I18) | K18: =IF(OR(J18="",H18="",R18="Closed"),"",J18-H18) | L18: =IF(OR(J18="",H18="",H18=0,R18="Closed"),"",(J18-H18)/H18) | O18: =IF(OR(E18="",N18=""),"",E18*N18) | P18: =IF(OR(O18="",H18=""),"",O18-H18) | Q18: =IF(OR(O18="",H18="",H18=0),"",(O18-H18)/H18) | R18: =IF(B18="","",IF(M18="","Open","Closed"))
A19: 15 | H19: =IF(OR(E19="",F19=""),"",E19*F19+IF(G19="",0,G19)) | I19: =IFERROR(__xludf.DUMMYFUNCTION("IF(B19="""","""",IFERROR(GOOGLEFINANCE(UPPER(B19),""price""),""""))"),"") | J19: =IF(OR(E19="",I19="",R19="Closed"),"",E19*I19) | K19: =IF(OR(J19="",H19="",R19="Closed"),"",J19-H19) | L19: =IF(OR(J19="",H19="",H19=0,R19="Closed"),"",(J19-H19)/H19) | O19: =IF(OR(E19="",N19=""),"",E19*N19) | P19: =IF(OR(O19="",H19=""),"",O19-H19) | Q19: =IF(OR(O19="",H19="",H19=0),"",(O19-H19)/H19) | R19: =IF(B19="","",IF(M19="","Open","Closed"))
A20: 16 | H20: =IF(OR(E20="",F20=""),"",E20*F20+IF(G20="",0,G20)) | I20: =IFERROR(__xludf.DUMMYFUNCTION("IF(B20="""","""",IFERROR(GOOGLEFINANCE(UPPER(B20),""price""),""""))"),"") | J20: =IF(OR(E20="",I20="",R20="Closed"),"",E20*I20) | K20: =IF(OR(J20="",H20="",R20="Closed"),"",J20-H20) | L20: =IF(OR(J20="",H20="",H20=0,R20="Closed"),"",(J20-H20)/H20) | O20: =IF(OR(E20="",N20=""),"",E20*N20) | P20: =IF(OR(O20="",H20=""),"",O20-H20) | Q20: =IF(OR(O20="",H20="",H20=0),"",(O20-H20)/H20) | R20: =IF(B20="","",IF(M20="","Open","Closed"))
A21: 17 | H21: =IF(OR(E21="",F21=""),"",E21*F21+IF(G21="",0,G21)) | I21: =IFERROR(__xludf.DUMMYFUNCTION("IF(B21="""","""",IFERROR(GOOGLEFINANCE(UPPER(B21),""price""),""""))"),"") | J21: =IF(OR(E21="",I21="",R21="Closed"),"",E21*I21) | K21: =IF(OR(J21="",H21="",R21="Closed"),"",J21-H21) | L21: =IF(OR(J21="",H21="",H21=0,R21="Closed"),"",(J21-H21)/H21) | O21: =IF(OR(E21="",N21=""),"",E21*N21) | P21: =IF(OR(O21="",H21=""),"",O21-H21) | Q21: =IF(OR(O21="",H21="",H21=0),"",(O21-H21)/H21) | R21: =IF(B21="","",IF(M21="","Open","Closed"))
A22: 18 | H22: =IF(OR(E22="",F22=""),"",E22*F22+IF(G22="",0,G22)) | I22: =IFERROR(__xludf.DUMMYFUNCTION("IF(B22="""","""",IFERROR(GOOGLEFINANCE(UPPER(B22),""price""),""""))"),"") | J22: =IF(OR(E22="",I22="",R22="Closed"),"",E22*I22) | K22: =IF(OR(J22="",H22="",R22="Closed"),"",J22-H22) | L22: =IF(OR(J22="",H22="",H22=0,R22="Closed"),"",(J22-H22)/H22) | O22: =IF(OR(E22="",N22=""),"",E22*N22) | P22: =IF(OR(O22="",H22=""),"",O22-H22) | Q22: =IF(OR(O22="",H22="",H22=0),"",(O22-H22)/H22) | R22: =IF(B22="","",IF(M22="","Open","Closed"))
A23: 19 | H23: =IF(OR(E23="",F23=""),"",E23*F23+IF(G23="",0,G23)) | I23: =IFERROR(__xludf.DUMMYFUNCTION("IF(B23="""","""",IFERROR(GOOGLEFINANCE(UPPER(B23),""price""),""""))"),"") | J23: =IF(OR(E23="",I23="",R23="Closed"),"",E23*I23) | K23: =IF(OR(J23="",H23="",R23="Closed"),"",J23-H23) | L23: =IF(OR(J23="",H23="",H23=0,R23="Closed"),"",(J23-H23)/H23) | O23: =IF(OR(E23="",N23=""),"",E23*N23) | P23: =IF(OR(O23="",H23=""),"",O23-H23) | Q23: =IF(OR(O23="",H23="",H23=0),"",(O23-H23)/H23) | R23: =IF(B23="","",IF(M23="","Open","Closed"))
A24: 20 | H24: =IF(OR(E24="",F24=""),"",E24*F24+IF(G24="",0,G24)) | I24: =IFERROR(__xludf.DUMMYFUNCTION("IF(B24="""","""",IFERROR(GOOGLEFINANCE(UPPER(B24),""price""),""""))"),"") | J24: =IF(OR(E24="",I24="",R24="Closed"),"",E24*I24) | K24: =IF(OR(J24="",H24="",R24="Closed"),"",J24-H24) | L24: =IF(OR(J24="",H24="",H24=0,R24="Closed"),"",(J24-H24)/H24) | O24: =IF(OR(E24="",N24=""),"",E24*N24) | P24: =IF(OR(O24="",H24=""),"",O24-H24) | Q24: =IF(OR(O24="",H24="",H24=0),"",(O24-H24)/H24) | R24: =IF(B24="","",IF(M24="","Open","Closed"))
A25: 21 | H25: =IF(OR(E25="",F25=""),"",E25*F25+IF(G25="",0,G25)) | I25: =IFERROR(__xludf.DUMMYFUNCTION("IF(B25="""","""",IFERROR(GOOGLEFINANCE(UPPER(B25),""price""),""""))"),"") | J25: =IF(OR(E25="",I25="",R25="Closed"),"",E25*I25) | K25: =IF(OR(J25="",H25="",R25="Closed"),"",J25-H25) | L25: =IF(OR(J25="",H25="",H25=0,R25="Closed"),"",(J25-H25)/H25) | O25: =IF(OR(E25="",N25=""),"",E25*N25) | P25: =IF(OR(O25="",H25=""),"",O25-H25) | Q25: =IF(OR(O25="",H25="",H25=0),"",(O25-H25)/H25) | R25: =IF(B25="","",IF(M25="","Open","Closed"))
A26: 22 | H26: =IF(OR(E26="",F26=""),"",E26*F26+IF(G26="",0,G26)) | I26: =IFERROR(__xludf.DUMMYFUNCTION("IF(B26="""","""",IFERROR(GOOGLEFINANCE(UPPER(B26),""price""),""""))"),"") | J26: =IF(OR(E26="",I26="",R26="Closed"),"",E26*I26) | K26: =IF(OR(J26="",H26="",R26="Closed"),"",J26-H26) | L26: =IF(OR(J26="",H26="",H26=0,R26="Closed"),"",(J26-H26)/H26) | O26: =IF(OR(E26="",N26=""),"",E26*N26) | P26: =IF(OR(O26="",H26=""),"",O26-H26) | Q26: =IF(OR(O26="",H26="",H26=0),"",(O26-H26)/H26) | R26: =IF(B26="","",IF(M26="","Open","Closed"))
A27: 23 | H27: =IF(OR(E27="",F27=""),"",E27*F27+IF(G27="",0,G27)) | I27: =IFERROR(__xludf.DUMMYFUNCTION("IF(B27="""","""",IFERROR(GOOGLEFINANCE(UPPER(B27),""price""),""""))"),"") | J27: =IF(OR(E27="",I27="",R27="Closed"),"",E27*I27) | K27: =IF(OR(J27="",H27="",R27="Closed"),"",J27-H27) | L27: =IF(OR(J27="",H27="",H27=0,R27="Closed"),"",(J27-H27)/H27) | O27: =IF(OR(E27="",N27=""),"",E27*N27) | P27: =IF(OR(O27="",H27=""),"",O27-H27) | Q27: =IF(OR(O27="",H27="",H27=0),"",(O27-H27)/H27) | R27: =IF(B27="","",IF(M27="","Open","Closed"))
A28: 24 | H28: =IF(OR(E28="",F28=""),"",E28*F28+IF(G28="",0,G28)) | I28: =IFERROR(__xludf.DUMMYFUNCTION("IF(B28="""","""",IFERROR(GOOGLEFINANCE(UPPER(B28),""price""),""""))"),"") | J28: =IF(OR(E28="",I28="",R28="Closed"),"",E28*I28) | K28: =IF(OR(J28="",H28="",R28="Closed"),"",J28-H28) | L28: =IF(OR(J28="",H28="",H28=0,R28="Closed"),"",(J28-H28)/H28) | O28: =IF(OR(E28="",N28=""),"",E28*N28) | P28: =IF(OR(O28="",H28=""),"",O28-H28) | Q28: =IF(OR(O28="",H28="",H28=0),"",(O28-H28)/H28) | R28: =IF(B28="","",IF(M28="","Open","Closed"))
A29: 25 | H29: =IF(OR(E29="",F29=""),"",E29*F29+IF(G29="",0,G29)) | I29: =IFERROR(__xludf.DUMMYFUNCTION("IF(B29="""","""",IFERROR(GOOGLEFINANCE(UPPER(B29),""price""),""""))"),"") | J29: =IF(OR(E29="",I29="",R29="Closed"),"",E29*I29) | K29: =IF(OR(J29="",H29="",R29="Closed"),"",J29-H29) | L29: =IF(OR(J29="",H29="",H29=0,R29="Closed"),"",(J29-H29)/H29) | O29: =IF(OR(E29="",N29=""),"",E29*N29) | P29: =IF(OR(O29="",H29=""),"",O29-H29) | Q29: =IF(OR(O29="",H29="",H29=0),"",(O29-H29)/H29) | R29: =IF(B29="","",IF(M29="","Open","Closed"))
A30: 26 | H30: =IF(OR(E30="",F30=""),"",E30*F30+IF(G30="",0,G30)) | I30: =IFERROR(__xludf.DUMMYFUNCTION("IF(B30="""","""",IFERROR(GOOGLEFINANCE(UPPER(B30),""price""),""""))"),"") | J30: =IF(OR(E30="",I30="",R30="Closed"),"",E30*I30) | K30: =IF(OR(J30="",H30="",R30="Closed"),"",J30-H30) | L30: =IF(OR(J30="",H30="",H30=0,R30="Closed"),"",(J30-H30)/H30) | O30: =IF(OR(E30="",N30=""),"",E30*N30) | P30: =IF(OR(O30="",H30=""),"",O30-H30) | Q30: =IF(OR(O30="",H30="",H30=0),"",(O30-H30)/H30) | R30: =IF(B30="","",IF(M30="","Open","Closed"))
A31: 27 | H31: =IF(OR(E31="",F31=""),"",E31*F31+IF(G31="",0,G31)) | I31: =IFERROR(__xludf.DUMMYFUNCTION("IF(B31="""","""",IFERROR(GOOGLEFINANCE(UPPER(B31),""price""),""""))"),"") | J31: =IF(OR(E31="",I31="",R31="Closed"),"",E31*I31) | K31: =IF(OR(J31="",H31="",R31="Closed"),"",J31-H31) | L31: =IF(OR(J31="",H31="",H31=0,R31="Closed"),"",(J31-H31)/H31) | O31: =IF(OR(E31="",N31=""),"",E31*N31) | P31: =IF(OR(O31="",H31=""),"",O31-H31) | Q31: =IF(OR(O31="",H31="",H31=0),"",(O31-H31)/H31) | R31: =IF(B31="","",IF(M31="","Open","Closed"))
A32: 28 | H32: =IF(OR(E32="",F32=""),"",E32*F32+IF(G32="",0,G32)) | I32: =IFERROR(__xludf.DUMMYFUNCTION("IF(B32="""","""",IFERROR(GOOGLEFINANCE(UPPER(B32),""price""),""""))"),"") | J32: =IF(OR(E32="",I32="",R32="Closed"),"",E32*I32) | K32: =IF(OR(J32="",H32="",R32="Closed"),"",J32-H32) | L32: =IF(OR(J32="",H32="",H32=0,R32="Closed"),"",(J32-H32)/H32) | O32: =IF(OR(E32="",N32=""),"",E32*N32) | P32: =IF(OR(O32="",H32=""),"",O32-H32) | Q32: =IF(OR(O32="",H32="",H32=0),"",(O32-H32)/H32) | R32: =IF(B32="","",IF(M32="","Open","Closed"))
A33: 29 | H33: =IF(OR(E33="",F33=""),"",E33*F33+IF(G33="",0,G33)) | I33: =IFERROR(__xludf.DUMMYFUNCTION("IF(B33="""","""",IFERROR(GOOGLEFINANCE(UPPER(B33),""price""),""""))"),"") | J33: =IF(OR(E33="",I33="",R33="Closed"),"",E33*I33) | K33: =IF(OR(J33="",H33="",R33="Closed"),"",J33-H33) | L33: =IF(OR(J33="",H33="",H33=0,R33="Closed"),"",(J33-H33)/H33) | O33: =IF(OR(E33="",N33=""),"",E33*N33) | P33: =IF(OR(O33="",H33=""),"",O33-H33) | Q33: =IF(OR(O33="",H33="",H33=0),"",(O33-H33)/H33) | R33: =IF(B33="","",IF(M33="","Open","Closed"))
A34: 30 | H34: =IF(OR(E34="",F34=""),"",E34*F34+IF(G34="",0,G34)) | I34: =IFERROR(__xludf.DUMMYFUNCTION("IF(B34="""","""",IFERROR(GOOGLEFINANCE(UPPER(B34),""price""),""""))"),"") | J34: =IF(OR(E34="",I34="",R34="Closed"),"",E34*I34) | K34: =IF(OR(J34="",H34="",R34="Closed"),"",J34-H34) | L34: =IF(OR(J34="",H34="",H34=0,R34="Closed"),"",(J34-H34)/H34) | O34: =IF(OR(E34="",N34=""),"",E34*N34) | P34: =IF(OR(O34="",H34=""),"",O34-H34) | Q34: =IF(OR(O34="",H34="",H34=0),"",(O34-H34)/H34) | R34: =IF(B34="","",IF(M34="","Open","Closed"))
A35: 31 | H35: =IF(OR(E35="",F35=""),"",E35*F35+IF(G35="",0,G35)) | I35: =IFERROR(__xludf.DUMMYFUNCTION("IF(B35="""","""",IFERROR(GOOGLEFINANCE(UPPER(B35),""price""),""""))"),"") | J35: =IF(OR(E35="",I35="",R35="Closed"),"",E35*I35) | K35: =IF(OR(J35="",H35="",R35="Closed"),"",J35-H35) | L35: =IF(OR(J35="",H35="",H35=0,R35="Closed"),"",(J35-H35)/H35) | O35: =IF(OR(E35="",N35=""),"",E35*N35) | P35: =IF(OR(O35="",H35=""),"",O35-H35) | Q35: =IF(OR(O35="",H35="",H35=0),"",(O35-H35)/H35) | R35: =IF(B35="","",IF(M35="","Open","Closed"))
A36: 32 | H36: =IF(OR(E36="",F36=""),"",E36*F36+IF(G36="",0,G36)) | I36: =IFERROR(__xludf.DUMMYFUNCTION("IF(B36="""","""",IFERROR(GOOGLEFINANCE(UPPER(B36),""price""),""""))"),"") | J36: =IF(OR(E36="",I36="",R36="Closed"),"",E36*I36) | K36: =IF(OR(J36="",H36="",R36="Closed"),"",J36-H36) | L36: =IF(OR(J36="",H36="",H36=0,R36="Closed"),"",(J36-H36)/H36) | O36: =IF(OR(E36="",N36=""),"",E36*N36) | P36: =IF(OR(O36="",H36=""),"",O36-H36) | Q36: =IF(OR(O36="",H36="",H36=0),"",(O36-H36)/H36) | R36: =IF(B36="","",IF(M36="","Open","Closed"))
A37: 33 | H37: =IF(OR(E37="",F37=""),"",E37*F37+IF(G37="",0,G37)) | I37: =IFERROR(__xludf.DUMMYFUNCTION("IF(B37="""","""",IFERROR(GOOGLEFINANCE(UPPER(B37),""price""),""""))"),"") | J37: =IF(OR(E37="",I37="",R37="Closed"),"",E37*I37) | K37: =IF(OR(J37="",H37="",R37="Closed"),"",J37-H37) | L37: =IF(OR(J37="",H37="",H37=0,R37="Closed"),"",(J37-H37)/H37) | O37: =IF(OR(E37="",N37=""),"",E37*N37) | P37: =IF(OR(O37="",H37=""),"",O37-H37) | Q37: =IF(OR(O37="",H37="",H37=0),"",(O37-H37)/H37) | R37: =IF(B37="","",IF(M37="","Open","Closed"))
A38: 34 | H38: =IF(OR(E38="",F38=""),"",E38*F38+IF(G38="",0,G38)) | I38: =IFERROR(__xludf.DUMMYFUNCTION("IF(B38="""","""",IFERROR(GOOGLEFINANCE(UPPER(B38),""price""),""""))"),"") | J38: =IF(OR(E38="",I38="",R38="Closed"),"",E38*I38) | K38: =IF(OR(J38="",H38="",R38="Closed"),"",J38-H38) | L38: =IF(OR(J38="",H38="",H38=0,R38="Closed"),"",(J38-H38)/H38) | O38: =IF(OR(E38="",N38=""),"",E38*N38) | P38: =IF(OR(O38="",H38=""),"",O38-H38) | Q38: =IF(OR(O38="",H38="",H38=0),"",(O38-H38)/H38) | R38: =IF(B38="","",IF(M38="","Open","Closed"))
A39: 35 | H39: =IF(OR(E39="",F39=""),"",E39*F39+IF(G39="",0,G39)) | I39: =IFERROR(__xludf.DUMMYFUNCTION("IF(B39="""","""",IFERROR(GOOGLEFINANCE(UPPER(B39),""price""),""""))"),"") | J39: =IF(OR(E39="",I39="",R39="Closed"),"",E39*I39) | K39: =IF(OR(J39="",H39="",R39="Closed"),"",J39-H39) | L39: =IF(OR(J39="",H39="",H39=0,R39="Closed"),"",(J39-H39)/H39) | O39: =IF(OR(E39="",N39=""),"",E39*N39) | P39: =IF(OR(O39="",H39=""),"",O39-H39) | Q39: =IF(OR(O39="",H39="",H39=0),"",(O39-H39)/H39) | R39: =IF(B39="","",IF(M39="","Open","Closed"))
A40: 36 | H40: =IF(OR(E40="",F40=""),"",E40*F40+IF(G40="",0,G40)) | I40: =IFERROR(__xludf.DUMMYFUNCTION("IF(B40="""","""",IFERROR(GOOGLEFINANCE(UPPER(B40),""price""),""""))"),"") | J40: =IF(OR(E40="",I40="",R40="Closed"),"",E40*I40) | K40: =IF(OR(J40="",H40="",R40="Closed"),"",J40-H40) | L40: =IF(OR(J40="",H40="",H40=0,R40="Closed"),"",(J40-H40)/H40) | O40: =IF(OR(E40="",N40=""),"",E40*N40) | P40: =IF(OR(O40="",H40=""),"",O40-H40) | Q40: =IF(OR(O40="",H40="",H40=0),"",(O40-H40)/H40) | R40: =IF(B40="","",IF(M40="","Open","Closed"))
A41: 37 | H41: =IF(OR(E41="",F41=""),"",E41*F41+IF(G41="",0,G41)) | I41: =IFERROR(__xludf.DUMMYFUNCTION("IF(B41="""","""",IFERROR(GOOGLEFINANCE(UPPER(B41),""price""),""""))"),"") | J41: =IF(OR(E41="",I41="",R41="Closed"),"",E41*I41) | K41: =IF(OR(J41="",H41="",R41="Closed"),"",J41-H41) | L41: =IF(OR(J41="",H41="",H41=0,R41="Closed"),"",(J41-H41)/H41) | O41: =IF(OR(E41="",N41=""),"",E41*N41) | P41: =IF(OR(O41="",H41=""),"",O41-H41) | Q41: =IF(OR(O41="",H41="",H41=0),"",(O41-H41)/H41) | R41: =IF(B41="","",IF(M41="","Open","Closed"))
A42: 38 | H42: =IF(OR(E42="",F42=""),"",E42*F42+IF(G42="",0,G42)) | I42: =IFERROR(__xludf.DUMMYFUNCTION("IF(B42="""","""",IFERROR(GOOGLEFINANCE(UPPER(B42),""price""),""""))"),"") | J42: =IF(OR(E42="",I42="",R42="Closed"),"",E42*I42) | K42: =IF(OR(J42="",H42="",R42="Closed"),"",J42-H42) | L42: =IF(OR(J42="",H42="",H42=0,R42="Closed"),"",(J42-H42)/H42) | O42: =IF(OR(E42="",N42=""),"",E42*N42) | P42: =IF(OR(O42="",H42=""),"",O42-H42) | Q42: =IF(OR(O42="",H42="",H42=0),"",(O42-H42)/H42) | R42: =IF(B42="","",IF(M42="","Open","Closed"))
A43: 39 | H43: =IF(OR(E43="",F43=""),"",E43*F43+IF(G43="",0,G43)) | I43: =IFERROR(__xludf.DUMMYFUNCTION("IF(B43="""","""",IFERROR(GOOGLEFINANCE(UPPER(B43),""price""),""""))"),"") | J43: =IF(OR(E43="",I43="",R43="Closed"),"",E43*I43) | K43: =IF(OR(J43="",H43="",R43="Closed"),"",J43-H43) | L43: =IF(OR(J43="",H43="",H43=0,R43="Closed"),"",(J43-H43)/H43) | O43: =IF(OR(E43="",N43=""),"",E43*N43) | P43: =IF(OR(O43="",H43=""),"",O43-H43) | Q43: =IF(OR(O43="",H43="",H43=0),"",(O43-H43)/H43) | R43: =IF(B43="","",IF(M43="","Open","Closed"))
A44: 40 | H44: =IF(OR(E44="",F44=""),"",E44*F44+IF(G44="",0,G44)) | I44: =IFERROR(__xludf.DUMMYFUNCTION("IF(B44="""","""",IFERROR(GOOGLEFINANCE(UPPER(B44),""price""),""""))"),"") | J44: =IF(OR(E44="",I44="",R44="Closed"),"",E44*I44) | K44: =IF(OR(J44="",H44="",R44="Closed"),"",J44-H44) | L44: =IF(OR(J44="",H44="",H44=0,R44="Closed"),"",(J44-H44)/H44) | O44: =IF(OR(E44="",N44=""),"",E44*N44) | P44: =IF(OR(O44="",H44=""),"",O44-H44) | Q44: =IF(OR(O44="",H44="",H44=0),"",(O44-H44)/H44) | R44: =IF(B44="","",IF(M44="","Open","Closed"))
A45: 41 | H45: =IF(OR(E45="",F45=""),"",E45*F45+IF(G45="",0,G45)) | I45: =IFERROR(__xludf.DUMMYFUNCTION("IF(B45="""","""",IFERROR(GOOGLEFINANCE(UPPER(B45),""price""),""""))"),"") | J45: =IF(OR(E45="",I45="",R45="Closed"),"",E45*I45) | K45: =IF(OR(J45="",H45="",R45="Closed"),"",J45-H45) | L45: =IF(OR(J45="",H45="",H45=0,R45="Closed"),"",(J45-H45)/H45) | O45: =IF(OR(E45="",N45=""),"",E45*N45) | P45: =IF(OR(O45="",H45=""),"",O45-H45) | Q45: =IF(OR(O45="",H45="",H45=0),"",(O45-H45)/H45) | R45: =IF(B45="","",IF(M45="","Open","Closed"))
A46: 42 | H46: =IF(OR(E46="",F46=""),"",E46*F46+IF(G46="",0,G46)) | I46: =IFERROR(__xludf.DUMMYFUNCTION("IF(B46="""","""",IFERROR(GOOGLEFINANCE(UPPER(B46),""price""),""""))"),"") | J46: =IF(OR(E46="",I46="",R46="Closed"),"",E46*I46) | K46: =IF(OR(J46="",H46="",R46="Closed"),"",J46-H46) | L46: =IF(OR(J46="",H46="",H46=0,R46="Closed"),"",(J46-H46)/H46) | O46: =IF(OR(E46="",N46=""),"",E46*N46) | P46: =IF(OR(O46="",H46=""),"",O46-H46) | Q46: =IF(OR(O46="",H46="",H46=0),"",(O46-H46)/H46) | R46: =IF(B46="","",IF(M46="","Open","Closed"))
A47: 43 | H47: =IF(OR(E47="",F47=""),"",E47*F47+IF(G47="",0,G47)) | I47: =IFERROR(__xludf.DUMMYFUNCTION("IF(B47="""","""",IFERROR(GOOGLEFINANCE(UPPER(B47),""price""),""""))"),"") | J47: =IF(OR(E47="",I47="",R47="Closed"),"",E47*I47) | K47: =IF(OR(J47="",H47="",R47="Closed"),"",J47-H47) | L47: =IF(OR(J47="",H47="",H47=0,R47="Closed"),"",(J47-H47)/H47) | O47: =IF(OR(E47="",N47=""),"",E47*N47) | P47: =IF(OR(O47="",H47=""),"",O47-H47) | Q47: =IF(OR(O47="",H47="",H47=0),"",(O47-H47)/H47) | R47: =IF(B47="","",IF(M47="","Open","Closed"))
A48: 44 | H48: =IF(OR(E48="",F48=""),"",E48*F48+IF(G48="",0,G48)) | I48: =IFERROR(__xludf.DUMMYFUNCTION("IF(B48="""","""",IFERROR(GOOGLEFINANCE(UPPER(B48),""price""),""""))"),"") | J48: =IF(OR(E48="",I48="",R48="Closed"),"",E48*I48) | K48: =IF(OR(J48="",H48="",R48="Closed"),"",J48-H48) | L48: =IF(OR(J48="",H48="",H48=0,R48="Closed"),"",(J48-H48)/H48) | O48: =IF(OR(E48="",N48=""),"",E48*N48) | P48: =IF(OR(O48="",H48=""),"",O48-H48) | Q48: =IF(OR(O48="",H48="",H48=0),"",(O48-H48)/H48) | R48: =IF(B48="","",IF(M48="","Open","Closed"))
A49: 45 | H49: =IF(OR(E49="",F49=""),"",E49*F49+IF(G49="",0,G49)) | I49: =IFERROR(__xludf.DUMMYFUNCTION("IF(B49="""","""",IFERROR(GOOGLEFINANCE(UPPER(B49),""price""),""""))"),"") | J49: =IF(OR(E49="",I49="",R49="Closed"),"",E49*I49) | K49: =IF(OR(J49="",H49="",R49="Closed"),"",J49-H49) | L49: =IF(OR(J49="",H49="",H49=0,R49="Closed"),"",(J49-H49)/H49) | O49: =IF(OR(E49="",N49=""),"",E49*N49) | P49: =IF(OR(O49="",H49=""),"",O49-H49) | Q49: =IF(OR(O49="",H49="",H49=0),"",(O49-H49)/H49) | R49: =IF(B49="","",IF(M49="","Open","Closed"))
A50: 46 | H50: =IF(OR(E50="",F50=""),"",E50*F50+IF(G50="",0,G50)) | I50: =IFERROR(__xludf.DUMMYFUNCTION("IF(B50="""","""",IFERROR(GOOGLEFINANCE(UPPER(B50),""price""),""""))"),"") | J50: =IF(OR(E50="",I50="",R50="Closed"),"",E50*I50) | K50: =IF(OR(J50="",H50="",R50="Closed"),"",J50-H50) | L50: =IF(OR(J50="",H50="",H50=0,R50="Closed"),"",(J50-H50)/H50) | O50: =IF(OR(E50="",N50=""),"",E50*N50) | P50: =IF(OR(O50="",H50=""),"",O50-H50) | Q50: =IF(OR(O50="",H50="",H50=0),"",(O50-H50)/H50) | R50: =IF(B50="","",IF(M50="","Open","Closed"))
A51: 47 | H51: =IF(OR(E51="",F51=""),"",E51*F51+IF(G51="",0,G51)) | I51: =IFERROR(__xludf.DUMMYFUNCTION("IF(B51="""","""",IFERROR(GOOGLEFINANCE(UPPER(B51),""price""),""""))"),"") | J51: =IF(OR(E51="",I51="",R51="Closed"),"",E51*I51) | K51: =IF(OR(J51="",H51="",R51="Closed"),"",J51-H51) | L51: =IF(OR(J51="",H51="",H51=0,R51="Closed"),"",(J51-H51)/H51) | O51: =IF(OR(E51="",N51=""),"",E51*N51) | P51: =IF(OR(O51="",H51=""),"",O51-H51) | Q51: =IF(OR(O51="",H51="",H51=0),"",(O51-H51)/H51) | R51: =IF(B51="","",IF(M51="","Open","Closed"))
A52: 48 | H52: =IF(OR(E52="",F52=""),"",E52*F52+IF(G52="",0,G52)) | I52: =IFERROR(__xludf.DUMMYFUNCTION("IF(B52="""","""",IFERROR(GOOGLEFINANCE(UPPER(B52),""price""),""""))"),"") | J52: =IF(OR(E52="",I52="",R52="Closed"),"",E52*I52) | K52: =IF(OR(J52="",H52="",R52="Closed"),"",J52-H52) | L52: =IF(OR(J52="",H52="",H52=0,R52="Closed"),"",(J52-H52)/H52) | O52: =IF(OR(E52="",N52=""),"",E52*N52) | P52: =IF(OR(O52="",H52=""),"",O52-H52) | Q52: =IF(OR(O52="",H52="",H52=0),"",(O52-H52)/H52) | R52: =IF(B52="","",IF(M52="","Open","Closed"))
A53: 49 | H53: =IF(OR(E53="",F53=""),"",E53*F53+IF(G53="",0,G53)) | I53: =IFERROR(__xludf.DUMMYFUNCTION("IF(B53="""","""",IFERROR(GOOGLEFINANCE(UPPER(B53),""price""),""""))"),"") | J53: =IF(OR(E53="",I53="",R53="Closed"),"",E53*I53) | K53: =IF(OR(J53="",H53="",R53="Closed"),"",J53-H53) | L53: =IF(OR(J53="",H53="",H53=0,R53="Closed"),"",(J53-H53)/H53) | O53: =IF(OR(E53="",N53=""),"",E53*N53) | P53: =IF(OR(O53="",H53=""),"",O53-H53) | Q53: =IF(OR(O53="",H53="",H53=0),"",(O53-H53)/H53) | R53: =IF(B53="","",IF(M53="","Open","Closed"))
A54: 50 | H54: =IF(OR(E54="",F54=""),"",E54*F54+IF(G54="",0,G54)) | I54: =IFERROR(__xludf.DUMMYFUNCTION("IF(B54="""","""",IFERROR(GOOGLEFINANCE(UPPER(B54),""price""),""""))"),"") | J54: =IF(OR(E54="",I54="",R54="Closed"),"",E54*I54) | K54: =IF(OR(J54="",H54="",R54="Closed"),"",J54-H54) | L54: =IF(OR(J54="",H54="",H54=0,R54="Closed"),"",(J54-H54)/H54) | O54: =IF(OR(E54="",N54=""),"",E54*N54) | P54: =IF(OR(O54="",H54=""),"",O54-H54) | Q54: =IF(OR(O54="",H54="",H54=0),"",(O54-H54)/H54) | R54: =IF(B54="","",IF(M54="","Open","Closed"))
A55: 51 | H55: =IF(OR(E55="",F55=""),"",E55*F55+IF(G55="",0,G55)) | I55: =IFERROR(__xludf.DUMMYFUNCTION("IF(B55="""","""",IFERROR(GOOGLEFINANCE(UPPER(B55),""price""),""""))"),"") | J55: =IF(OR(E55="",I55="",R55="Closed"),"",E55*I55) | K55: =IF(OR(J55="",H55="",R55="Closed"),"",J55-H55) | L55: =IF(OR(J55="",H55="",H55=0,R55="Closed"),"",(J55-H55)/H55) | O55: =IF(OR(E55="",N55=""),"",E55*N55) | P55: =IF(OR(O55="",H55=""),"",O55-H55) | Q55: =IF(OR(O55="",H55="",H55=0),"",(O55-H55)/H55) | R55: =IF(B55="","",IF(M55="","Open","Closed"))
A56: 52 | H56: =IF(OR(E56="",F56=""),"",E56*F56+IF(G56="",0,G56)) | I56: =IFERROR(__xludf.DUMMYFUNCTION("IF(B56="""","""",IFERROR(GOOGLEFINANCE(UPPER(B56),""price""),""""))"),"") | J56: =IF(OR(E56="",I56="",R56="Closed"),"",E56*I56) | K56: =IF(OR(J56="",H56="",R56="Closed"),"",J56-H56) | L56: =IF(OR(J56="",H56="",H56=0,R56="Closed"),"",(J56-H56)/H56) | O56: =IF(OR(E56="",N56=""),"",E56*N56) | P56: =IF(OR(O56="",H56=""),"",O56-H56) | Q56: =IF(OR(O56="",H56="",H56=0),"",(O56-H56)/H56) | R56: =IF(B56="","",IF(M56="","Open","Closed"))
A57: 53 | H57: =IF(OR(E57="",F57=""),"",E57*F57+IF(G57="",0,G57)) | I57: =IFERROR(__xludf.DUMMYFUNCTION("IF(B57="""","""",IFERROR(GOOGLEFINANCE(UPPER(B57),""price""),""""))"),"") | J57: =IF(OR(E57="",I57="",R57="Closed"),"",E57*I57) | K57: =IF(OR(J57="",H57="",R57="Closed"),"",J57-H57) | L57: =IF(OR(J57="",H57="",H57=0,R57="Closed"),"",(J57-H57)/H57) | O57: =IF(OR(E57="",N57=""),"",E57*N57) | P57: =IF(OR(O57="",H57=""),"",O57-H57) | Q57: =IF(OR(O57="",H57="",H57=0),"",(O57-H57)/H57) | R57: =IF(B57="","",IF(M57="","Open","Closed"))
A58: 54 | H58: =IF(OR(E58="",F58=""),"",E58*F58+IF(G58="",0,G58)) | I58: =IFERROR(__xludf.DUMMYFUNCTION("IF(B58="""","""",IFERROR(GOOGLEFINANCE(UPPER(B58),""price""),""""))"),"") | J58: =IF(OR(E58="",I58="",R58="Closed"),"",E58*I58) | K58: =IF(OR(J58="",H58="",R58="Closed"),"",J58-H58) | L58: =IF(OR(J58="",H58="",H58=0,R58="Closed"),"",(J58-H58)/H58) | O58: =IF(OR(E58="",N58=""),"",E58*N58) | P58: =IF(OR(O58="",H58=""),"",O58-H58) | Q58: =IF(OR(O58="",H58="",H58=0),"",(O58-H58)/H58) | R58: =IF(B58="","",IF(M58="","Open","Closed"))
A59: 55 | H59: =IF(OR(E59="",F59=""),"",E59*F59+IF(G59="",0,G59)) | I59: =IFERROR(__xludf.DUMMYFUNCTION("IF(B59="""","""",IFERROR(GOOGLEFINANCE(UPPER(B59),""price""),""""))"),"") | J59: =IF(OR(E59="",I59="",R59="Closed"),"",E59*I59) | K59: =IF(OR(J59="",H59="",R59="Closed"),"",J59-H59) | L59: =IF(OR(J59="",H59="",H59=0,R59="Closed"),"",(J59-H59)/H59) | O59: =IF(OR(E59="",N59=""),"",E59*N59) | P59: =IF(OR(O59="",H59=""),"",O59-H59) | Q59: =IF(OR(O59="",H59="",H59=0),"",(O59-H59)/H59) | R59: =IF(B59="","",IF(M59="","Open","Closed"))
A60: 56 | H60: =IF(OR(E60="",F60=""),"",E60*F60+IF(G60="",0,G60)) | I60: =IFERROR(__xludf.DUMMYFUNCTION("IF(B60="""","""",IFERROR(GOOGLEFINANCE(UPPER(B60),""price""),""""))"),"") | J60: =IF(OR(E60="",I60="",R60="Closed"),"",E60*I60) | K60: =IF(OR(J60="",H60="",R60="Closed"),"",J60-H60) | L60: =IF(OR(J60="",H60="",H60=0,R60="Closed"),"",(J60-H60)/H60) | O60: =IF(OR(E60="",N60=""),"",E60*N60) | P60: =IF(OR(O60="",H60=""),"",O60-H60) | Q60: =IF(OR(O60="",H60="",H60=0),"",(O60-H60)/H60) | R60: =IF(B60="","",IF(M60="","Open","Closed"))
A61: 57 | H61: =IF(OR(E61="",F61=""),"",E61*F61+IF(G61="",0,G61)) | I61: =IFERROR(__xludf.DUMMYFUNCTION("IF(B61="""","""",IFERROR(GOOGLEFINANCE(UPPER(B61),""price""),""""))"),"") | J61: =IF(OR(E61="",I61="",R61="Closed"),"",E61*I61) | K61: =IF(OR(J61="",H61="",R61="Closed"),"",J61-H61) | L61: =IF(OR(J61="",H61="",H61=0,R61="Closed"),"",(J61-H61)/H61) | O61: =IF(OR(E61="",N61=""),"",E61*N61) | P61: =IF(OR(O61="",H61=""),"",O61-H61) | Q61: =IF(OR(O61="",H61="",H61=0),"",(O61-H61)/H61) | R61: =IF(B61="","",IF(M61="","Open","Closed"))
A62: 58 | H62: =IF(OR(E62="",F62=""),"",E62*F62+IF(G62="",0,G62)) | I62: =IFERROR(__xludf.DUMMYFUNCTION("IF(B62="""","""",IFERROR(GOOGLEFINANCE(UPPER(B62),""price""),""""))"),"") | J62: =IF(OR(E62="",I62="",R62="Closed"),"",E62*I62) | K62: =IF(OR(J62="",H62="",R62="Closed"),"",J62-H62) | L62: =IF(OR(J62="",H62="",H62=0,R62="Closed"),"",(J62-H62)/H62) | O62: =IF(OR(E62="",N62=""),"",E62*N62) | P62: =IF(OR(O62="",H62=""),"",O62-H62) | Q62: =IF(OR(O62="",H62="",H62=0),"",(O62-H62)/H62) | R62: =IF(B62="","",IF(M62="","Open","Closed"))
A63: 59 | H63: =IF(OR(E63="",F63=""),"",E63*F63+IF(G63="",0,G63)) | I63: =IFERROR(__xludf.DUMMYFUNCTION("IF(B63="""","""",IFERROR(GOOGLEFINANCE(UPPER(B63),""price""),""""))"),"") | J63: =IF(OR(E63="",I63="",R63="Closed"),"",E63*I63) | K63: =IF(OR(J63="",H63="",R63="Closed"),"",J63-H63) | L63: =IF(OR(J63="",H63="",H63=0,R63="Closed"),"",(J63-H63)/H63) | O63: =IF(OR(E63="",N63=""),"",E63*N63) | P63: =IF(OR(O63="",H63=""),"",O63-H63) | Q63: =IF(OR(O63="",H63="",H63=0),"",(O63-H63)/H63) | R63: =IF(B63="","",IF(M63="","Open","Closed"))
A64: 60 | H64: =IF(OR(E64="",F64=""),"",E64*F64+IF(G64="",0,G64)) | I64: =IFERROR(__xludf.DUMMYFUNCTION("IF(B64="""","""",IFERROR(GOOGLEFINANCE(UPPER(B64),""price""),""""))"),"") | J64: =IF(OR(E64="",I64="",R64="Closed"),"",E64*I64) | K64: =IF(OR(J64="",H64="",R64="Closed"),"",J64-H64) | L64: =IF(OR(J64="",H64="",H64=0,R64="Closed"),"",(J64-H64)/H64) | O64: =IF(OR(E64="",N64=""),"",E64*N64) | P64: =IF(OR(O64="",H64=""),"",O64-H64) | Q64: =IF(OR(O64="",H64="",H64=0),"",(O64-H64)/H64) | R64: =IF(B64="","",IF(M64="","Open","Closed"))
A65: 61 | H65: =IF(OR(E65="",F65=""),"",E65*F65+IF(G65="",0,G65)) | I65: =IFERROR(__xludf.DUMMYFUNCTION("IF(B65="""","""",IFERROR(GOOGLEFINANCE(UPPER(B65),""price""),""""))"),"") | J65: =IF(OR(E65="",I65="",R65="Closed"),"",E65*I65) | K65: =IF(OR(J65="",H65="",R65="Closed"),"",J65-H65) | L65: =IF(OR(J65="",H65="",H65=0,R65="Closed"),"",(J65-H65)/H65) | O65: =IF(OR(E65="",N65=""),"",E65*N65) | P65: =IF(OR(O65="",H65=""),"",O65-H65) | Q65: =IF(OR(O65="",H65="",H65=0),"",(O65-H65)/H65) | R65: =IF(B65="","",IF(M65="","Open","Closed"))
A66: 62 | H66: =IF(OR(E66="",F66=""),"",E66*F66+IF(G66="",0,G66)) | I66: =IFERROR(__xludf.DUMMYFUNCTION("IF(B66="""","""",IFERROR(GOOGLEFINANCE(UPPER(B66),""price""),""""))"),"") | J66: =IF(OR(E66="",I66="",R66="Closed"),"",E66*I66) | K66: =IF(OR(J66="",H66="",R66="Closed"),"",J66-H66) | L66: =IF(OR(J66="",H66="",H66=0,R66="Closed"),"",(J66-H66)/H66) | O66: =IF(OR(E66="",N66=""),"",E66*N66) | P66: =IF(OR(O66="",H66=""),"",O66-H66) | Q66: =IF(OR(O66="",H66="",H66=0),"",(O66-H66)/H66) | R66: =IF(B66="","",IF(M66="","Open","Closed"))
A67: 63 | H67: =IF(OR(E67="",F67=""),"",E67*F67+IF(G67="",0,G67)) | I67: =IFERROR(__xludf.DUMMYFUNCTION("IF(B67="""","""",IFERROR(GOOGLEFINANCE(UPPER(B67),""price""),""""))"),"") | J67: =IF(OR(E67="",I67="",R67="Closed"),"",E67*I67) | K67: =IF(OR(J67="",H67="",R67="Closed"),"",J67-H67) | L67: =IF(OR(J67="",H67="",H67=0,R67="Closed"),"",(J67-H67)/H67) | O67: =IF(OR(E67="",N67=""),"",E67*N67) | P67: =IF(OR(O67="",H67=""),"",O67-H67) | Q67: =IF(OR(O67="",H67="",H67=0),"",(O67-H67)/H67) | R67: =IF(B67="","",IF(M67="","Open","Closed"))
A68: 64 | H68: =IF(OR(E68="",F68=""),"",E68*F68+IF(G68="",0,G68)) | I68: =IFERROR(__xludf.DUMMYFUNCTION("IF(B68="""","""",IFERROR(GOOGLEFINANCE(UPPER(B68),""price""),""""))"),"") | J68: =IF(OR(E68="",I68="",R68="Closed"),"",E68*I68) | K68: =IF(OR(J68="",H68="",R68="Closed"),"",J68-H68) | L68: =IF(OR(J68="",H68="",H68=0,R68="Closed"),"",(J68-H68)/H68) | O68: =IF(OR(E68="",N68=""),"",E68*N68) | P68: =IF(OR(O68="",H68=""),"",O68-H68) | Q68: =IF(OR(O68="",H68="",H68=0),"",(O68-H68)/H68) | R68: =IF(B68="","",IF(M68="","Open","Closed"))
A69: 65 | H69: =IF(OR(E69="",F69=""),"",E69*F69+IF(G69="",0,G69)) | I69: =IFERROR(__xludf.DUMMYFUNCTION("IF(B69="""","""",IFERROR(GOOGLEFINANCE(UPPER(B69),""price""),""""))"),"") | J69: =IF(OR(E69="",I69="",R69="Closed"),"",E69*I69) | K69: =IF(OR(J69="",H69="",R69="Closed"),"",J69-H69) | L69: =IF(OR(J69="",H69="",H69=0,R69="Closed"),"",(J69-H69)/H69) | O69: =IF(OR(E69="",N69=""),"",E69*N69) | P69: =IF(OR(O69="",H69=""),"",O69-H69) | Q69: =IF(OR(O69="",H69="",H69=0),"",(O69-H69)/H69) | R69: =IF(B69="","",IF(M69="","Open","Closed"))
A70: 66 | H70: =IF(OR(E70="",F70=""),"",E70*F70+IF(G70="",0,G70)) | I70: =IFERROR(__xludf.DUMMYFUNCTION("IF(B70="""","""",IFERROR(GOOGLEFINANCE(UPPER(B70),""price""),""""))"),"") | J70: =IF(OR(E70="",I70="",R70="Closed"),"",E70*I70) | K70: =IF(OR(J70="",H70="",R70="Closed"),"",J70-H70) | L70: =IF(OR(J70="",H70="",H70=0,R70="Closed"),"",(J70-H70)/H70) | O70: =IF(OR(E70="",N70=""),"",E70*N70) | P70: =IF(OR(O70="",H70=""),"",O70-H70) | Q70: =IF(OR(O70="",H70="",H70=0),"",(O70-H70)/H70) | R70: =IF(B70="","",IF(M70="","Open","Closed"))
A71: 67 | H71: =IF(OR(E71="",F71=""),"",E71*F71+IF(G71="",0,G71)) | I71: =IFERROR(__xludf.DUMMYFUNCTION("IF(B71="""","""",IFERROR(GOOGLEFINANCE(UPPER(B71),""price""),""""))"),"") | J71: =IF(OR(E71="",I71="",R71="Closed"),"",E71*I71) | K71: =IF(OR(J71="",H71="",R71="Closed"),"",J71-H71) | L71: =IF(OR(J71="",H71="",H71=0,R71="Closed"),"",(J71-H71)/H71) | O71: =IF(OR(E71="",N71=""),"",E71*N71) | P71: =IF(OR(O71="",H71=""),"",O71-H71) | Q71: =IF(OR(O71="",H71="",H71=0),"",(O71-H71)/H71) | R71: =IF(B71="","",IF(M71="","Open","Closed"))
A72: 68 | H72: =IF(OR(E72="",F72=""),"",E72*F72+IF(G72="",0,G72)) | I72: =IFERROR(__xludf.DUMMYFUNCTION("IF(B72="""","""",IFERROR(GOOGLEFINANCE(UPPER(B72),""price""),""""))"),"") | J72: =IF(OR(E72="",I72="",R72="Closed"),"",E72*I72) | K72: =IF(OR(J72="",H72="",R72="Closed"),"",J72-H72) | L72: =IF(OR(J72="",H72="",H72=0,R72="Closed"),"",(J72-H72)/H72) | O72: =IF(OR(E72="",N72=""),"",E72*N72) | P72: =IF(OR(O72="",H72=""),"",O72-H72) | Q72: =IF(OR(O72="",H72="",H72=0),"",(O72-H72)/H72) | R72: =IF(B72="","",IF(M72="","Open","Closed"))
A73: 69 | H73: =IF(OR(E73="",F73=""),"",E73*F73+IF(G73="",0,G73)) | I73: =IFERROR(__xludf.DUMMYFUNCTION("IF(B73="""","""",IFERROR(GOOGLEFINANCE(UPPER(B73),""price""),""""))"),"") | J73: =IF(OR(E73="",I73="",R73="Closed"),"",E73*I73) | K73: =IF(OR(J73="",H73="",R73="Closed"),"",J73-H73) | L73: =IF(OR(J73="",H73="",H73=0,R73="Closed"),"",(J73-H73)/H73) | O73: =IF(OR(E73="",N73=""),"",E73*N73) | P73: =IF(OR(O73="",H73=""),"",O73-H73) | Q73: =IF(OR(O73="",H73="",H73=0),"",(O73-H73)/H73) | R73: =IF(B73="","",IF(M73="","Open","Closed"))
A74: 70 | H74: =IF(OR(E74="",F74=""),"",E74*F74+IF(G74="",0,G74)) | I74: =IFERROR(__xludf.DUMMYFUNCTION("IF(B74="""","""",IFERROR(GOOGLEFINANCE(UPPER(B74),""price""),""""))"),"") | J74: =IF(OR(E74="",I74="",R74="Closed"),"",E74*I74) | K74: =IF(OR(J74="",H74="",R74="Closed"),"",J74-H74) | L74: =IF(OR(J74="",H74="",H74=0,R74="Closed"),"",(J74-H74)/H74) | O74: =IF(OR(E74="",N74=""),"",E74*N74) | P74: =IF(OR(O74="",H74=""),"",O74-H74) | Q74: =IF(OR(O74="",H74="",H74=0),"",(O74-H74)/H74) | R74: =IF(B74="","",IF(M74="","Open","Closed"))
A75: 71 | H75: =IF(OR(E75="",F75=""),"",E75*F75+IF(G75="",0,G75)) | I75: =IFERROR(__xludf.DUMMYFUNCTION("IF(B75="""","""",IFERROR(GOOGLEFINANCE(UPPER(B75),""price""),""""))"),"") | J75: =IF(OR(E75="",I75="",R75="Closed"),"",E75*I75) | K75: =IF(OR(J75="",H75="",R75="Closed"),"",J75-H75) | L75: =IF(OR(J75="",H75="",H75=0,R75="Closed"),"",(J75-H75)/H75) | O75: =IF(OR(E75="",N75=""),"",E75*N75) | P75: =IF(OR(O75="",H75=""),"",O75-H75) | Q75: =IF(OR(O75="",H75="",H75=0),"",(O75-H75)/H75) | R75: =IF(B75="","",IF(M75="","Open","Closed"))
A76: 72 | H76: =IF(OR(E76="",F76=""),"",E76*F76+IF(G76="",0,G76)) | I76: =IFERROR(__xludf.DUMMYFUNCTION("IF(B76="""","""",IFERROR(GOOGLEFINANCE(UPPER(B76),""price""),""""))"),"") | J76: =IF(OR(E76="",I76="",R76="Closed"),"",E76*I76) | K76: =IF(OR(J76="",H76="",R76="Closed"),"",J76-H76) | L76: =IF(OR(J76="",H76="",H76=0,R76="Closed"),"",(J76-H76)/H76) | O76: =IF(OR(E76="",N76=""),"",E76*N76) | P76: =IF(OR(O76="",H76=""),"",O76-H76) | Q76: =IF(OR(O76="",H76="",H76=0),"",(O76-H76)/H76) | R76: =IF(B76="","",IF(M76="","Open","Closed"))
A77: 73 | H77: =IF(OR(E77="",F77=""),"",E77*F77+IF(G77="",0,G77)) | I77: =IFERROR(__xludf.DUMMYFUNCTION("IF(B77="""","""",IFERROR(GOOGLEFINANCE(UPPER(B77),""price""),""""))"),"") | J77: =IF(OR(E77="",I77="",R77="Closed"),"",E77*I77) | K77: =IF(OR(J77="",H77="",R77="Closed"),"",J77-H77) | L77: =IF(OR(J77="",H77="",H77=0,R77="Closed"),"",(J77-H77)/H77) | O77: =IF(OR(E77="",N77=""),"",E77*N77) | P77: =IF(OR(O77="",H77=""),"",O77-H77) | Q77: =IF(OR(O77="",H77="",H77=0),"",(O77-H77)/H77) | R77: =IF(B77="","",IF(M77="","Open","Closed"))
A78: 74 | H78: =IF(OR(E78="",F78=""),"",E78*F78+IF(G78="",0,G78)) | I78: =IFERROR(__xludf.DUMMYFUNCTION("IF(B78="""","""",IFERROR(GOOGLEFINANCE(UPPER(B78),""price""),""""))"),"") | J78: =IF(OR(E78="",I78="",R78="Closed"),"",E78*I78) | K78: =IF(OR(J78="",H78="",R78="Closed"),"",J78-H78) | L78: =IF(OR(J78="",H78="",H78=0,R78="Closed"),"",(J78-H78)/H78) | O78: =IF(OR(E78="",N78=""),"",E78*N78) | P78: =IF(OR(O78="",H78=""),"",O78-H78) | Q78: =IF(OR(O78="",H78="",H78=0),"",(O78-H78)/H78) | R78: =IF(B78="","",IF(M78="","Open","Closed"))
A79: 75 | H79: =IF(OR(E79="",F79=""),"",E79*F79+IF(G79="",0,G79)) | I79: =IFERROR(__xludf.DUMMYFUNCTION("IF(B79="""","""",IFERROR(GOOGLEFINANCE(UPPER(B79),""price""),""""))"),"") | J79: =IF(OR(E79="",I79="",R79="Closed"),"",E79*I79) | K79: =IF(OR(J79="",H79="",R79="Closed"),"",J79-H79) | L79: =IF(OR(J79="",H79="",H79=0,R79="Closed"),"",(J79-H79)/H79) | O79: =IF(OR(E79="",N79=""),"",E79*N79) | P79: =IF(OR(O79="",H79=""),"",O79-H79) | Q79: =IF(OR(O79="",H79="",H79=0),"",(O79-H79)/H79) | R79: =IF(B79="","",IF(M79="","Open","Closed"))
A80: 76 | H80: =IF(OR(E80="",F80=""),"",E80*F80+IF(G80="",0,G80)) | I80: =IFERROR(__xludf.DUMMYFUNCTION("IF(B80="""","""",IFERROR(GOOGLEFINANCE(UPPER(B80),""price""),""""))"),"") | J80: =IF(OR(E80="",I80="",R80="Closed"),"",E80*I80) | K80: =IF(OR(J80="",H80="",R80="Closed"),"",J80-H80) | L80: =IF(OR(J80="",H80="",H80=0,R80="Closed"),"",(J80-H80)/H80) | O80: =IF(OR(E80="",N80=""),"",E80*N80) | P80: =IF(OR(O80="",H80=""),"",O80-H80) | Q80: =IF(OR(O80="",H80="",H80=0),"",(O80-H80)/H80) | R80: =IF(B80="","",IF(M80="","Open","Closed"))
A81: 77 | H81: =IF(OR(E81="",F81=""),"",E81*F81+IF(G81="",0,G81)) | I81: =IFERROR(__xludf.DUMMYFUNCTION("IF(B81="""","""",IFERROR(GOOGLEFINANCE(UPPER(B81),""price""),""""))"),"") | J81: =IF(OR(E81="",I81="",R81="Closed"),"",E81*I81) | K81: =IF(OR(J81="",H81="",R81="Closed"),"",J81-H81) | L81: =IF(OR(J81="",H81="",H81=0,R81="Closed"),"",(J81-H81)/H81) | O81: =IF(OR(E81="",N81=""),"",E81*N81) | P81: =IF(OR(O81="",H81=""),"",O81-H81) | Q81: =IF(OR(O81="",H81="",H81=0),"",(O81-H81)/H81) | R81: =IF(B81="","",IF(M81="","Open","Closed"))
A82: 78 | H82: =IF(OR(E82="",F82=""),"",E82*F82+IF(G82="",0,G82)) | I82: =IFERROR(__xludf.DUMMYFUNCTION("IF(B82="""","""",IFERROR(GOOGLEFINANCE(UPPER(B82),""price""),""""))"),"") | J82: =IF(OR(E82="",I82="",R82="Closed"),"",E82*I82) | K82: =IF(OR(J82="",H82="",R82="Closed"),"",J82-H82) | L82: =IF(OR(J82="",H82="",H82=0,R82="Closed"),"",(J82-H82)/H82) | O82: =IF(OR(E82="",N82=""),"",E82*N82) | P82: =IF(OR(O82="",H82=""),"",O82-H82) | Q82: =IF(OR(O82="",H82="",H82=0),"",(O82-H82)/H82) | R82: =IF(B82="","",IF(M82="","Open","Closed"))
A83: 79 | H83: =IF(OR(E83="",F83=""),"",E83*F83+IF(G83="",0,G83)) | I83: =IFERROR(__xludf.DUMMYFUNCTION("IF(B83="""","""",IFERROR(GOOGLEFINANCE(UPPER(B83),""price""),""""))"),"") | J83: =IF(OR(E83="",I83="",R83="Closed"),"",E83*I83) | K83: =IF(OR(J83="",H83="",R83="Closed"),"",J83-H83) | L83: =IF(OR(J83="",H83="",H83=0,R83="Closed"),"",(J83-H83)/H83) | O83: =IF(OR(E83="",N83=""),"",E83*N83) | P83: =IF(OR(O83="",H83=""),"",O83-H83) | Q83: =IF(OR(O83="",H83="",H83=0),"",(O83-H83)/H83) | R83: =IF(B83="","",IF(M83="","Open","Closed"))
A84: 80 | H84: =IF(OR(E84="",F84=""),"",E84*F84+IF(G84="",0,G84)) | I84: =IFERROR(__xludf.DUMMYFUNCTION("IF(B84="""","""",IFERROR(GOOGLEFINANCE(UPPER(B84),""price""),""""))"),"") | J84: =IF(OR(E84="",I84="",R84="Closed"),"",E84*I84) | K84: =IF(OR(J84="",H84="",R84="Closed"),"",J84-H84) | L84: =IF(OR(J84="",H84="",H84=0,R84="Closed"),"",(J84-H84)/H84) | O84: =IF(OR(E84="",N84=""),"",E84*N84) | P84: =IF(OR(O84="",H84=""),"",O84-H84) | Q84: =IF(OR(O84="",H84="",H84=0),"",(O84-H84)/H84) | R84: =IF(B84="","",IF(M84="","Open","Closed"))
A85: 81 | H85: =IF(OR(E85="",F85=""),"",E85*F85+IF(G85="",0,G85)) | I85: =IFERROR(__xludf.DUMMYFUNCTION("IF(B85="""","""",IFERROR(GOOGLEFINANCE(UPPER(B85),""price""),""""))"),"") | J85: =IF(OR(E85="",I85="",R85="Closed"),"",E85*I85) | K85: =IF(OR(J85="",H85="",R85="Closed"),"",J85-H85) | L85: =IF(OR(J85="",H85="",H85=0,R85="Closed"),"",(J85-H85)/H85) | O85: =IF(OR(E85="",N85=""),"",E85*N85) | P85: =IF(OR(O85="",H85=""),"",O85-H85) | Q85: =IF(OR(O85="",H85="",H85=0),"",(O85-H85)/H85) | R85: =IF(B85="","",IF(M85="","Open","Closed"))
A86: 82 | H86: =IF(OR(E86="",F86=""),"",E86*F86+IF(G86="",0,G86)) | I86: =IFERROR(__xludf.DUMMYFUNCTION("IF(B86="""","""",IFERROR(GOOGLEFINANCE(UPPER(B86),""price""),""""))"),"") | J86: =IF(OR(E86="",I86="",R86="Closed"),"",E86*I86) | K86: =IF(OR(J86="",H86="",R86="Closed"),"",J86-H86) | L86: =IF(OR(J86="",H86="",H86=0,R86="Closed"),"",(J86-H86)/H86) | O86: =IF(OR(E86="",N86=""),"",E86*N86) | P86: =IF(OR(O86="",H86=""),"",O86-H86) | Q86: =IF(OR(O86="",H86="",H86=0),"",(O86-H86)/H86) | R86: =IF(B86="","",IF(M86="","Open","Closed"))
A87: 83 | H87: =IF(OR(E87="",F87=""),"",E87*F87+IF(G87="",0,G87)) | I87: =IFERROR(__xludf.DUMMYFUNCTION("IF(B87="""","""",IFERROR(GOOGLEFINANCE(UPPER(B87),""price""),""""))"),"") | J87: =IF(OR(E87="",I87="",R87="Closed"),"",E87*I87) | K87: =IF(OR(J87="",H87="",R87="Closed"),"",J87-H87) | L87: =IF(OR(J87="",H87="",H87=0,R87="Closed"),"",(J87-H87)/H87) | O87: =IF(OR(E87="",N87=""),"",E87*N87) | P87: =IF(OR(O87="",H87=""),"",O87-H87) | Q87: =IF(OR(O87="",H87="",H87=0),"",(O87-H87)/H87) | R87: =IF(B87="","",IF(M87="","Open","Closed"))
A88: 84 | H88: =IF(OR(E88="",F88=""),"",E88*F88+IF(G88="",0,G88)) | I88: =IFERROR(__xludf.DUMMYFUNCTION("IF(B88="""","""",IFERROR(GOOGLEFINANCE(UPPER(B88),""price""),""""))"),"") | J88: =IF(OR(E88="",I88="",R88="Closed"),"",E88*I88) | K88: =IF(OR(J88="",H88="",R88="Closed"),"",J88-H88) | L88: =IF(OR(J88="",H88="",H88=0,R88="Closed"),"",(J88-H88)/H88) | O88: =IF(OR(E88="",N88=""),"",E88*N88) | P88: =IF(OR(O88="",H88=""),"",O88-H88) | Q88: =IF(OR(O88="",H88="",H88=0),"",(O88-H88)/H88) | R88: =IF(B88="","",IF(M88="","Open","Closed"))
A89: 85 | H89: =IF(OR(E89="",F89=""),"",E89*F89+IF(G89="",0,G89)) | I89: =IFERROR(__xludf.DUMMYFUNCTION("IF(B89="""","""",IFERROR(GOOGLEFINANCE(UPPER(B89),""price""),""""))"),"") | J89: =IF(OR(E89="",I89="",R89="Closed"),"",E89*I89) | K89: =IF(OR(J89="",H89="",R89="Closed"),"",J89-H89) | L89: =IF(OR(J89="",H89="",H89=0,R89="Closed"),"",(J89-H89)/H89) | O89: =IF(OR(E89="",N89=""),"",E89*N89) | P89: =IF(OR(O89="",H89=""),"",O89-H89) | Q89: =IF(OR(O89="",H89="",H89=0),"",(O89-H89)/H89) | R89: =IF(B89="","",IF(M89="","Open","Closed"))
A90: 86 | H90: =IF(OR(E90="",F90=""),"",E90*F90+IF(G90="",0,G90)) | I90: =IFERROR(__xludf.DUMMYFUNCTION("IF(B90="""","""",IFERROR(GOOGLEFINANCE(UPPER(B90),""price""),""""))"),"") | J90: =IF(OR(E90="",I90="",R90="Closed"),"",E90*I90) | K90: =IF(OR(J90="",H90="",R90="Closed"),"",J90-H90) | L90: =IF(OR(J90="",H90="",H90=0,R90="Closed"),"",(J90-H90)/H90) | O90: =IF(OR(E90="",N90=""),"",E90*N90) | P90: =IF(OR(O90="",H90=""),"",O90-H90) | Q90: =IF(OR(O90="",H90="",H90=0),"",(O90-H90)/H90) | R90: =IF(B90="","",IF(M90="","Open","Closed"))
A91: 87 | H91: =IF(OR(E91="",F91=""),"",E91*F91+IF(G91="",0,G91)) | I91: =IFERROR(__xludf.DUMMYFUNCTION("IF(B91="""","""",IFERROR(GOOGLEFINANCE(UPPER(B91),""price""),""""))"),"") | J91: =IF(OR(E91="",I91="",R91="Closed"),"",E91*I91) | K91: =IF(OR(J91="",H91="",R91="Closed"),"",J91-H91) | L91: =IF(OR(J91="",H91="",H91=0,R91="Closed"),"",(J91-H91)/H91) | O91: =IF(OR(E91="",N91=""),"",E91*N91) | P91: =IF(OR(O91="",H91=""),"",O91-H91) | Q91: =IF(OR(O91="",H91="",H91=0),"",(O91-H91)/H91) | R91: =IF(B91="","",IF(M91="","Open","Closed"))
A92: 88 | H92: =IF(OR(E92="",F92=""),"",E92*F92+IF(G92="",0,G92)) | I92: =IFERROR(__xludf.DUMMYFUNCTION("IF(B92="""","""",IFERROR(GOOGLEFINANCE(UPPER(B92),""price""),""""))"),"") | J92: =IF(OR(E92="",I92="",R92="Closed"),"",E92*I92) | K92: =IF(OR(J92="",H92="",R92="Closed"),"",J92-H92) | L92: =IF(OR(J92="",H92="",H92=0,R92="Closed"),"",(J92-H92)/H92) | O92: =IF(OR(E92="",N92=""),"",E92*N92) | P92: =IF(OR(O92="",H92=""),"",O92-H92) | Q92: =IF(OR(O92="",H92="",H92=0),"",(O92-H92)/H92) | R92: =IF(B92="","",IF(M92="","Open","Closed"))
A93: 89 | H93: =IF(OR(E93="",F93=""),"",E93*F93+IF(G93="",0,G93)) | I93: =IFERROR(__xludf.DUMMYFUNCTION("IF(B93="""","""",IFERROR(GOOGLEFINANCE(UPPER(B93),""price""),""""))"),"") | J93: =IF(OR(E93="",I93="",R93="Closed"),"",E93*I93) | K93: =IF(OR(J93="",H93="",R93="Closed"),"",J93-H93) | L93: =IF(OR(J93="",H93="",H93=0,R93="Closed"),"",(J93-H93)/H93) | O93: =IF(OR(E93="",N93=""),"",E93*N93) | P93: =IF(OR(O93="",H93=""),"",O93-H93) | Q93: =IF(OR(O93="",H93="",H93=0),"",(O93-H93)/H93) | R93: =IF(B93="","",IF(M93="","Open","Closed"))
A94: 90 | H94: =IF(OR(E94="",F94=""),"",E94*F94+IF(G94="",0,G94)) | I94: =IFERROR(__xludf.DUMMYFUNCTION("IF(B94="""","""",IFERROR(GOOGLEFINANCE(UPPER(B94),""price""),""""))"),"") | J94: =IF(OR(E94="",I94="",R94="Closed"),"",E94*I94) | K94: =IF(OR(J94="",H94="",R94="Closed"),"",J94-H94) | L94: =IF(OR(J94="",H94="",H94=0,R94="Closed"),"",(J94-H94)/H94) | O94: =IF(OR(E94="",N94=""),"",E94*N94) | P94: =IF(OR(O94="",H94=""),"",O94-H94) | Q94: =IF(OR(O94="",H94="",H94=0),"",(O94-H94)/H94) | R94: =IF(B94="","",IF(M94="","Open","Closed"))
A95: 91 | H95: =IF(OR(E95="",F95=""),"",E95*F95+IF(G95="",0,G95)) | I95: =IFERROR(__xludf.DUMMYFUNCTION("IF(B95="""","""",IFERROR(GOOGLEFINANCE(UPPER(B95),""price""),""""))"),"") | J95: =IF(OR(E95="",I95="",R95="Closed"),"",E95*I95) | K95: =IF(OR(J95="",H95="",R95="Closed"),"",J95-H95) | L95: =IF(OR(J95="",H95="",H95=0,R95="Closed"),"",(J95-H95)/H95) | O95: =IF(OR(E95="",N95=""),"",E95*N95) | P95: =IF(OR(O95="",H95=""),"",O95-H95) | Q95: =IF(OR(O95="",H95="",H95=0),"",(O95-H95)/H95) | R95: =IF(B95="","",IF(M95="","Open","Closed"))
